Workbook

Sheet Resumen
C1: Tech | D1: Pharma | E1: Oil & Gas
B2: Porcentajes del balance general | C2: A | D2: B | E2: C | F2: D | H2: Balance Sheet | I2: O&G | J2: Biotech | K2: Tech | L2: Pharma
B3: Efectivo | C3: 5.13 | D3: 6.46 | E3: 2.34 | F3: 10.22 | H3: Cash & Cash Equivalents | I3: ='O&G>>'!C6 -> 0.044334162 | J3: ='Biotech>>'!C6 -> 0.26583922 | K3: ='Technology>>'!C6 -> 0.088860134 | L3: ='Pharma>>'!C6 -> 0.068277686
B4: Inversiones temporales | C4: 25.12 | D4: 0 | E4: 0 | F4: 2.74 | H4: Short-Term Investments - Total | I4: ='O&G>>'!C7 -> 0.00099538573 | J4: ='Biotech>>'!C7 -> 0.028661459 | K4: ='Technology>>'!C7 -> 0.10693765 | L4: ='Pharma>>'!C7 -> 0.038361788
B5: Cuentas por cobrar | C5: 18.6 | D5: 15.79 | E5: 3.06 | F5: 4.56 | H5: Trade Accounts & Trade Notes Receivable - Net | I5: ='O&G>>'!C8 -> 0.058588596 | J5: ='Biotech>>'!C8 -> 0.12034977 | K5: ='Technology>>'!C8 -> 0.08827602 | L5: ='Pharma>>'!C8 -> 0.11083459
B6: Inventarios | C6: 10.35 | D6: 12.22 | E6: 2.17 | F6: 7.36 | H6: Inventories - Total | I6: ='O&G>>'!C9 -> 0.05870483 | J6: ='Biotech>>'!C9 -> 0.032203793 | K6: ='Technology>>'!C9 -> 0.064861903 | L6: ='Pharma>>'!C9 -> 0.079086347
B7: Otros activos corrientes | C7: 1.54 | D7: 14.99 | E7: 2.92 | F7: 5.6 | H7: Other Current Assets | I7: ='O&G>>'!C10 -> 0.045459006 | J7: ='Biotech>>'!C10 -> 0.047883613 | K7: ='Technology>>'!C10 -> 0.039079975 | L7: ='Pharma>>'!C10 -> 0.072524795
B8: Total Activo Corriente/Total Activos | C8: =SUM(C3:C7) -> 60.74 | D8: =SUM(D3:D7) -> 49.46 | E8: =SUM(E3:E7) -> 10.49 | F8: =SUM(F3:F7) -> 30.48 | H8: Total Current Assets | I8: ='O&G>>'!C11 -> 0.20808198 | J8: ='Biotech>>'!C11 -> 0.49493785 | K8: ='Technology>>'!C11 -> 0.38801568 | L8: ='Pharma>>'!C11 -> 0.36908521
B10: PPE neto/Total Activos | C10: =C11-C12 -> 6.4 | D10: =D11-D12 -> 21.93 | E10: =E11-E12 -> 76.68 | F10: =F11-F12 -> 11.28
B11: PPE/Total Activos | C11: 9.59 | D11: 33.1 | E11: 164.71 | F11: 21.24 | H11: Investments - Long-Term | I11: ='O&G>>'!C13 -> 0.0033376611 | J11: ='Biotech>>'!C13 -> 0.004142382 | K11: ='Technology>>'!C13 -> 0.022570739 | L11: ='Pharma>>'!C13 -> 0.0088218137
B12: Depreciación Acumulada/Total Activos | C12: 3.19 | D12: 11.17 | E12: 88.03 | F12: 9.96 | H12: Property, Plant & Equipment - Net - Total | I12: ='O&G>>'!C14 -> 0.66171933 | J12: ='Biotech>>'!C14 -> 0.070967518 | K12: ='Technology>>'!C14 -> 0.29175239 | L12: ='Pharma>>'!C14 -> 0.19428293
B13: Inversiones a largo plazo/Total Activos | C13: 0 | D13: 2.49 | E13: 0 | F13: 4.02 | H13: Intangible Assets - Total - Net | I13: ='O&G>>'!C15 -> 0.0051757645 | J13: ='Biotech>>'!C15 -> 0.37396698 | K13: ='Technology>>'!C15 -> 0.239886 | L13: ='Pharma>>'!C15 -> 0.3067805
B14: Otros Activos a largo Plazo | C14: 32.86 | D14: 26.11 | E14: 12.84 | F14: 54.22 | H14: Other Non-Current Assets | I14: ='O&G>>'!C16 -> 0.12168527 | J14: ='Biotech>>'!C16 -> 0.055985269 | K14: ='Technology>>'!C16 -> 0.057775191 | L14: ='Pharma>>'!C16 -> 0.12102954
B15: Total Activo No Corriente/Total Activos | C15: =SUM(C13:C14,C10) -> 39.26 | D15: =SUM(D13:D14,D10) -> 50.53 | E15: =SUM(E13:E14,E10) -> 89.52 | F15: =SUM(F13:F14,F10) -> 69.52 | H15: Total Non-Current Assets | I15: ='O&G>>'!C17 -> 0.79191802 | J15: ='Biotech>>'!C17 -> 0.50506215 | K15: ='Technology>>'!C17 -> 0.61198432 | L15: ='Pharma>>'!C17 -> 0.63091479
B17: Total Activos/Total Activos | C17: =C15+C8 -> 100 | D17: =D15+D8 -> 99.99 | E17: =E15+E8 -> 100.01 | F17: =F15+F8 -> 100 | H17: Total Assets | I17: ='O&G>>'!C18 -> 1 | J17: ='Biotech>>'!C18 -> 1 | K17: ='Technology>>'!C18 -> 1 | L17: ='Pharma>>'!C18 -> 1
B19: Cuentas por pagar/Total Activo | C19: 4.74 | D19: 4.78 | E19: 3.9 | F19: 1.47 | H19: Trade Accounts & Trade Notes Payable - Short-Term | I19: ='O&G>>'!C20 -> 0.09140852 | J19: ='Biotech>>'!C20 -> 0.040048569 | K19: ='Technology>>'!C20 -> 0.038486151 | L19: ='Pharma>>'!C20 -> 0.04556699
B20: Obligaciones financieras CP/Total Activo | C20: 0.66 | D20: 1.65 | E20: 2.34 | F20: 0.27 | H20: Short-Term Debt & Current Portion of Long-Term Debt | I20: ='O&G>>'!C21 -> 0.012116478 | J20: ='Biotech>>'!C21 -> 0.027344937 | K20: ='Technology>>'!C21 -> 0.0093649772 | L20: ='Pharma>>'!C21 -> 0.030237708
B21: Otros pasivos corto plazo/Total Activo | C21: 10.14 | D21: 24.89 | E21: 4.96 | F21: 9.64 | H21: Other Current Liabilities | I21: ='O&G>>'!C22 -> 0.047882544 | J21: ='Biotech>>'!C22 -> 0.14517893 | K21: ='Technology>>'!C22 -> 0.09154847 | L21: ='Pharma>>'!C22 -> 0.19167829
B22: Pasivo corriente/Total Activo | C22: =SUM(C19:C21) -> 15.54 | D22: =SUM(D19:D21) -> 31.32 | E22: =SUM(E19:E21) -> 11.2 | F22: =SUM(F19:F21) -> 11.38 | H22: Total Current Liabilities | I22: ='O&G>>'!C23 -> 0.15140754 | J22: ='Biotech>>'!C23 -> 0.21257243 | K22: ='Technology>>'!C23 -> 0.1393996 | L22: ='Pharma>>'!C23 -> 0.26748299
B24: Obligaciones financieras LP/Total Activo | C24: 4.86 | D24: 37.35 | E24: 24.5 | F24: 22.34 | H24: Debt - Long-Term - Total | I24: ='O&G>>'!C25 -> 0.13748423 | J24: ='Biotech>>'!C25 -> 0.21819869 | K24: ='Technology>>'!C25 -> 0.20402456 | L24: ='Pharma>>'!C25 -> 0.29690847
B25: Otros pasivos LP/Total Activo | C25: 3.53 | D25: 7.74 | E25: 20.83 | F25: 4.27 | H25: Other Non-Current Liabilities | I25: ='O&G>>'!C26 -> 0.16745564 | J25: ='Biotech>>'!C26 -> 0.027724485 | K25: ='Technology>>'!C26 -> 0.047132057 | L25: ='Pharma>>'!C26 -> 0.084063527
B26: Pasivo No corriente/Total Activo | C26: =SUM(C24:C25) -> 8.39 | D26: =SUM(D24:D25) -> 45.09 | E26: =SUM(E24:E25) -> 45.33 | F26: =SUM(F24:F25) -> 26.61 | H26: Total Non-Current Liabilities | I26: ='O&G>>'!C27 -> 0.30493988 | J26: ='Biotech>>'!C27 -> 0.24592318 | K26: ='Technology>>'!C27 -> 0.25115662 | L26: ='Pharma>>'!C27 -> 0.380972
B28: Total pasivo/Total Activo | C28: =SUM(C26+C22) -> 23.93 | D28: =SUM(D26+D22) -> 76.41 | E28: =SUM(E26+E22) -> 56.53 | F28: =SUM(F26+F22) -> 37.99 | H28: Total Liabilities | I28: ='O&G>>'!C28 -> 0.45634742 | J28: ='Biotech>>'!C28 -> 0.45849561 | K28: ='Technology>>'!C28 -> 0.39055622 | L28: ='Pharma>>'!C28 -> 0.64845499
B30: Acciones Preferenciales/Total Activo | C30: 0 | D30: 0 | E30: 10.59 | F30: 0
B31: Interes Minoritario/Total Activo | C31: 0 | D31: 0 | E31: 0.67 | F31: 0 | H31: Common Equity - Total | I31: ='O&G>>'!C30 -> 0.52278681 | J31: ='Biotech>>'!C30 -> 0.54044421 | K31: ='Technology>>'!C30 -> 0.59516121 | L31: ='Pharma>>'!C30 -> 0.34131888
B32: Capital suscrito/Total Activo | C32: 76.06 | D32: 23.59 | E32: 32.21 | F32: 62.01 | H32: Other Shareholders' Equity | I32: ='O&G>>'!C31 -> 0.020865768 | J32: ='Biotech>>'!C31 -> 0.0010603126 | K32: ='Technology>>'!C31 -> 0.014282572 | L32: ='Pharma>>'!C31 -> 0.010226119
B33: Total patrimonio/Total Activo | C33: =SUM(C30:C32) -> 76.06 | D33: =SUM(D30:D32) -> 23.59 | E33: =SUM(E30:E32) -> 43.47 | F33: =SUM(F30:F32) -> 62.01 | H33: Total Shareholders' Equity | I33: ='O&G>>'!C32 -> 0.54365258 | J33: ='Biotech>>'!C32 -> 0.54150452 | K33: ='Technology>>'!C32 -> 0.60944378 | L33: ='Pharma>>'!C32 -> 0.35154499
B35: Total Pasivo y Patrimonio/Total Activos | C35: =C33+C28 -> 99.99 | D35: =D33+D28 -> 100 | E35: =E33+E28 -> 100 | F35: =F33+F28 -> 100 | H35: Total Liabilities & Equity | I35: ='O&G>>'!C33 -> 1 | J35: ='Biotech>>'!C33 -> 1.0000001 | K35: ='Technology>>'!C33 -> 1 | L35: ='Pharma>>'!C33 -> 0.99999998
B38: Indicadores Seleccionados | C38: A | D38: B | E38: C | F38: D | H38: Financial Statement
B39: ROE | C39: 1.0149 | D39: 1.0116 | E39: 0.0616 | F39: 0.0739 | H39: Revenue from Business Activities - Total | I39: ='O&G>>'!C37 -> 1 | J39: ='Biotech>>'!C37 -> 1 | K39: ='Technology>>'!C37 -> 1 | L39: ='Pharma>>'!C37 -> 1
B40: Margen operacional | C40: 0.6038 | D40: 0.4035 | E40: 0.1812 | F40: 0.1883 | H40: Cost of Sales | I40: ='O&G>>'!C38 -> 0.79133438 | J40: ='Biotech>>'!C38 -> 0.43841282 | K40: ='Technology>>'!C38 -> 0.46436961 | L40: ='Pharma>>'!C38 -> 0.24492516
B41: Prueba Acida | C41: 3.14 | D41: 0.71 | E41: 0.48 | F41: 1.54 | H41: Gross Profit - Industrials/Property - Total | I41: ='O&G>>'!C39 -> 0.20866562 | J41: ='Biotech>>'!C39 -> 0.56158718 | K41: ='Technology>>'!C39 -> 0.53563039 | L41: ='Pharma>>'!C39 -> 0.75507484
B42: Razon corriente | C42: 3.91 | D42: 1.58 | E42: 0.94 | F42: 2.68 | H42: Selling, General & Administrative Expenses excluding Research & Development Expenses | I42: ='O&G>>'!C40 -> 0.058566314 | J42: ='Biotech>>'!C40 -> 0.2347643 | K42: ='Technology>>'!C40 -> 0.053097745 | L42: ='Pharma>>'!C40 -> 0.20364667
B43: Días de inventario | C43: 91.72 | D43: 352.27 | E43: 0 | F43: 0 | H43: Research & Development Expense - Supplemental | I43: ='O&G>>'!C41 -> 0.0018574354 | J43: ='Biotech>>'!C41 -> 0.18178826 | K43: ='Technology>>'!C41 -> 0.15824983 | L43: ='Pharma>>'!C41 -> 0.19678567
B44: Días de cuentas por cobrar | C44: 51.86 | D44: 79.57 | E44: 45.76 | F44: 0 | H44: — | I44: ='O&G>>'!C42 -> 0.033082048 | J44: ='Biotech>>'!C42 -> -0.0051284893 | K44: ='Technology>>'!C42 -> 2.6753705e-05 | L44: ='Pharma>>'!C42 -> -0.013057139
B45: Rotación de activos totales | C45: 1.36 | D45: 0.68 | E45: 0.25 | F45: 0.34 | H45: Operating Expenses - Total | I45: ='O&G>>'!C43 -> 0.88484018 | J45: ='Biotech>>'!C43 -> 0.84983689 | K45: ='Technology>>'!C43 -> 0.67574394 | L45: ='Pharma>>'!C43 -> 0.63230036
B46: Rotación de activos fijos netos | C46: 20.25 | D46: 3.12 | E46: 0.33 | F46: 2.88 | H46: Earnings before Interest & Taxes (EBIT) | I46: ='O&G>>'!C44 -> 0.11515982 | J46: ='Biotech>>'!C44 -> 0.15016311 | K46: ='Technology>>'!C44 -> 0.32425606 | L46: ='Pharma>>'!C44 -> 0.36769964
H47: Depreciation, Depletion & Amortization - Total | I47: ='O&G>>'!C45 -> 0.1023705 | J47: ='Biotech>>'!C45 -> 0.037461328 | K47: ='Technology>>'!C45 -> 0.14946432 | L47: ='Pharma>>'!C45 -> 0.063811195
H48: Earnings before Interest, Taxes, Depreciation & Amortization (EBITDA) | I48: ='O&G>>'!C46 -> 0.21753032 | J48: ='Biotech>>'!C46 -> 0.18762444 | K48: ='Technology>>'!C46 -> 0.47372039 | L48: ='Pharma>>'!C46 -> 0.43151083
H49: Interest Expense - Net of (Interest Income) | I49: ='O&G>>'!C47 -> 0.0052725984 | J49: ='Biotech>>'!C47 -> 0.0061025372 | K49: ='Technology>>'!C47 -> 0.0085252794 | L49: ='Pharma>>'!C47 -> 0.011073026
H50: Other | I50: ='O&G>>'!C48 -> 0.0088828076 | J50: ='Biotech>>'!C48 -> -0.015519741 | K50: ='Technology>>'!C48 -> 0.0061192932 | L50: ='Pharma>>'!C48 -> -0.021467771
H51: Income before Taxes | I51: ='O&G>>'!C49 -> 0.11877003 | J51: ='Biotech>>'!C49 -> 0.12854083 | K51: ='Technology>>'!C49 -> 0.32185008 | L51: ='Pharma>>'!C49 -> 0.33515884
H52: Income Taxes | I52: ='O&G>>'!C50 -> 0.041898078 | J52: ='Biotech>>'!C50 -> 0.009833625 | K52: ='Technology>>'!C50 -> 0.034559032 | L52: ='Pharma>>'!C50 -> 0.055887626
H53: Other | I53: ='O&G>>'!C51 -> 0.0010036027 | J53: ='Biotech>>'!C51 -> 0.00032188841 | K53: ='Technology>>'!C51 -> -0.0013257236 | L53: ='Pharma>>'!C51 -> -0.0064235326
H54: Net Income after Minority Interest | I54: ='O&G>>'!C52 -> 0.077875556 | J54: ='Biotech>>'!C52 -> 0.1190291 | K54: ='Technology>>'!C52 -> 0.28596532 | L54: ='Pharma>>'!C52 -> 0.27284768
H57: Indicadores de Liquidez (Liquidity Ratios)
H58: Razón corriente (CR) | I58: ='O&G>>'!C56 -> 1.3124776 | J58: ='Biotech>>'!C56 -> 2.6198486 | K58: ='Technology>>'!C56 -> 2.6700583 | L58: ='Pharma>>'!C56 -> 1.3815302
H59: Prueba ácida (QR) | I59: ='O&G>>'!C57 -> 0.7458881 | J59: ='Biotech>>'!C57 -> 2.1949024 | K59: ='Technology>>'!C57 -> 1.940977 | L59: ='Pharma>>'!C57 -> 0.82294297
H60: Capital de trabajo neto (NWC) (USD mm) | I60: ='O&G>>'!C58 -> 7219.5 | J60: ='Biotech>>'!C58 -> 2050.0425 | K60: ='Technology>>'!C58 -> 31159.5 | L60: ='Pharma>>'!C58 -> 12657.082
H61: Administración de Activos (Efficiency Ratios)
H62: Rotación de inventario (ITR) | I62: ='O&G>>'!C60 -> 15.482208 | J62: ='Biotech>>'!C60 -> 0.55883642 | K62: ='Technology>>'!C60 -> 5.2367649 | L62: ='Pharma>>'!C60 -> 1.9519454
H63: Rotación de activos fijos netos (FAT) | I63: ='O&G>>'!C61 -> 1.635331 | J63: ='Biotech>>'!C61 -> 31.141838 | K63: ='Technology>>'!C61 -> 8.5126145 | L63: ='Pharma>>'!C61 -> 2.8380023
H64: Rotación de activos totales (ATR) | I64: ='O&G>>'!C62 -> 0.94346791 | J64: ='Biotech>>'!C62 -> 0.5456134 | K64: ='Technology>>'!C62 -> 0.56103517 | L64: ='Pharma>>'!C62 -> 0.5279056
H65: Días promedio de cartera (DSO) | I65: ='O&G>>'!C63 -> 30.351684 | J65: ='Biotech>>'!C63 -> 82.849007 | K65: ='Technology>>'!C63 -> 50.448262 | L65: ='Pharma>>'!C63 -> 75.707035
H66: Días promedio de inventario (DIO) | I66: ='O&G>>'!C64 -> 26.666694 | J66: ='Biotech>>'!C64 -> 178.89681 | K66: ='Technology>>'!C64 -> 101.99254 | L66: ='Pharma>>'!C64 -> 241.66918
H67: Periodo promedio de pago (DPO) | I67: ='O&G>>'!C65 -> 48.181355 | J67: ='Biotech>>'!C65 -> 186.24512 | K67: ='Technology>>'!C65 -> 64.056151 | L67: ='Pharma>>'!C65 -> 132.86021
H68: Ciclo operativo (OC) | I68: ='O&G>>'!C66 -> 57.018379 | J68: ='Biotech>>'!C66 -> 261.74582 | K68: ='Technology>>'!C66 -> 152.4408 | L68: ='Pharma>>'!C66 -> 317.37622
H69: Ciclo de efectivo (CC) | I69: ='O&G>>'!C67 -> 8.8370243 | J69: ='Biotech>>'!C67 -> 75.500691 | K69: ='Technology>>'!C67 -> 88.384649 | L69: ='Pharma>>'!C67 -> 184.51601
H70: Administración de Pasivos (Leverage Ratios)
H71: Nivel de endeudamiento (Debt to Assets) | I71: ='O&G>>'!C69 -> 0.45634742 | J71: ='Biotech>>'!C69 -> 0.45849561 | K71: ='Technology>>'!C69 -> 0.39055622 | L71: ='Pharma>>'!C69 -> 0.64845499
H72: Cobertura de intereses (Interest Coverage) | I72: ='O&G>>'!C70 -> 28.336329 | J72: ='Biotech>>'!C70 -> -8.6029145 | K72: ='Technology>>'!C70 -> -140.83219 | L72: ='Pharma>>'!C70 -> -59.979178
H73: Indicadores de Rentabilidad (Profitability Ratios)
H74: Margen neto (NPM) | I74: ='O&G>>'!C72 -> 0.077875556 | J74: ='Biotech>>'!C72 -> 0.1190291 | K74: ='Technology>>'!C72 -> 0.28596532 | L74: ='Pharma>>'!C72 -> 0.27284768
H75: Margen operacional (OM) | I75: ='O&G>>'!C73 -> 0.11515982 | J75: ='Biotech>>'!C73 -> 0.15016311 | K75: ='Technology>>'!C73 -> 0.32425606 | L75: ='Pharma>>'!C73 -> 0.36769964
H76: ROA | I76: ='O&G>>'!C74 -> 0.052050292 | J76: ='Biotech>>'!C74 -> 0.060840226 | K76: ='Technology>>'!C74 -> 0.22251887 | L76: ='Pharma>>'!C74 -> 0.1434418
H77: ROE | I77: ='O&G>>'!C75 -> 0.096076035 | J77: ='Biotech>>'!C75 -> 0.11796638 | K77: ='Technology>>'!C75 -> 0.33968609 | L77: ='Pharma>>'!C75 -> 0.44460154
H78: ROC | I78: ='O&G>>'!C76 -> 0.07713212 | J78: ='Biotech>>'!C76 -> 0.087902452 | K78: ='Technology>>'!C76 -> 0.27831607 | L78: ='Pharma>>'!C76 -> 0.24195464
H79: ROIC | I79: ='O&G>>'!C77 -> 0.067278452 | J79: ='Biotech>>'!C77 -> 0.15430129 | K79: ='Technology>>'!C77 -> 0.2919623 | L79: ='Pharma>>'!C77 -> 0.24662917
H80: ROCE | I80: ='O&G>>'!C78 -> 0.063296274 | J80: ='Biotech>>'!C78 -> 0.088143292 | K80: ='Technology>>'!C78 -> 0.26293342 | L80: ='Pharma>>'!C78 -> 0.22351693

Sheet O&G>>
C2: Average | D2: =L2 -> Conoco | E2: =M2 -> Chevron | F2: =N2 -> Exxon | G2: =O2 -> Valero | L2: Conoco | M2: Chevron | N2: Exxon | O2: Valero | R2: ICON | S2: ICON | T2: ICON
B4: Balance Sheet | C4: % | D4: % | E4: % | F4: % | G4: % | K4: Balance Sheet | L4: 2025 | M4: 2025 | N4: 2025 | O4: 2025 | Q4: Balance Sheet | R4: 2024 | S4: 2024 | T4: 2024
B6: Cash & Cash Equivalents | C6: =IFERROR(AVERAGE(D6:G6),0) -> 0.044334162 | D6: =IFERROR(L6/L$18,0) -> 0.053280739 | E6: =IFERROR(M6/M$18,0) -> 0.01942212 | F6: =IFERROR(N6/N$18,0) -> 0.023789478 | G6: =IFERROR(O6/O$18,0) -> 0.080844313 | K6: Cash & Cash Equivalents | L6: =SUMIF(INDIRECT("'"&L$2&"'!$A$1:$A$500"),$K6,INDIRECT("'"&L$2&"'!$C$1:$C$500")) -> 6497 | M6: =SUMIF(INDIRECT("'"&M$2&"'!$A$1:$A$500"),$K6,INDIRECT("'"&M$2&"'!$C$1:$C$500")) -> 6293 | N6: =SUMIF(INDIRECT("'"&N$2&"'!$A$1:$A$500"),$K6,INDIRECT("'"&N$2&"'!$C$1:$C$500")) -> 10681 | O6: =SUMIF(INDIRECT("'"&O$2&"'!$A$1:$A$500"),$K6,INDIRECT("'"&O$2&"'!$C$1:$C$500")) -> 4688 | Q6: Cash & Cash Equivalents | R6: =SUMIF(INDIRECT("'"&R$2&"'!$A$1:$A$400"),$K6,INDIRECT("'"&R$2&"'!$b$1:$b$400")) -> 538.79 | S6: =SUMIF(INDIRECT("'"&S$2&"'!$A$1:$A$400"),$K6,INDIRECT("'"&S$2&"'!$b$1:$b$400")) -> 538.79 | T6: =SUMIF(INDIRECT("'"&T$2&"'!$A$1:$A$400"),$K6,INDIRECT("'"&T$2&"'!$b$1:$b$400")) -> 538.79
B7: Short-Term Investments - Total | C7: =IFERROR(AVERAGE(D7:G7),0) -> 0.00099538573 | D7: =IFERROR(L7/L$18,0) -> 0.0039691977 | E7: =IFERROR(M7/M$18,0) -> 1.2345222e-05 | F7: =IFERROR(N7/N$18,0) -> 0 | G7: =IFERROR(O7/O$18,0) -> 0 | K7: Short-Term Investments - Total | L7: =SUMIF(INDIRECT("'"&L$2&"'!$A$1:$A$500"),$K7,INDIRECT("'"&L$2&"'!$C$1:$C$500")) -> 484 | M7: =SUMIF(INDIRECT("'"&M$2&"'!$A$1:$A$500"),$K7,INDIRECT("'"&M$2&"'!$C$1:$C$500")) -> 4 | N7: =SUMIF(INDIRECT("'"&N$2&"'!$A$1:$A$500"),$K7,INDIRECT("'"&N$2&"'!$C$1:$C$500")) -> 0 | O7: =SUMIF(INDIRECT("'"&O$2&"'!$A$1:$A$500"),$K7,INDIRECT("'"&O$2&"'!$C$1:$C$500")) -> 0 | Q7: Short-Term Investments - Total | R7: =SUMIF(INDIRECT("'"&R$2&"'!$A$1:$A$400"),$K7,INDIRECT("'"&R$2&"'!$b$1:$b$400")) -> 0 | S7: =SUMIF(INDIRECT("'"&S$2&"'!$A$1:$A$400"),$K7,INDIRECT("'"&S$2&"'!$b$1:$b$400")) -> 0 | T7: =SUMIF(INDIRECT("'"&T$2&"'!$A$1:$A$400"),$K7,INDIRECT("'"&T$2&"'!$b$1:$b$400")) -> 0
B8: Trade Accounts & Trade Notes Receivable - Net | C8: =IFERROR(AVERAGE(D8:G8),0) -> 0.058588596 | D8: =IFERROR(L8/L$18,0) -> 0.047671377 | E8: =IFERROR(M8/M$18,0) -> 0.055784971 | F8: =IFERROR(N8/N$18,0) -> 0.079611564 | G8: =IFERROR(O8/O$18,0) -> 0.051286473 | K8: Trade Accounts & Trade Notes Receivable - Net | L8: =SUMIF(INDIRECT("'"&L$2&"'!$A$1:$A$500"),$K8,INDIRECT("'"&L$2&"'!$C$1:$C$500")) -> 5813 | M8: =SUMIF(INDIRECT("'"&M$2&"'!$A$1:$A$500"),$K8,INDIRECT("'"&M$2&"'!$C$1:$C$500")) -> 18075 | N8: =SUMIF(INDIRECT("'"&N$2&"'!$A$1:$A$500"),$K8,INDIRECT("'"&N$2&"'!$C$1:$C$500")) -> 35744 | O8: =SUMIF(INDIRECT("'"&O$2&"'!$A$1:$A$500"),$K8,INDIRECT("'"&O$2&"'!$C$1:$C$500")) -> 2974 | Q8: Trade Accounts & Trade Notes Receivable - Net | R8: =SUMIF(INDIRECT("'"&R$2&"'!$A$1:$A$400"),$K8,INDIRECT("'"&R$2&"'!$b$1:$b$400")) -> 1392.76 | S8: =SUMIF(INDIRECT("'"&S$2&"'!$A$1:$A$400"),$K8,INDIRECT("'"&S$2&"'!$b$1:$b$400")) -> 1392.76 | T8: =SUMIF(INDIRECT("'"&T$2&"'!$A$1:$A$400"),$K8,INDIRECT("'"&T$2&"'!$b$1:$b$400")) -> 1392.76
B9: Inventories - Total | C9: =IFERROR(AVERAGE(D9:G9),0) -> 0.05870483 | D9: =IFERROR(L9/L$18,0) -> 0.015360139 | E9: =IFERROR(M9/M$18,0) -> 0.029971112 | F9: =IFERROR(N9/N$18,0) -> 0.058581674 | G9: =IFERROR(O9/O$18,0) -> 0.13090639 | K9: Inventories - Total | L9: =SUMIF(INDIRECT("'"&L$2&"'!$A$1:$A$500"),$K9,INDIRECT("'"&L$2&"'!$C$1:$C$500")) -> 1873 | M9: =SUMIF(INDIRECT("'"&M$2&"'!$A$1:$A$500"),$K9,INDIRECT("'"&M$2&"'!$C$1:$C$500")) -> 9711 | N9: =SUMIF(INDIRECT("'"&N$2&"'!$A$1:$A$500"),$K9,INDIRECT("'"&N$2&"'!$C$1:$C$500")) -> 26302 | O9: =SUMIF(INDIRECT("'"&O$2&"'!$A$1:$A$500"),$K9,INDIRECT("'"&O$2&"'!$C$1:$C$500")) -> 7591 | Q9: Inventories - Total | R9: =SUMIF(INDIRECT("'"&R$2&"'!$A$1:$A$400"),$K9,INDIRECT("'"&R$2&"'!$b$1:$b$400")) -> 0 | S9: =SUMIF(INDIRECT("'"&S$2&"'!$A$1:$A$400"),$K9,INDIRECT("'"&S$2&"'!$b$1:$b$400")) -> 0 | T9: =SUMIF(INDIRECT("'"&T$2&"'!$A$1:$A$400"),$K9,INDIRECT("'"&T$2&"'!$b$1:$b$400")) -> 0
B10: Other Current Assets | C10: =IFERROR(AVERAGE(D10:G10),0) -> 0.045459006 | D10: =IFERROR(L10/L$18,0) -> 0.0070937108 | E10: =IFERROR(M10/M$18,0) -> 0.013792699 | F10: =IFERROR(N10/N$18,0) -> 0.023731569 | G10: =IFERROR(O10/O$18,0) -> 0.13721805 | K10: Other Current Assets | L10: =SUMIF(INDIRECT("'"&L$2&"'!$A$1:$A$500"),$K11,INDIRECT("'"&L$2&"'!$C$1:$C$500"))-SUM(L6:L9) -> 865 | M10: =SUMIF(INDIRECT("'"&M$2&"'!$A$1:$A$500"),$K11,INDIRECT("'"&M$2&"'!$C$1:$C$500"))-SUM(M6:M9) -> 4469 | N10: =SUMIF(INDIRECT("'"&N$2&"'!$A$1:$A$500"),$K11,INDIRECT("'"&N$2&"'!$C$1:$C$500"))-SUM(N6:N9) -> 10655 | O10: =SUMIF(INDIRECT("'"&O$2&"'!$A$1:$A$500"),$K11,INDIRECT("'"&O$2&"'!$C$1:$C$500"))-SUM(O6:O9) -> 7957 | Q10: Other Current Assets | R10: =R11-R6-R7-R8-R9 -> 1343.62 | S10: =S11-S6-S7-S8-S9 -> 1343.62 | T10: =T11-T6-T7-T8-T9 -> 1343.62
B11: Total Current Assets | C11: =IFERROR(AVERAGE(D11:G11),0) -> 0.20808198 | D11: =IFERROR(L11/L$18,0) -> 0.12737516 | E11: =IFERROR(M11/M$18,0) -> 0.11898325 | F11: =IFERROR(N11/N$18,0) -> 0.18571429 | G11: =IFERROR(O11/O$18,0) -> 0.40025523 | K11: Total Current Assets | L11: =SUM(L6:L10) -> 15532 | M11: =SUM(M6:M10) -> 38552 | N11: =SUM(N6:N10) -> 83382 | O11: =SUM(O6:O10) -> 23210 | Q11: Total Current Assets | R11: =SUMIF(INDIRECT("'"&R$2&"'!$A$1:$A$400"),$K11,INDIRECT("'"&R$2&"'!$b$1:$b$400")) -> 3275.17 | S11: =SUMIF(INDIRECT("'"&S$2&"'!$A$1:$A$400"),$K11,INDIRECT("'"&S$2&"'!$b$1:$b$400")) -> 3275.17 | T11: =SUMIF(INDIRECT("'"&T$2&"'!$A$1:$A$400"),$K11,INDIRECT("'"&T$2&"'!$b$1:$b$400")) -> 3275.17
K12: Check Current Assets | L12: =ROUND(SUMIF(INDIRECT("'"&L$2&"'!$A$1:$A$500"),$K$11,INDIRECT("'"&L$2&"'!$C$1:$C$500"))-L11,2) -> 0 | M12: =ROUND(SUMIF(INDIRECT("'"&M$2&"'!$A$1:$A$500"),$K$11,INDIRECT("'"&M$2&"'!$C$1:$C$500"))-M11,2) -> 0 | N12: =ROUND(SUMIF(INDIRECT("'"&N$2&"'!$A$1:$A$500"),$K$11,INDIRECT("'"&N$2&"'!$C$1:$C$500"))-N11,2) -> 0 | O12: =ROUND(SUMIF(INDIRECT("'"&O$2&"'!$A$1:$A$500"),$K$11,INDIRECT("'"&O$2&"'!$C$1:$C$500"))-O11,2) -> 0
B13: Investments - Long-Term | C13: =IFERROR(AVERAGE(D13:G13),0) -> 0.0033376611 | D13: =IFERROR(L13/L$18,0) -> 0.010185421 | E13: =IFERROR(M13/M$18,0) -> 0.0025616335 | F13: =IFERROR(N13/N$18,0) -> 0.00060359036 | G13: =IFERROR(O13/O$18,0) -> 0 | K13: Investments - Long-Term | L13: =SUMIF(INDIRECT("'"&L$2&"'!$A$1:$A$500"),$K13,INDIRECT("'"&L$2&"'!$C$1:$C$500")) -> 1242 | M13: =SUMIF(INDIRECT("'"&M$2&"'!$A$1:$A$500"),$K13,INDIRECT("'"&M$2&"'!$C$1:$C$500")) -> 830 | N13: =SUMIF(INDIRECT("'"&N$2&"'!$A$1:$A$500"),$K13,INDIRECT("'"&N$2&"'!$C$1:$C$500")) -> 271 | O13: =SUMIF(INDIRECT("'"&O$2&"'!$A$1:$A$500"),$K13,INDIRECT("'"&O$2&"'!$C$1:$C$500")) -> 0 | Q13: Investments - Long-Term | R13: =SUMIF(INDIRECT("'"&R$2&"'!$A$1:$A$400"),$K13,INDIRECT("'"&R$2&"'!$b$1:$b$400")) -> 0 | S13: =SUMIF(INDIRECT("'"&S$2&"'!$A$1:$A$400"),$K13,INDIRECT("'"&S$2&"'!$b$1:$b$400")) -> 0 | T13: =SUMIF(INDIRECT("'"&T$2&"'!$A$1:$A$400"),$K13,INDIRECT("'"&T$2&"'!$b$1:$b$400")) -> 0
B14: Property, Plant & Equipment - Net - Total | C14: =IFERROR(AVERAGE(D14:G14),0) -> 0.66171933 | D14: =IFERROR(L14/L$18,0) -> 0.7724272 | E14: =IFERROR(M14/M$18,0) -> 0.6968353 | F14: =IFERROR(N14/N$18,0) -> 0.68287452 | G14: =IFERROR(O14/O$18,0) -> 0.49474029 | K14: Property, Plant & Equipment - Net - Total | L14: =SUMIF(INDIRECT("'"&L$2&"'!$A$1:$A$500"),$K14,INDIRECT("'"&L$2&"'!$C$1:$C$500")) -> 94189 | M14: =SUMIF(INDIRECT("'"&M$2&"'!$A$1:$A$500"),$K14,INDIRECT("'"&M$2&"'!$C$1:$C$500")) -> 225783 | N14: =SUMIF(INDIRECT("'"&N$2&"'!$A$1:$A$500"),$K14,INDIRECT("'"&N$2&"'!$C$1:$C$500")) -> 306597 | O14: =SUMIF(INDIRECT("'"&O$2&"'!$A$1:$A$500"),$K14,INDIRECT("'"&O$2&"'!$C$1:$C$500")) -> 28689 | Q14: Property, Plant & Equipment - Net - Total | R14: =SUMIF(INDIRECT("'"&R$2&"'!$A$1:$A$400"),$K14,INDIRECT("'"&R$2&"'!$b$1:$b$400")) -> 530.48 | S14: =SUMIF(INDIRECT("'"&S$2&"'!$A$1:$A$400"),$K14,INDIRECT("'"&S$2&"'!$b$1:$b$400")) -> 530.48 | T14: =SUMIF(INDIRECT("'"&T$2&"'!$A$1:$A$400"),$K14,INDIRECT("'"&T$2&"'!$b$1:$b$400")) -> 530.48
B15: Intangible Assets - Total - Net | C15: =IFERROR(AVERAGE(D15:G15),0) -> 0.0051757645 | D15: =IFERROR(L15/L$18,0) -> 0 | E15: =IFERROR(M15/M$18,0) -> 0.014098243 | F15: =IFERROR(N15/N$18,0) -> 0 | G15: =IFERROR(O15/O$18,0) -> 0.0066048148 | K15: Intangible Assets - Total - Net | L15: =SUMIF(INDIRECT("'"&L$2&"'!$A$1:$A$500"),$K15,INDIRECT("'"&L$2&"'!$C$1:$C$500")) -> 0 | M15: =SUMIF(INDIRECT("'"&M$2&"'!$A$1:$A$500"),$K15,INDIRECT("'"&M$2&"'!$C$1:$C$500")) -> 4568 | N15: =SUMIF(INDIRECT("'"&N$2&"'!$A$1:$A$500"),$K15,INDIRECT("'"&N$2&"'!$C$1:$C$500")) -> 0 | O15: =SUMIF(INDIRECT("'"&O$2&"'!$A$1:$A$500"),$K15,INDIRECT("'"&O$2&"'!$C$1:$C$500")) -> 383 | Q15: Intangible Assets - Total - Net | R15: =SUMIF(INDIRECT("'"&R$2&"'!$A$1:$A$400"),$K15,INDIRECT("'"&R$2&"'!$b$1:$b$400")) -> 12611.2 | S15: =SUMIF(INDIRECT("'"&S$2&"'!$A$1:$A$400"),$K15,INDIRECT("'"&S$2&"'!$b$1:$b$400")) -> 12611.2 | T15: =SUMIF(INDIRECT("'"&T$2&"'!$A$1:$A$400"),$K15,INDIRECT("'"&T$2&"'!$b$1:$b$400")) -> 12611.2
B16: Other Non-Current Assets | C16: =IFERROR(AVERAGE(D16:G16),0) -> 0.12168527 | D16: =IFERROR(L16/L$18,0) -> 0.090012219 | E16: =IFERROR(M16/M$18,0) -> 0.16752157 | F16: =IFERROR(N16/N$18,0) -> 0.13080761 | G16: =IFERROR(O16/O$18,0) -> 0.098399669 | K16: Other Non-Current Assets | L16: =SUMIF(INDIRECT("'"&L$2&"'!$A$1:$A$500"),$K17,INDIRECT("'"&L$2&"'!$C$1:$C$500"))-SUM(L12:L15) -> 10976 | M16: =SUMIF(INDIRECT("'"&M$2&"'!$A$1:$A$500"),$K17,INDIRECT("'"&M$2&"'!$C$1:$C$500"))-SUM(M12:M15) -> 54279 | N16: =SUMIF(INDIRECT("'"&N$2&"'!$A$1:$A$500"),$K17,INDIRECT("'"&N$2&"'!$C$1:$C$500"))-SUM(N12:N15) -> 58730 | O16: =SUMIF(INDIRECT("'"&O$2&"'!$A$1:$A$500"),$K17,INDIRECT("'"&O$2&"'!$C$1:$C$500"))-SUM(O12:O15) -> 5706 | Q16: Other Non-Current Assets | R16: =R17-R13-R14-R15 -> 217.97 | S16: =S17-S13-S14-S15 -> 217.97 | T16: =T17-T13-T14-T15 -> 217.97
B17: Total Non-Current Assets | C17: =IFERROR(AVERAGE(D17:G17),0) -> 0.79191802 | D17: =IFERROR(L17/L$18,0) -> 0.87262484 | E17: =IFERROR(M17/M$18,0) -> 0.88101675 | F17: =IFERROR(N17/N$18,0) -> 0.81428571 | G17: =IFERROR(O17/O$18,0) -> 0.59974477 | K17: Total Non-Current Assets | L17: =SUM(L13:L16) -> 106407 | M17: =SUM(M13:M16) -> 285460 | N17: =SUM(N13:N16) -> 365598 | O17: =SUM(O13:O16) -> 34778 | Q17: Total Non-Current Assets | R17: =SUMIF(INDIRECT("'"&R$2&"'!$A$1:$A$400"),$K17,INDIRECT("'"&R$2&"'!$b$1:$b$400")) -> 13359.65 | S17: =SUMIF(INDIRECT("'"&S$2&"'!$A$1:$A$400"),$K17,INDIRECT("'"&S$2&"'!$b$1:$b$400")) -> 13359.65 | T17: =SUMIF(INDIRECT("'"&T$2&"'!$A$1:$A$400"),$K17,INDIRECT("'"&T$2&"'!$b$1:$b$400")) -> 13359.65
B18: Total Assets | C18: =IFERROR(AVERAGE(D18:G18),0) -> 1 | D18: =IFERROR(L18/L$18,0) -> 1 | E18: =IFERROR(M18/M$18,0) -> 1 | F18: =IFERROR(N18/N$18,0) -> 1 | G18: =IFERROR(O18/O$18,0) -> 1 | K18: Total Assets | L18: =L17+L11 -> 121939 | M18: =M17+M11 -> 324012 | N18: =N17+N11 -> 448980 | O18: =O17+O11 -> 57988 | Q18: Total Assets | R18: =SUMIF(INDIRECT("'"&R$2&"'!$A$1:$A$400"),$K18,INDIRECT("'"&R$2&"'!$b$1:$b$400")) -> 16634.82 | S18: =SUMIF(INDIRECT("'"&S$2&"'!$A$1:$A$400"),$K18,INDIRECT("'"&S$2&"'!$b$1:$b$400")) -> 16634.82 | T18: =SUMIF(INDIRECT("'"&T$2&"'!$A$1:$A$400"),$K18,INDIRECT("'"&T$2&"'!$b$1:$b$400")) -> 16634.82
K19: Check Total Assets | L19: =ROUND(SUMIF(INDIRECT("'"&L$2&"'!$A$1:$A$500"),$K$18,INDIRECT("'"&L$2&"'!$C$1:$C$500"))-L18,2) -> 0 | M19: =ROUND(SUMIF(INDIRECT("'"&M$2&"'!$A$1:$A$500"),$K$18,INDIRECT("'"&M$2&"'!$C$1:$C$500"))-M18,2) -> 0 | N19: =ROUND(SUMIF(INDIRECT("'"&N$2&"'!$A$1:$A$500"),$K$18,INDIRECT("'"&N$2&"'!$C$1:$C$500"))-N18,2) -> 0 | O19: =ROUND(SUMIF(INDIRECT("'"&O$2&"'!$A$1:$A$500"),$K$18,INDIRECT("'"&O$2&"'!$C$1:$C$500"))-O18,2) -> 0
B20: Trade Accounts & Trade Notes Payable - Short-Term | C20: =IFERROR(AVERAGE(D20:G20),0) -> 0.09140852 | D20: =IFERROR(L20/L$18,0) -> 0.050992709 | E20: =IFERROR(M20/M$18,0) -> 0.059503969 | F20: =IFERROR(N20/N$18,0) -> 0.080290882 | G20: =IFERROR(O20/O$18,0) -> 0.17484652 | K20: Trade Accounts & Trade Notes Payable - Short-Term | L20: =SUMIF(INDIRECT("'"&L$2&"'!$A$1:$A$500"),$K20,INDIRECT("'"&L$2&"'!$C$1:$C$500")) -> 6218 | M20: =SUMIF(INDIRECT("'"&M$2&"'!$A$1:$A$500"),$K20,INDIRECT("'"&M$2&"'!$C$1:$C$500")) -> 19280 | N20: =SUMIF(INDIRECT("'"&N$2&"'!$A$1:$A$500"),$K20,INDIRECT("'"&N$2&"'!$C$1:$C$500")) -> 36049 | O20: =SUMIF(INDIRECT("'"&O$2&"'!$A$1:$A$500"),$K20,INDIRECT("'"&O$2&"'!$C$1:$C$500")) -> 10139 | Q20: Trade Accounts & Trade Notes Payable - Short-Term | R20: =SUMIF(INDIRECT("'"&R$2&"'!$A$1:$A$400"),$K20,INDIRECT("'"&R$2&"'!$b$1:$b$400")) -> 173.03 | S20: =SUMIF(INDIRECT("'"&S$2&"'!$A$1:$A$400"),$K20,INDIRECT("'"&S$2&"'!$b$1:$b$400")) -> 173.03 | T20: =SUMIF(INDIRECT("'"&T$2&"'!$A$1:$A$400"),$K20,INDIRECT("'"&T$2&"'!$b$1:$b$400")) -> 173.03
B21: Short-Term Debt & Current Portion of Long-Term Debt | C21: =IFERROR(AVERAGE(D21:G21),0) -> 0.012116478 | D21: =IFERROR(L21/L$18,0) -> 0.0083648382 | E21: =IFERROR(M21/M$18,0) -> 0.0030153204 | F21: =IFERROR(N21/N$18,0) -> 0.020720299 | G21: =IFERROR(O21/O$18,0) -> 0.016365455 | K21: Short-Term Debt & Current Portion of Long-Term Debt | L21: =SUMIF(INDIRECT("'"&L$2&"'!$A$1:$A$500"),$K21,INDIRECT("'"&L$2&"'!$C$1:$C$500")) -> 1020 | M21: =SUMIF(INDIRECT("'"&M$2&"'!$A$1:$A$500"),$K21,INDIRECT("'"&M$2&"'!$C$1:$C$500")) -> 977 | N21: =SUMIF(INDIRECT("'"&N$2&"'!$A$1:$A$500"),$K21,INDIRECT("'"&N$2&"'!$C$1:$C$500")) -> 9303 | O21: =SUMIF(INDIRECT("'"&O$2&"'!$A$1:$A$500"),$K21,INDIRECT("'"&O$2&"'!$C$1:$C$500")) -> 949 | Q21: Short-Term Debt & Current Portion of Long-Term Debt | R21: =SUMIF(INDIRECT("'"&R$2&"'!$A$1:$A$400"),$K21,INDIRECT("'"&R$2&"'!$b$1:$b$400")) -> 29.76 | S21: =SUMIF(INDIRECT("'"&S$2&"'!$A$1:$A$400"),$K21,INDIRECT("'"&S$2&"'!$b$1:$b$400")) -> 29.76 | T21: =SUMIF(INDIRECT("'"&T$2&"'!$A$1:$A$400"),$K21,INDIRECT("'"&T$2&"'!$b$1:$b$400")) -> 29.76
B22: Other Current Liabilities | C22: =IFERROR(AVERAGE(D22:G22),0) -> 0.047882544 | D22: =IFERROR(L22/L$18,0) -> 0.03882269 | E22: =IFERROR(M22/M$18,0) -> 0.04052319 | F22: =IFERROR(N22/N$18,0) -> 0.060087309 | G22: =IFERROR(O22/O$18,0) -> 0.052096986 | K22: Other Current Liabilities | L22: =SUMIF(INDIRECT("'"&L$2&"'!$A$1:$A$500"),$K23,INDIRECT("'"&L$2&"'!$C$1:$C$500"))-SUM(L20:L21) -> 4734 | M22: =SUMIF(INDIRECT("'"&M$2&"'!$A$1:$A$500"),$K23,INDIRECT("'"&M$2&"'!$C$1:$C$500"))-SUM(M20:M21) -> 13130 | N22: =SUMIF(INDIRECT("'"&N$2&"'!$A$1:$A$500"),$K23,INDIRECT("'"&N$2&"'!$C$1:$C$500"))-SUM(N20:N21) -> 26978 | O22: =SUMIF(INDIRECT("'"&O$2&"'!$A$1:$A$500"),$K23,INDIRECT("'"&O$2&"'!$C$1:$C$500"))-SUM(O20:O21) -> 3021 | Q22: Other Current Liabilities | R22: =R23-R20-R21 -> 2432.7 | S22: =S23-S20-S21 -> 2432.7 | T22: =T23-T20-T21 -> 2432.7
B23: Total Current Liabilities | C23: =IFERROR(AVERAGE(D23:G23),0) -> 0.15140754 | D23: =IFERROR(L23/L$18,0) -> 0.098180238 | E23: =IFERROR(M23/M$18,0) -> 0.10304248 | F23: =IFERROR(N23/N$18,0) -> 0.16109849 | G23: =IFERROR(O23/O$18,0) -> 0.24330896 | K23: Total Current Liabilities | L23: =SUM(L20:L22) -> 11972 | M23: =SUM(M20:M22) -> 33387 | N23: =SUM(N20:N22) -> 72330 | O23: =SUM(O20:O22) -> 14109 | Q23: Total Current Liabilities | R23: =SUMIF(INDIRECT("'"&R$2&"'!$A$1:$A$400"),$K23,INDIRECT("'"&R$2&"'!$b$1:$b$400")) -> 2635.49 | S23: =SUMIF(INDIRECT("'"&S$2&"'!$A$1:$A$400"),$K23,INDIRECT("'"&S$2&"'!$b$1:$b$400")) -> 2635.49 | T23: =SUMIF(INDIRECT("'"&T$2&"'!$A$1:$A$400"),$K23,INDIRECT("'"&T$2&"'!$b$1:$b$400")) -> 2635.49
K24: Check Current Liabilities | L24: =ROUND(SUMIF(INDIRECT("'"&L$2&"'!$A$1:$A$500"),$K$23,INDIRECT("'"&L$2&"'!$C$1:$C$500"))-L23,2) -> 0 | M24: =ROUND(SUMIF(INDIRECT("'"&M$2&"'!$A$1:$A$500"),$K$23,INDIRECT("'"&M$2&"'!$C$1:$C$500"))-M23,2) -> 0 | N24: =ROUND(SUMIF(INDIRECT("'"&N$2&"'!$A$1:$A$500"),$K$23,INDIRECT("'"&N$2&"'!$C$1:$C$500"))-N23,2) -> 0 | O24: =ROUND(SUMIF(INDIRECT("'"&O$2&"'!$A$1:$A$500"),$K$23,INDIRECT("'"&O$2&"'!$C$1:$C$500"))-O23,2) -> 0
B25: Debt - Long-Term - Total | C25: =IFERROR(AVERAGE(D25:G25),0) -> 0.13748423 | D25: =IFERROR(L25/L$18,0) -> 0.18389523 | E25: =IFERROR(M25/M$18,0) -> 0.12277632 | F25: =IFERROR(N25/N$18,0) -> 0.076506749 | G25: =IFERROR(O25/O$18,0) -> 0.16675864 | K25: Debt - Long-Term - Total | L25: =SUMIF(INDIRECT("'"&L$2&"'!$A$1:$A$500"),$K25,INDIRECT("'"&L$2&"'!$C$1:$C$500")) -> 22424 | M25: =SUMIF(INDIRECT("'"&M$2&"'!$A$1:$A$500"),$K25,INDIRECT("'"&M$2&"'!$C$1:$C$500")) -> 39781 | N25: =SUMIF(INDIRECT("'"&N$2&"'!$A$1:$A$500"),$K25,INDIRECT("'"&N$2&"'!$C$1:$C$500")) -> 34350 | O25: =SUMIF(INDIRECT("'"&O$2&"'!$A$1:$A$500"),$K25,INDIRECT("'"&O$2&"'!$C$1:$C$500")) -> 9670 | Q25: Debt - Long-Term - Total | R25: =SUMIF(INDIRECT("'"&R$2&"'!$A$1:$A$400"),$K25,INDIRECT("'"&R$2&"'!$b$1:$b$400")) -> 3396.4 | S25: =SUMIF(INDIRECT("'"&S$2&"'!$A$1:$A$400"),$K25,INDIRECT("'"&S$2&"'!$b$1:$b$400")) -> 3396.4 | T25: =SUMIF(INDIRECT("'"&T$2&"'!$A$1:$A$400"),$K25,INDIRECT("'"&T$2&"'!$b$1:$b$400")) -> 3396.4
B26: Other Non-Current Liabilities | C26: =IFERROR(AVERAGE(D26:G26),0) -> 0.16745564 | D26: =IFERROR(L26/L$18,0) -> 0.18907815 | E26: =IFERROR(M26/M$18,0) -> 0.18106737 | F26: =IFERROR(N26/N$18,0) -> 0.16854648 | G26: =IFERROR(O26/O$18,0) -> 0.13113058 | K26: Other Non-Current Liabilities | L26: =SUMIF(INDIRECT("'"&L$2&"'!$A$1:$A$500"),$K27,INDIRECT("'"&L$2&"'!$C$1:$C$500"))-L25 -> 23056 | M26: =SUMIF(INDIRECT("'"&M$2&"'!$A$1:$A$500"),$K27,INDIRECT("'"&M$2&"'!$C$1:$C$500"))-M25 -> 58668 | N26: =SUMIF(INDIRECT("'"&N$2&"'!$A$1:$A$500"),$K27,INDIRECT("'"&N$2&"'!$C$1:$C$500"))-N25 -> 75674 | O26: =SUMIF(INDIRECT("'"&O$2&"'!$A$1:$A$500"),$K27,INDIRECT("'"&O$2&"'!$C$1:$C$500"))-O25 -> 7604 | Q26: Other Non-Current Liabilities | R26: =SUMIF(INDIRECT("'"&R$2&"'!$A$1:$A$400"),$K26,INDIRECT("'"&R$2&"'!$b$1:$b$400")) -> 210.26 | S26: =SUMIF(INDIRECT("'"&S$2&"'!$A$1:$A$400"),$K26,INDIRECT("'"&S$2&"'!$b$1:$b$400")) -> 210.26 | T26: =SUMIF(INDIRECT("'"&T$2&"'!$A$1:$A$400"),$K26,INDIRECT("'"&T$2&"'!$b$1:$b$400")) -> 210.26
B27: Total Non-Current Liabilities | C27: =IFERROR(AVERAGE(D27:G27),0) -> 0.30493988 | D27: =IFERROR(L27/L$18,0) -> 0.37297337 | E27: =IFERROR(M27/M$18,0) -> 0.30384368 | F27: =IFERROR(N27/N$18,0) -> 0.24505323 | G27: =IFERROR(O27/O$18,0) -> 0.29788922 | K27: Total Non-Current Liabilities | L27: =SUM(L25:L26) -> 45480 | M27: =SUM(M25:M26) -> 98449 | N27: =SUM(N25:N26) -> 110024 | O27: =SUM(O25:O26) -> 17274 | Q27: Total Non-Current Liabilities | R27: =SUMIF(INDIRECT("'"&R$2&"'!$A$1:$A$400"),$K27,INDIRECT("'"&R$2&"'!$b$1:$b$400")) -> 4557.98 | S27: =SUMIF(INDIRECT("'"&S$2&"'!$A$1:$A$400"),$K27,INDIRECT("'"&S$2&"'!$b$1:$b$400")) -> 4557.98 | T27: =SUMIF(INDIRECT("'"&T$2&"'!$A$1:$A$400"),$K27,INDIRECT("'"&T$2&"'!$b$1:$b$400")) -> 4557.98
B28: Total Liabilities | C28: =IFERROR(AVERAGE(D28:G28),0) -> 0.45634742 | D28: =IFERROR(L28/L$18,0) -> 0.47115361 | E28: =IFERROR(M28/M$18,0) -> 0.40688616 | F28: =IFERROR(N28/N$18,0) -> 0.40615172 | G28: =IFERROR(O28/O$18,0) -> 0.54119818 | K28: Total Liabilities | L28: =SUM(L27,L23) -> 57452 | M28: =SUM(M27,M23) -> 131836 | N28: =SUM(N27,N23) -> 182354 | O28: =SUM(O27,O23) -> 31383 | Q28: Total Liabilities | R28: =SUMIF(INDIRECT("'"&R$2&"'!$A$1:$A$400"),$K28,INDIRECT("'"&R$2&"'!$b$1:$b$400")) -> 7193.47 | S28: =SUMIF(INDIRECT("'"&S$2&"'!$A$1:$A$400"),$K28,INDIRECT("'"&S$2&"'!$b$1:$b$400")) -> 7193.47 | T28: =SUMIF(INDIRECT("'"&T$2&"'!$A$1:$A$400"),$K28,INDIRECT("'"&T$2&"'!$b$1:$b$400")) -> 7193.47
K29: Check Total Liabilities | L29: =ROUND(SUMIF(INDIRECT("'"&L$2&"'!$A$1:$A$500"),$K$28,INDIRECT("'"&L$2&"'!$C$1:$C$500"))-L28,2) -> 0 | M29: =ROUND(SUMIF(INDIRECT("'"&M$2&"'!$A$1:$A$500"),$K$28,INDIRECT("'"&M$2&"'!$C$1:$C$500"))-M28,2) -> 0 | N29: =ROUND(SUMIF(INDIRECT("'"&N$2&"'!$A$1:$A$500"),$K$28,INDIRECT("'"&N$2&"'!$C$1:$C$500"))-N28,2) -> 0 | O29: =ROUND(SUMIF(INDIRECT("'"&O$2&"'!$A$1:$A$500"),$K$28,INDIRECT("'"&O$2&"'!$C$1:$C$500"))-O28,2) -> 0
B30: Common Equity - Total | C30: =IFERROR(AVERAGE(D30:G30),0) -> 0.52278681 | D30: =IFERROR(L30/L$18,0) -> 0.52884639 | E30: =IFERROR(M30/M$18,0) -> 0.57544165 | F30: =IFERROR(N30/N$18,0) -> 0.57772284 | G30: =IFERROR(O30/O$18,0) -> 0.40913637 | K30: Common Equity - Total | L30: =SUMIF(INDIRECT("'"&L$2&"'!$A$1:$A$500"),$K30,INDIRECT("'"&L$2&"'!$C$1:$C$500")) -> 64487 | M30: =SUMIF(INDIRECT("'"&M$2&"'!$A$1:$A$500"),$K30,INDIRECT("'"&M$2&"'!$C$1:$C$500")) -> 186450 | N30: =SUMIF(INDIRECT("'"&N$2&"'!$A$1:$A$500"),$K30,INDIRECT("'"&N$2&"'!$C$1:$C$500")) -> 259386 | O30: =SUMIF(INDIRECT("'"&O$2&"'!$A$1:$A$500"),$K30,INDIRECT("'"&O$2&"'!$C$1:$C$500")) -> 23725 | Q30: Common Equity - Total | R30: =SUMIF(INDIRECT("'"&R$2&"'!$A$1:$A$400"),$K30,INDIRECT("'"&R$2&"'!$b$1:$b$400")) -> 9441.35 | S30: =SUMIF(INDIRECT("'"&S$2&"'!$A$1:$A$400"),$K30,INDIRECT("'"&S$2&"'!$b$1:$b$400")) -> 9441.35 | T30: =SUMIF(INDIRECT("'"&T$2&"'!$A$1:$A$400"),$K30,INDIRECT("'"&T$2&"'!$b$1:$b$400")) -> 9441.35
B31: Other Shareholders' Equity | C31: =IFERROR(AVERAGE(D31:G31),0) -> 0.020865768 | D31: =IFERROR(L31/L$18,0) -> 0 | E31: =IFERROR(M31/M$18,0) -> 0.017672185 | F31: =IFERROR(N31/N$18,0) -> 0.01612544 | G31: =IFERROR(O31/O$18,0) -> 0.049665448 | K31: Other Shareholders' Equity | L31: =SUMIF(INDIRECT("'"&L$2&"'!$A$1:$A$500"),$K32,INDIRECT("'"&L$2&"'!$C$1:$C$500"))-L30 -> 0 | M31: =SUMIF(INDIRECT("'"&M$2&"'!$A$1:$A$500"),$K32,INDIRECT("'"&M$2&"'!$C$1:$C$500"))-M30 -> 5726 | N31: =SUMIF(INDIRECT("'"&N$2&"'!$A$1:$A$500"),$K32,INDIRECT("'"&N$2&"'!$C$1:$C$500"))-N30 -> 7240 | O31: =SUMIF(INDIRECT("'"&O$2&"'!$A$1:$A$500"),$K32,INDIRECT("'"&O$2&"'!$C$1:$C$500"))-O30 -> 2880 | Q31: Other Shareholders' Equity | R31: =SUMIF(INDIRECT("'"&R$2&"'!$A$1:$A$400"),$K31,INDIRECT("'"&R$2&"'!$b$1:$b$400")) -> 0 | S31: =SUMIF(INDIRECT("'"&S$2&"'!$A$1:$A$400"),$K31,INDIRECT("'"&S$2&"'!$b$1:$b$400")) -> 0 | T31: =SUMIF(INDIRECT("'"&T$2&"'!$A$1:$A$400"),$K31,INDIRECT("'"&T$2&"'!$b$1:$b$400")) -> 0
B32: Total Shareholders' Equity - including Minority Interest & Hybrid Debt | C32: =IFERROR(AVERAGE(D32:G32),0) -> 0.54365258 | D32: =IFERROR(L32/L$18,0) -> 0.52884639 | E32: =IFERROR(M32/M$18,0) -> 0.59311384 | F32: =IFERROR(N32/N$18,0) -> 0.59384828 | G32: =IFERROR(O32/O$18,0) -> 0.45880182 | K32: Total Shareholders' Equity - including Minority Interest & Hybrid Debt | L32: =SUM(L30:L31) -> 64487 | M32: =SUM(M30:M31) -> 192176 | N32: =SUM(N30:N31) -> 266626 | O32: =SUM(O30:O31) -> 26605 | Q32: Total Shareholders' Equity - including Minority Interest & Hybrid Debt | R32: =SUMIF(INDIRECT("'"&R$2&"'!$A$1:$A$400"),$K32,INDIRECT("'"&R$2&"'!$b$1:$b$400")) -> 9441.35 | S32: =SUMIF(INDIRECT("'"&S$2&"'!$A$1:$A$400"),$K32,INDIRECT("'"&S$2&"'!$b$1:$b$400")) -> 9441.35 | T32: =SUMIF(INDIRECT("'"&T$2&"'!$A$1:$A$400"),$K32,INDIRECT("'"&T$2&"'!$b$1:$b$400")) -> 9441.35
B33: Total Liabilities & Equity | C33: =IFERROR(AVERAGE(D33:G33),0) -> 1 | D33: =IFERROR(L33/L$18,0) -> 1 | E33: =IFERROR(M33/M$18,0) -> 1 | F33: =IFERROR(N33/N$18,0) -> 1 | G33: =IFERROR(O33/O$18,0) -> 1 | K33: Total Liabilities & Equity | L33: =L32+L28 -> 121939 | M33: =M32+M28 -> 324012 | N33: =N32+N28 -> 448980 | O33: =O32+O28 -> 57988 | Q33: Total Liabilities & Equity | R33: =SUMIF(INDIRECT("'"&R$2&"'!$A$1:$A$400"),$K33,INDIRECT("'"&R$2&"'!$b$1:$b$400")) -> 16634.82 | S33: =SUMIF(INDIRECT("'"&S$2&"'!$A$1:$A$400"),$K33,INDIRECT("'"&S$2&"'!$b$1:$b$400")) -> 16634.82 | T33: =SUMIF(INDIRECT("'"&T$2&"'!$A$1:$A$400"),$K33,INDIRECT("'"&T$2&"'!$b$1:$b$400")) -> 16634.82
B34: Check | K34: Check Balance | L34: =ROUND(L18-L33,2) -> 0 | M34: =ROUND(M18-M33,2) -> 0 | N34: =ROUND(N18-N33,2) -> 0 | O34: =ROUND(O18-O33,2) -> 0 | Q34: Check | R34: =R18-R33 -> 0 | S34: =S18-S33 -> 0 | T34: =T18-T33 -> 0
B36: Financial Statement | K36: Financial Statement | L36: 2025 | M36: 2025 | N36: 2025 | O36: 2025 | Q36: Financial Statement | R36: 2024 | S36: 2024 | T36: 2024
B37: Revenue from Business Activities - Total | C37: =IFERROR(AVERAGE(D37:G37),0) -> 1 | D37: =IFERROR(L37/L$37,0) -> 1 | E37: =IFERROR(M37/M$37,0) -> 1 | F37: =IFERROR(N37/N$37,0) -> 1 | G37: =IFERROR(O37/O$37,0) -> 1 | K37: Revenue from Business Activities - Total | L37: =SUMIF(INDIRECT("'"&L$2&"'!$A$1:$A$500"),$K37,INDIRECT("'"&L$2&"'!$C$1:$C$500")) -> 58944 | M37: =SUMIF(INDIRECT("'"&M$2&"'!$A$1:$A$500"),$K37,INDIRECT("'"&M$2&"'!$C$1:$C$500")) -> 184432 | N37: =SUMIF(INDIRECT("'"&N$2&"'!$A$1:$A$500"),$K37,INDIRECT("'"&N$2&"'!$C$1:$C$500")) -> 323905 | O37: =SUMIF(INDIRECT("'"&O$2&"'!$A$1:$A$500"),$K37,INDIRECT("'"&O$2&"'!$C$1:$C$500")) -> 115967 | Q37: Revenue from Business Activities - Total | R37: =SUMIF(INDIRECT("'"&R$2&"'!$A$1:$A$400"),$K37,INDIRECT("'"&R$2&"'!$b$1:$b$400")) -> 8188.99 | S37: =SUMIF(INDIRECT("'"&S$2&"'!$A$1:$A$400"),$K37,INDIRECT("'"&S$2&"'!$b$1:$b$400")) -> 8188.99 | T37: =SUMIF(INDIRECT("'"&T$2&"'!$A$1:$A$400"),$K37,INDIRECT("'"&T$2&"'!$b$1:$b$400")) -> 8188.99
B38: Cost of Sales | C38: =IFERROR(AVERAGE(D38:G38),0) -> 0.79133438 | D38: =IFERROR(L38/L$37,0) -> 0.74548724 | E38: =IFERROR(M38/M$37,0) -> 0.69181595 | F38: =IFERROR(N38/N$37,0) -> 0.77433198 | G38: =IFERROR(O38/O$37,0) -> 0.95370235 | K38: Cost of Operating Revenue | L38: =SUMIF(INDIRECT("'"&L$2&"'!$A$1:$A$500"),$K38,INDIRECT("'"&L$2&"'!$C$1:$C$500")) -> 43942 | M38: =SUMIF(INDIRECT("'"&M$2&"'!$A$1:$A$500"),$K38,INDIRECT("'"&M$2&"'!$C$1:$C$500")) -> 127593 | N38: =SUMIF(INDIRECT("'"&N$2&"'!$A$1:$A$500"),$K38,INDIRECT("'"&N$2&"'!$C$1:$C$500")) -> 250810 | O38: =SUMIF(INDIRECT("'"&O$2&"'!$A$1:$A$500"),$K38,INDIRECT("'"&O$2&"'!$C$1:$C$500")) -> 110598 | Q38: Cost of Sales | R38: =SUMIF(INDIRECT("'"&R$2&"'!$A$1:$A$400"),$K38,INDIRECT("'"&R$2&"'!$b$1:$b$400")) -> 6306.56 | S38: =SUMIF(INDIRECT("'"&S$2&"'!$A$1:$A$400"),$K38,INDIRECT("'"&S$2&"'!$b$1:$b$400")) -> 6306.56 | T38: =SUMIF(INDIRECT("'"&T$2&"'!$A$1:$A$400"),$K38,INDIRECT("'"&T$2&"'!$b$1:$b$400")) -> 6306.56
B39: Gross Profit - Industrials/Property - Total | C39: =IFERROR(AVERAGE(D39:G39),0) -> 0.20866562 | D39: =IFERROR(L39/L$37,0) -> 0.25451276 | E39: =IFERROR(M39/M$37,0) -> 0.30818405 | F39: =IFERROR(N39/N$37,0) -> 0.22566802 | G39: =IFERROR(O39/O$37,0) -> 0.046297654 | K39: Gross Profit - Industrials/Property - Total | L39: =L37-L38 -> 15002 | M39: =M37-M38 -> 56839 | N39: =N37-N38 -> 73095 | O39: =O37-O38 -> 5369 | Q39: Gross Profit - Industrials/Property - Total | R39: =SUMIF(INDIRECT("'"&R$2&"'!$A$1:$A$400"),$K39,INDIRECT("'"&R$2&"'!$b$1:$b$400")) -> 1882.43 | S39: =SUMIF(INDIRECT("'"&S$2&"'!$A$1:$A$400"),$K39,INDIRECT("'"&S$2&"'!$b$1:$b$400")) -> 1882.43 | T39: =SUMIF(INDIRECT("'"&T$2&"'!$A$1:$A$400"),$K39,INDIRECT("'"&T$2&"'!$b$1:$b$400")) -> 1882.43
B40: Selling, General & Administrative Expenses excluding Research & Development Expenses | C40: =IFERROR(AVERAGE(D40:G40),0) -> 0.058566314 | D40: =IFERROR(L40/L$37,0) -> 0.054373643 | E40: =IFERROR(M40/M$37,0) -> 0.059534137 | F40: =IFERROR(N40/N$37,0) -> 0.11137216 | G40: =IFERROR(O40/O$37,0) -> 0.0089853148 | K40: Selling, General & Administrative Expenses excluding Research & Development Expenses | L40: =SUMIF( INDIRECT("'"&L$2&"'!$A$1:$A$500"), $K40, INDIRECT("'"&L$2&"'!$C$1:$C$500") ) -> 3205 | M40: =SUMIF( INDIRECT("'"&M$2&"'!$A$1:$A$500"), $K40, INDIRECT("'"&M$2&"'!$C$1:$C$500") ) -> 10980 | N40: =SUMIF( INDIRECT("'"&N$2&"'!$A$1:$A$500"), $K40, INDIRECT("'"&N$2&"'!$C$1:$C$500") ) -> 36074 | O40: =SUMIF( INDIRECT("'"&O$2&"'!$A$1:$A$500"), $K40, INDIRECT("'"&O$2&"'!$C$1:$C$500") ) -> 1042 | Q40: Selling, General & Administrative Expenses excluding Research & Development Expenses | R40: =SUMIF(INDIRECT("'"&R$2&"'!$A$1:$A$400"),$K40,INDIRECT("'"&R$2&"'!$b$1:$b$400")) -> 728.35 | S40: =SUMIF(INDIRECT("'"&S$2&"'!$A$1:$A$400"),$K40,INDIRECT("'"&S$2&"'!$b$1:$b$400")) -> 728.35 | T40: =SUMIF(INDIRECT("'"&T$2&"'!$A$1:$A$400"),$K40,INDIRECT("'"&T$2&"'!$b$1:$b$400")) -> 728.35
B41: Research & Development Expense - Supplemental | C41: =IFERROR(AVERAGE(D41:G41),0) -> 0.0018574354 | D41: =IFERROR(L41/L$37,0) -> 0.0013232899 | E41: =IFERROR(M41/M$37,0) -> 0.0023152164 | F41: =IFERROR(N41/N$37,0) -> 0.0037912351 | G41: =IFERROR(O41/O$37,0) -> 0 | K41: Research & Development Expense - Supplemental | L41: =SUMIF( INDIRECT("'"&L$2&"'!$A$1:$A$500"), $K41, INDIRECT("'"&L$2&"'!$C$1:$C$500") ) -> 78 | M41: =SUMIF( INDIRECT("'"&M$2&"'!$A$1:$A$500"), $K41, INDIRECT("'"&M$2&"'!$C$1:$C$500") ) -> 427 | N41: =SUMIF( INDIRECT("'"&N$2&"'!$A$1:$A$500"), $K41, INDIRECT("'"&N$2&"'!$C$1:$C$500") ) -> 1228 | O41: =SUMIF( INDIRECT("'"&O$2&"'!$A$1:$A$500"), $K41, INDIRECT("'"&O$2&"'!$C$1:$C$500") ) -> 0 | Q41: Research & Development Expense - Supplemental | R41: =SUMIF(INDIRECT("'"&R$2&"'!$A$1:$A$400"),$K41,INDIRECT("'"&R$2&"'!$b$1:$b$400")) -> 0 | S41: =SUMIF(INDIRECT("'"&S$2&"'!$A$1:$A$400"),$K41,INDIRECT("'"&S$2&"'!$b$1:$b$400")) -> 0 | T41: =SUMIF(INDIRECT("'"&T$2&"'!$A$1:$A$400"),$K41,INDIRECT("'"&T$2&"'!$b$1:$b$400")) -> 0
B42: — | C42: =IFERROR(AVERAGE(D42:G42),0) -> 0.033082048 | D42: =IFERROR(L42/L$37,0) -> -0.0035118078 | E42: =IFERROR(M42/M$37,0) -> 0.14456819 | F42: =IFERROR(N42/N$37,0) -> -0.0088575354 | G42: =IFERROR(O42/O$37,0) -> 0.00012934714 | K42: Other | L42: =SUMIF(INDIRECT("'"&L$2&"'!$A$1:$A$500"),$K$43,INDIRECT("'"&L$2&"'!$C$1:$C$500"))-L38-L40-L41 -> -207 | M42: =SUMIF(INDIRECT("'"&M$2&"'!$A$1:$A$500"),$K$43,INDIRECT("'"&M$2&"'!$C$1:$C$500"))-M38-M40-M41 -> 26663 | N42: =SUMIF(INDIRECT("'"&N$2&"'!$A$1:$A$500"),$K$43,INDIRECT("'"&N$2&"'!$C$1:$C$500"))-N38-N40-N41 -> -2869 | O42: =SUMIF(INDIRECT("'"&O$2&"'!$A$1:$A$500"),$K$43,INDIRECT("'"&O$2&"'!$C$1:$C$500"))-O38-O40-O41 -> 15 | Q42: Other | R42: =SUMIF(INDIRECT("'"&R$2&"'!$A$1:$A$400"),$K42,INDIRECT("'"&R$2&"'!$b$1:$b$400")) -> 0 | S42: =SUMIF(INDIRECT("'"&S$2&"'!$A$1:$A$400"),$K42,INDIRECT("'"&S$2&"'!$b$1:$b$400")) -> 0 | T42: =SUMIF(INDIRECT("'"&T$2&"'!$A$1:$A$400"),$K42,INDIRECT("'"&T$2&"'!$b$1:$b$400")) -> 0
B43: Operating Expenses - Total | C43: =IFERROR(AVERAGE(D43:G43),0) -> 0.88484018 | D43: =IFERROR(L43/L$37,0) -> 0.79767237 | E43: =IFERROR(M43/M$37,0) -> 0.8982335 | F43: =IFERROR(N43/N$37,0) -> 0.88063784 | G43: =IFERROR(O43/O$37,0) -> 0.96281701 | K43: Operating Expenses - Total | L43: =SUM(L38,L40:L42) -> 47018 | M43: =SUM(M38,M40:M42) -> 165663 | N43: =SUM(N38,N40:N42) -> 285243 | O43: =SUM(O38,O40:O42) -> 111655 | Q43: Operating Expenses - Total | R43: =SUMIF(INDIRECT("'"&R$2&"'!$A$1:$A$400"),$K43,INDIRECT("'"&R$2&"'!$b$1:$b$400")) -> 7034.91 | S43: =SUMIF(INDIRECT("'"&S$2&"'!$A$1:$A$400"),$K43,INDIRECT("'"&S$2&"'!$b$1:$b$400")) -> 7034.91 | T43: =SUMIF(INDIRECT("'"&T$2&"'!$A$1:$A$400"),$K43,INDIRECT("'"&T$2&"'!$b$1:$b$400")) -> 7034.91
B44: Earnings before Interest & Taxes (EBIT) | C44: =IFERROR(AVERAGE(D44:G44),0) -> 0.11515982 | D44: =IFERROR(L44/L$37,0) -> 0.20232763 | E44: =IFERROR(M44/M$37,0) -> 0.1017665 | F44: =IFERROR(N44/N$37,0) -> 0.11936216 | G44: =IFERROR(O44/O$37,0) -> 0.037182992 | K44: Earnings before Interest & Taxes (EBIT) | L44: =L37-L43 -> 11926 | M44: =M37-M43 -> 18769 | N44: =N37-N43 -> 38662 | O44: =O37-O43 -> 4312 | Q44: Earnings before Interest & Taxes (EBIT) | R44: =SUMIF(INDIRECT("'"&R$2&"'!$A$1:$A$400"),$K44,INDIRECT("'"&R$2&"'!$b$1:$b$400")) -> 1154.08 | S44: =SUMIF(INDIRECT("'"&S$2&"'!$A$1:$A$400"),$K44,INDIRECT("'"&S$2&"'!$b$1:$b$400")) -> 1154.08 | T44: =SUMIF(INDIRECT("'"&T$2&"'!$A$1:$A$400"),$K44,INDIRECT("'"&T$2&"'!$b$1:$b$400")) -> 1154.08
B45: Depreciation, Depletion & Amortization - Total | C45: =IFERROR(AVERAGE(D45:G45),0) -> 0.1023705 | D45: =IFERROR(L45/L$37,0) -> 0.19510043 | E45: =IFERROR(M45/M$37,0) -> 0.10507396 | F45: =IFERROR(N45/N$37,0) -> 0.074521851 | G45: =IFERROR(O45/O$37,0) -> 0.034785758 | K45: Depreciation, Depletion & Amortization - Total | L45: =SUMIF( INDIRECT("'"&L$2&"'!$A$1:$A$500"), $K45, INDIRECT("'"&L$2&"'!$C$1:$C$500") ) -> 11500 | M45: =SUMIF( INDIRECT("'"&M$2&"'!$A$1:$A$500"), $K45, INDIRECT("'"&M$2&"'!$C$1:$C$500") ) -> 19379 | N45: =SUMIF( INDIRECT("'"&N$2&"'!$A$1:$A$500"), $K45, INDIRECT("'"&N$2&"'!$C$1:$C$500") ) -> 24138 | O45: =SUMIF( INDIRECT("'"&O$2&"'!$A$1:$A$500"), $K45, INDIRECT("'"&O$2&"'!$C$1:$C$500") ) -> 4034 | Q45: Depreciation, Depletion & Amortization - Total | R45: =SUMIF(INDIRECT("'"&R$2&"'!$A$1:$A$400"),$K45,INDIRECT("'"&R$2&"'!$b$1:$b$400")) -> 488.5 | S45: =SUMIF(INDIRECT("'"&S$2&"'!$A$1:$A$400"),$K45,INDIRECT("'"&S$2&"'!$b$1:$b$400")) -> 488.5 | T45: =SUMIF(INDIRECT("'"&T$2&"'!$A$1:$A$400"),$K45,INDIRECT("'"&T$2&"'!$b$1:$b$400")) -> 488.5
B46: Earnings before Interest, Taxes, Depreciation & Amortization (EBITDA) | C46: =IFERROR(AVERAGE(D46:G46),0) -> 0.21753032 | D46: =IFERROR(L46/L$37,0) -> 0.39742807 | E46: =IFERROR(M46/M$37,0) -> 0.20684046 | F46: =IFERROR(N46/N$37,0) -> 0.19388401 | G46: =IFERROR(O46/O$37,0) -> 0.07196875 | K46: Earnings before Interest, Taxes, Depreciation & Amortization (EBITDA) | L46: =L44+L45 -> 23426 | M46: =M44+M45 -> 38148 | N46: =N44+N45 -> 62800 | O46: =O44+O45 -> 8346 | Q46: Earnings before Interest, Taxes, Depreciation & Amortization (EBITDA) | R46: =SUMIF(INDIRECT("'"&R$2&"'!$A$1:$A$400"),$K46,INDIRECT("'"&R$2&"'!$b$1:$b$400")) -> 1642.58 | S46: =SUMIF(INDIRECT("'"&S$2&"'!$A$1:$A$400"),$K46,INDIRECT("'"&S$2&"'!$b$1:$b$400")) -> 1642.58 | T46: =SUMIF(INDIRECT("'"&T$2&"'!$A$1:$A$400"),$K46,INDIRECT("'"&T$2&"'!$b$1:$b$400")) -> 1642.58
B47: Interest Expense - Net of (Interest Income) | C47: =IFERROR(AVERAGE(D47:G47),0) -> 0.0052725984 | D47: =IFERROR(L47/L$37,0) -> 0.0092290988 | E47: =IFERROR(M47/M$37,0) -> 0.0052051705 | F47: =IFERROR(N47/N$37,0) -> 0.001861657 | G47: =IFERROR(O47/O$37,0) -> 0.0047944674 | K47: Interest Expense - Net of (Interest Income) | L47: =SUMIF( INDIRECT("'"&L$2&"'!$A$1:$A$500"), $K47, INDIRECT("'"&L$2&"'!$C$1:$C$500") ) -> 544 | M47: =SUMIF( INDIRECT("'"&M$2&"'!$A$1:$A$500"), $K47, INDIRECT("'"&M$2&"'!$C$1:$C$500") ) -> 960 | N47: =SUMIF( INDIRECT("'"&N$2&"'!$A$1:$A$500"), $K47, INDIRECT("'"&N$2&"'!$C$1:$C$500") ) -> 603 | O47: =SUMIF( INDIRECT("'"&O$2&"'!$A$1:$A$500"), $K47, INDIRECT("'"&O$2&"'!$C$1:$C$500") ) -> 556 | Q47: Interest Expense - Net of (Interest Income) | R47: =SUMIF(INDIRECT("'"&R$2&"'!$A$1:$A$400"),$K47,INDIRECT("'"&R$2&"'!$b$1:$b$400")) -> 228.63 | S47: =SUMIF(INDIRECT("'"&S$2&"'!$A$1:$A$400"),$K47,INDIRECT("'"&S$2&"'!$b$1:$b$400")) -> 228.63 | T47: =SUMIF(INDIRECT("'"&T$2&"'!$A$1:$A$400"),$K47,INDIRECT("'"&T$2&"'!$b$1:$b$400")) -> 228.63
B48: Other | C48: =IFERROR(AVERAGE(D48:G48),0) -> 0.0088828076 | D48: =IFERROR(L48/L$37,0) -> 0.021613735 | E48: =IFERROR(M48/M$37,0) -> 0.01048625 | F48: =IFERROR(N48/N$37,0) -> 0.0099072259 | G48: =IFERROR(O48/O$37,0) -> -0.0064759802 | K48: Other | L48: =SUMIF(INDIRECT("'"&L$2&"'!$A$1:$A$500"),$K$49,INDIRECT("'"&L$2&"'!$C$1:$C$500"))-L44+L47 -> 1274 | M48: =SUMIF(INDIRECT("'"&M$2&"'!$A$1:$A$500"),$K$49,INDIRECT("'"&M$2&"'!$C$1:$C$500"))-M44+M47 -> 1934 | N48: =SUMIF(INDIRECT("'"&N$2&"'!$A$1:$A$500"),$K$49,INDIRECT("'"&N$2&"'!$C$1:$C$500"))-N44+N47 -> 3209 | O48: =SUMIF(INDIRECT("'"&O$2&"'!$A$1:$A$500"),$K$49,INDIRECT("'"&O$2&"'!$C$1:$C$500"))-O44+O47 -> -751 | Q48: Other | R48: =SUMIF(INDIRECT("'"&R$2&"'!$A$1:$A$400"),$K48,INDIRECT("'"&R$2&"'!$b$1:$b$400")) -> 0 | S48: =SUMIF(INDIRECT("'"&S$2&"'!$A$1:$A$400"),$K48,INDIRECT("'"&S$2&"'!$b$1:$b$400")) -> 0 | T48: =SUMIF(INDIRECT("'"&T$2&"'!$A$1:$A$400"),$K48,INDIRECT("'"&T$2&"'!$b$1:$b$400")) -> 0
B49: Income before Taxes | C49: =IFERROR(AVERAGE(D49:G49),0) -> 0.11877003 | D49: =IFERROR(L49/L$37,0) -> 0.21471227 | E49: =IFERROR(M49/M$37,0) -> 0.10704758 | F49: =IFERROR(N49/N$37,0) -> 0.12740773 | G49: =IFERROR(O49/O$37,0) -> 0.025912544 | K49: Income before Taxes | L49: =L44-L47+L48 -> 12656 | M49: =M44-M47+M48 -> 19743 | N49: =N44-N47+N48 -> 41268 | O49: =O44-O47+O48 -> 3005 | Q49: Income before Taxes | R49: =SUMIF(INDIRECT("'"&R$2&"'!$A$1:$A$400"),$K49,INDIRECT("'"&R$2&"'!$b$1:$b$400")) -> 803.76 | S49: =SUMIF(INDIRECT("'"&S$2&"'!$A$1:$A$400"),$K49,INDIRECT("'"&S$2&"'!$b$1:$b$400")) -> 803.76 | T49: =SUMIF(INDIRECT("'"&T$2&"'!$A$1:$A$400"),$K49,INDIRECT("'"&T$2&"'!$b$1:$b$400")) -> 803.76
B50: Income Taxes | C50: =IFERROR(AVERAGE(D50:G50),0) -> 0.041898078 | D50: =IFERROR(L50/L$37,0) -> 0.085979913 | E50: =IFERROR(M50/M$37,0) -> 0.039353258 | F50: =IFERROR(N50/N$37,0) -> 0.035714175 | G50: =IFERROR(O50/O$37,0) -> 0.0065449654 | K50: Income Taxes | L50: =SUMIF(INDIRECT("'"&L$2&"'!$A$1:$A$500"),$K$50,INDIRECT("'"&L$2&"'!$C$1:$C$500")) -> 5068 | M50: =SUMIF(INDIRECT("'"&M$2&"'!$A$1:$A$500"),$K$50,INDIRECT("'"&M$2&"'!$C$1:$C$500")) -> 7258 | N50: =SUMIF(INDIRECT("'"&N$2&"'!$A$1:$A$500"),$K$50,INDIRECT("'"&N$2&"'!$C$1:$C$500")) -> 11568 | O50: =SUMIF(INDIRECT("'"&O$2&"'!$A$1:$A$500"),$K$50,INDIRECT("'"&O$2&"'!$C$1:$C$500")) -> 759 | Q50: Income Taxes | R50: =SUMIF(INDIRECT("'"&R$2&"'!$A$1:$A$400"),$K50,INDIRECT("'"&R$2&"'!$b$1:$b$400")) -> 64.63 | S50: =SUMIF(INDIRECT("'"&S$2&"'!$A$1:$A$400"),$K50,INDIRECT("'"&S$2&"'!$b$1:$b$400")) -> 64.63 | T50: =SUMIF(INDIRECT("'"&T$2&"'!$A$1:$A$400"),$K50,INDIRECT("'"&T$2&"'!$b$1:$b$400")) -> 64.63
B51: Other | C51: =IFERROR(AVERAGE(D51:G51),0) -> 0.0010036027 | D51: =IFERROR(L51/L$37,0) -> 0.0067861021 | E51: =IFERROR(M51/M$37,0) -> -0.0010085018 | F51: =IFERROR(N51/N$37,0) -> -0.0026427502 | G51: =IFERROR(O51/O$37,0) -> 0.00087956056 | K51: Other | L51: =SUMIF(INDIRECT("'"&L$2&"'!$A$1:$A$500"),$K$52,INDIRECT("'"&L$2&"'!$C$1:$C$500"))-(L49-L50) -> 400 | M51: =SUMIF(INDIRECT("'"&M$2&"'!$A$1:$A$500"),$K$52,INDIRECT("'"&M$2&"'!$C$1:$C$500"))-(M49-M50) -> -186 | N51: =SUMIF(INDIRECT("'"&N$2&"'!$A$1:$A$500"),$K$52,INDIRECT("'"&N$2&"'!$C$1:$C$500"))-(N49-N50) -> -856 | O51: =SUMIF(INDIRECT("'"&O$2&"'!$A$1:$A$500"),$K$52,INDIRECT("'"&O$2&"'!$C$1:$C$500"))-(O49-O50) -> 102 | Q51: Other | R51: =SUMIF(INDIRECT("'"&R$2&"'!$A$1:$A$400"),$K51,INDIRECT("'"&R$2&"'!$b$1:$b$400")) -> 0 | S51: =SUMIF(INDIRECT("'"&S$2&"'!$A$1:$A$400"),$K51,INDIRECT("'"&S$2&"'!$b$1:$b$400")) -> 0 | T51: =SUMIF(INDIRECT("'"&T$2&"'!$A$1:$A$400"),$K51,INDIRECT("'"&T$2&"'!$b$1:$b$400")) -> 0
B52: Net Income after Minority Interest | C52: =IFERROR(AVERAGE(D52:G52),0) -> 0.077875556 | D52: =IFERROR(L52/L$37,0) -> 0.13551846 | E52: =IFERROR(M52/M$37,0) -> 0.066685825 | F52: =IFERROR(N52/N$37,0) -> 0.089050802 | G52: =IFERROR(O52/O$37,0) -> 0.020247139 | K52: Net Income after Minority Interest | L52: =L49-L50+L51 -> 7988 | M52: =M49-M50+M51 -> 12299 | N52: =N49-N50+N51 -> 28844 | O52: =O49-O50+O51 -> 2348 | Q52: Net Income after Minority Interest | R52: =SUMIF(INDIRECT("'"&R$2&"'!$A$1:$A$400"),$K52,INDIRECT("'"&R$2&"'!$b$1:$b$400")) -> 739.13 | S52: =SUMIF(INDIRECT("'"&S$2&"'!$A$1:$A$400"),$K52,INDIRECT("'"&S$2&"'!$b$1:$b$400")) -> 739.13 | T52: =SUMIF(INDIRECT("'"&T$2&"'!$A$1:$A$400"),$K52,INDIRECT("'"&T$2&"'!$b$1:$b$400")) -> 739.13
K53: Check Net Income | L53: =ROUND(SUMIF(INDIRECT("'"&L$2&"'!$A$1:$A$500"),$K$52,INDIRECT("'"&L$2&"'!$C$1:$C$500"))-L52,2) -> 0 | M53: =ROUND(SUMIF(INDIRECT("'"&M$2&"'!$A$1:$A$500"),$K$52,INDIRECT("'"&M$2&"'!$C$1:$C$500"))-M52,2) -> 0 | N53: =ROUND(SUMIF(INDIRECT("'"&N$2&"'!$A$1:$A$500"),$K$52,INDIRECT("'"&N$2&"'!$C$1:$C$500"))-N52,2) -> 0 | O53: =ROUND(SUMIF(INDIRECT("'"&O$2&"'!$A$1:$A$500"),$K$52,INDIRECT("'"&O$2&"'!$C$1:$C$500"))-O52,2) -> 0
B55: Indicadores de Liquidez (Liquidity Ratios) | K55: Indicadores de Liquidez (Liquidity Ratios)
B56: Razón corriente (CR) | C56: =IFERROR(AVERAGE(D56:G56),0) -> 1.3124776 | D56: =L56 -> 1.2973605 | E56: =M56 -> 1.1547009 | F56: =N56 -> 1.1527997 | G56: =O56 -> 1.6450493 | K56: Razón corriente (CR) | L56: =IFERROR(L11/L23,0) -> 1.2973605 | M56: =IFERROR(M11/M23,0) -> 1.1547009 | N56: =IFERROR(N11/N23,0) -> 1.1527997 | O56: =IFERROR(O11/O23,0) -> 1.6450493
B57: Prueba ácida (QR) | C57: =IFERROR(AVERAGE(D57:G57),0) -> 0.7458881 | D57: =L57 -> 1.0686602 | E57: =M57 -> 0.72998472 | F57: =N57 -> 0.64184985 | G57: =O57 -> 0.54305762 | K57: Prueba ácida (QR) | L57: =IFERROR(SUM(L6:L8)/L23,0) -> 1.0686602 | M57: =IFERROR(SUM(M6:M8)/M23,0) -> 0.72998472 | N57: =IFERROR(SUM(N6:N8)/N23,0) -> 0.64184985 | O57: =IFERROR(SUM(O6:O8)/O23,0) -> 0.54305762
B58: Capital de trabajo neto (NWC) (USD mm) | C58: =IFERROR(AVERAGE(D58:G58),0) -> 7219.5 | D58: =L58 -> 3560 | E58: =M58 -> 5165 | F58: =N58 -> 11052 | G58: =O58 -> 9101 | K58: Capital de trabajo neto (NWC) (USD mm) | L58: =L11-L23 -> 3560 | M58: =M11-M23 -> 5165 | N58: =N11-N23 -> 11052 | O58: =O11-O23 -> 9101
B59: Administración de Activos (Efficiency Ratios) | D59: =L59 -> 0 | E59: =M59 -> 0 | F59: =N59 -> 0 | G59: =O59 -> 0 | K59: Administración de Activos (Efficiency Ratios)
B60: Rotación de inventario (ITR) | C60: =IFERROR(AVERAGE(D60:G60),0) -> 15.482208 | D60: =L60 -> 23.86855 | E60: =M60 -> 13.584562 | F60: =N60 -> 10.067435 | G60: =O60 -> 14.408286 | K60: Rotación de inventario (ITR) | L60: =IFERROR(L38/AVERAGE(L9,SUMIF(INDIRECT("'"&L$2&"'!$A$1:$A$500"),$K$9,INDIRECT("'"&L$2&"'!$B$1:$B$500"))),0) -> 23.86855 | M60: =IFERROR(M38/AVERAGE(M9,SUMIF(INDIRECT("'"&M$2&"'!$A$1:$A$500"),$K$9,INDIRECT("'"&M$2&"'!$B$1:$B$500"))),0) -> 13.584562 | N60: =IFERROR(N38/AVERAGE(N9,SUMIF(INDIRECT("'"&N$2&"'!$A$1:$A$500"),$K$9,INDIRECT("'"&N$2&"'!$B$1:$B$500"))),0) -> 10.067435 | O60: =IFERROR(O38/AVERAGE(O9,SUMIF(INDIRECT("'"&O$2&"'!$A$1:$A$500"),$K$9,INDIRECT("'"&O$2&"'!$B$1:$B$500"))),0) -> 14.408286
B61: Rotación de activos fijos netos (FAT) | C61: =IFERROR(AVERAGE(D61:G61),0) -> 1.635331 | D61: =L61 -> 0.62580556 | E61: =M61 -> 0.81685512 | F61: =N61 -> 1.056452 | G61: =O61 -> 4.0422113 | K61: Rotación de activos fijos netos (FAT) | L61: =IFERROR(L37/L14,0) -> 0.62580556 | M61: =IFERROR(M37/M14,0) -> 0.81685512 | N61: =IFERROR(N37/N14,0) -> 1.056452 | O61: =IFERROR(O37/O14,0) -> 4.0422113
B62: Rotación de activos totales (ATR) | C62: =IFERROR(AVERAGE(D62:G62),0) -> 0.94346791 | D62: =L62 -> 0.48338924 | E62: =M62 -> 0.56921349 | F62: =N62 -> 0.72142412 | G62: =O62 -> 1.9998448 | K62: Rotación de activos totales (ATR) | L62: =IFERROR(L37/L18,0) -> 0.48338924 | M62: =IFERROR(M37/M18,0) -> 0.56921349 | N62: =IFERROR(N37/N18,0) -> 0.72142412 | O62: =IFERROR(O37/O18,0) -> 1.9998448
B63: Días promedio de cartera (DSO) | C63: =IFERROR(AVERAGE(D63:G63),0) -> 30.351684 | D63: =L63 -> 35.995945 | E63: =M63 -> 35.771314 | F63: =N63 -> 40.278971 | G63: =O63 -> 9.3605077 | K63: Días promedio de cartera (DSO) | L63: =IFERROR(L8/(L37/365),0) -> 35.995945 | M63: =IFERROR(M8/(M37/365),0) -> 35.771314 | N63: =IFERROR(N8/(N37/365),0) -> 40.278971 | O63: =IFERROR(O8/(O37/365),0) -> 9.3605077
B64: Días promedio de inventario (DIO) | C64: =IFERROR(AVERAGE(D64:G64),0) -> 26.666694 | D64: =L64 -> 15.557894 | E64: =M64 -> 27.779855 | F64: =N64 -> 38.276903 | G64: =O64 -> 25.052126 | K64: Días promedio de inventario (DIO) | L64: =IFERROR(L9/(L38/365),0) -> 15.557894 | M64: =IFERROR(M9/(M38/365),0) -> 27.779855 | N64: =IFERROR(N9/(N38/365),0) -> 38.276903 | O64: =IFERROR(O9/(O38/365),0) -> 25.052126
B65: Periodo promedio de pago (DPO) | C65: =IFERROR(AVERAGE(D65:G65),0) -> 48.181355 | D65: =L65 -> 51.649219 | E65: =M65 -> 55.153496 | F65: =N65 -> 52.461565 | G65: =O65 -> 33.461139 | K65: Periodo promedio de pago (DPO) | L65: =IFERROR(L20/(L38/365),0) -> 51.649219 | M65: =IFERROR(M20/(M38/365),0) -> 55.153496 | N65: =IFERROR(N20/(N38/365),0) -> 52.461565 | O65: =IFERROR(O20/(O38/365),0) -> 33.461139
B66: Ciclo operativo (OC) | C66: =IFERROR(AVERAGE(D66:G66),0) -> 57.018379 | D66: =L66 -> 51.55384 | E66: =M66 -> 63.551169 | F66: =N66 -> 78.555874 | G66: =O66 -> 34.412633 | K66: Ciclo operativo (OC) | L66: =L63+L64 -> 51.55384 | M66: =M63+M64 -> 63.551169 | N66: =N63+N64 -> 78.555874 | O66: =O63+O64 -> 34.412633
B67: Ciclo de efectivo (CC) | C67: =IFERROR(AVERAGE(D67:G67),0) -> 8.8370243 | D67: =L67 -> -0.095379624 | E67: =M67 -> 8.3976729 | F67: =N67 -> 26.094309 | G67: =O67 -> 0.95149491 | K67: Ciclo de efectivo (CC) | L67: =L63+L64-L65 -> -0.095379624 | M67: =M63+M64-M65 -> 8.3976729 | N67: =N63+N64-N65 -> 26.094309 | O67: =O63+O64-O65 -> 0.95149491
B68: Administración de Pasivos (Leverage Ratios) | K68: Administración de Pasivos (Leverage Ratios)
B69: Nivel de endeudamiento (Debt to Assets) | C69: =IFERROR(AVERAGE(D69:G69),0) -> 0.45634742 | D69: =L69 -> 0.47115361 | E69: =M69 -> 0.40688616 | F69: =N69 -> 0.40615172 | G69: =O69 -> 0.54119818 | K69: Nivel de endeudamiento (Debt to Assets) | L69: =IFERROR(L28/L18,0) -> 0.47115361 | M69: =IFERROR(M28/M18,0) -> 0.40688616 | N69: =IFERROR(N28/N18,0) -> 0.40615172 | O69: =IFERROR(O28/O18,0) -> 0.54119818
B70: Cobertura de intereses (Interest Coverage) | C70: =IFERROR(AVERAGE(D70:G70),0) -> 28.336329 | D70: =L70 -> 21.922794 | E70: =M70 -> 19.551042 | F70: =N70 -> 64.116086 | G70: =O70 -> 7.7553957 | K70: Cobertura de intereses (Interest Coverage) | L70: =IFERROR(L44/L47,0) -> 21.922794 | M70: =IFERROR(M44/M47,0) -> 19.551042 | N70: =IFERROR(N44/N47,0) -> 64.116086 | O70: =IFERROR(O44/O47,0) -> 7.7553957
B71: Indicadores de Rentabilidad (Profitability Ratios) | K71: Indicadores de Rentabilidad (Profitability Ratios)
B72: Margen neto (NPM) | C72: =IFERROR(AVERAGE(D72:G72),0) -> 0.077875556 | D72: =L72 -> 0.13551846 | E72: =M72 -> 0.066685825 | F72: =N72 -> 0.089050802 | G72: =O72 -> 0.020247139 | K72: Margen neto (NPM) | L72: =IFERROR(L52/L37,0) -> 0.13551846 | M72: =IFERROR(M52/M37,0) -> 0.066685825 | N72: =IFERROR(N52/N37,0) -> 0.089050802 | O72: =IFERROR(O52/O37,0) -> 0.020247139
B73: Margen operacional (OM) | C73: =IFERROR(AVERAGE(D73:G73),0) -> 0.11515982 | D73: =L73 -> 0.20232763 | E73: =M73 -> 0.1017665 | F73: =N73 -> 0.11936216 | G73: =O73 -> 0.037182992 | K73: Margen operacional (OM) | L73: =IFERROR(L44/L37,0) -> 0.20232763 | M73: =IFERROR(M44/M37,0) -> 0.1017665 | N73: =IFERROR(N44/N37,0) -> 0.11936216 | O73: =IFERROR(O44/O37,0) -> 0.037182992
B74: ROA | C74: =IFERROR(AVERAGE(D74:G74),0) -> 0.052050292 | D74: =L74 -> 0.065508164 | E74: =M74 -> 0.037958471 | F74: =N74 -> 0.064243396 | G74: =O74 -> 0.040491136 | K74: ROA | L74: =IFERROR(L52/L18,0) -> 0.065508164 | M74: =IFERROR(M52/M18,0) -> 0.037958471 | N74: =IFERROR(N52/N18,0) -> 0.064243396 | O74: =IFERROR(O52/O18,0) -> 0.040491136
B75: ROE | C75: =IFERROR(AVERAGE(D75:G75),0) -> 0.096076035 | D75: =L75 -> 0.12386993 | E75: =M75 -> 0.063998626 | F75: =N75 -> 0.1081815 | G75: =O75 -> 0.088254088 | K75: ROE | L75: =IFERROR(L52/L32,0) -> 0.12386993 | M75: =IFERROR(M52/M32,0) -> 0.063998626 | N75: =IFERROR(N52/N32,0) -> 0.1081815 | O75: =IFERROR(O52/O32,0) -> 0.088254088
B76: ROC | C76: =IFERROR(AVERAGE(D76:G76),0) -> 0.07713212 | D76: =L76 -> 0.081317431 | E76: =M76 -> 0.05095463 | F76: =N76 -> 0.089675738 | G76: =O76 -> 0.086580679 | K76: ROC | L76: =IFERROR((L44*(1-IFERROR(L50/L49,0)))/(L21+L25+L32),0) -> 0.081317431 | M76: =IFERROR((M44*(1-IFERROR(M50/M49,0)))/(M21+M25+M32),0) -> 0.05095463 | N76: =IFERROR((N44*(1-IFERROR(N50/N49,0)))/(N21+N25+N32),0) -> 0.089675738 | O76: =IFERROR((O44*(1-IFERROR(O50/O49,0)))/(O21+O25+O32),0) -> 0.086580679
B77: ROIC | C77: =IFERROR(AVERAGE(D77:G77),0) -> 0.067278452 | D77: =L77 -> 0.069105277 | E77: =M77 -> 0.041743686 | F77: =N77 -> 0.076029659 | G77: =O77 -> 0.082235187 | K77: ROIC | L77: =IFERROR((L44*(1-IFERROR(L50/L49,0)))/(L17+(L11-L6-L23)),0) -> 0.069105277 | M77: =IFERROR((M44*(1-IFERROR(M50/M49,0)))/(M17+(M11-M6-M23)),0) -> 0.041743686 | N77: =IFERROR((N44*(1-IFERROR(N50/N49,0)))/(N17+(N11-N6-N23)),0) -> 0.076029659 | O77: =IFERROR((O44*(1-IFERROR(O50/O49,0)))/(O17+(O11-O6-O23)),0) -> 0.082235187
B78: ROCE | C78: =IFERROR(AVERAGE(D78:G78),0) -> 0.063296274 | D78: =L78 -> 0.065022443 | E78: =M78 -> 0.040839796 | F78: =N78 -> 0.073873618 | G78: =O78 -> 0.07344924 | K78: ROCE | L78: =IFERROR((L44*(1-IFERROR(L50/L49,0)))/(L18-L23),0) -> 0.065022443 | M78: =IFERROR((M44*(1-IFERROR(M50/M49,0)))/(M18-M23),0) -> 0.040839796 | N78: =IFERROR((N44*(1-IFERROR(N50/N49,0)))/(N18-N23),0) -> 0.073873618 | O78: =IFERROR((O44*(1-IFERROR(O50/O49,0)))/(O18-O23),0) -> 0.07344924

Sheet Conoco
A1: Company Fundamentals - Balance Sheet
A2: Company Name | B2: ConocoPhillips (COP.N)
A3: Country of Exchange | B3: United States of America
A4: Country of Headquarters | B4: United States of America
A5: TRBC Industry Group | B5: Oil & Gas
A6: CF Template | B6: IND
A7: Consolidation Basis | B7: Consolidated
A8: Scaling | B8: Millions
A9: Period | B9: Annual
A10: Export Date | B10: 46295.614
A11: Statement Data | B11: 2024 | C11: 2025
A12: Period End Date | B12: 45657 | C12: 46022
A13: Standardized Currency | B13: USD | C13: USD
A14: Balance Sheet - Standardized (Currency: US Dollar)
A15: Field Name | B15: 30-12-2024 | C15: 30-12-2025
A16: Current Assets
A17: Cash & Short-Term Investments | B17: 6114 | C17: 6981
A18: Cash & Cash Equivalents | B18: 5607 | C18: 6497
A19: Short-Term Investments - Total | B19: 507 | C19: 484
A20: Loans & Receivables - Net - Short-Term | B20: 6695 | C20: 5813
A21: Trade Accounts & Trade Notes Receivable - Net | B21: 6695 | C21: 5813
A22: Trade Accounts & Trade Notes Receivable - Gross | B22: 6702 | C22: 5817
A23: Provision - Trade Accounts & Trade Notes Receivable | B23: 7 | C23: 4
A24: Inventories - Total | B24: 1809 | C24: 1873
A25: Inventories - Raw Materials | B25: 902 | C25: 873
A26: Inventories - Finished Goods | B26: 907 | C26: 1000
A27: Prepaid Expenses - Short-Term | B27: 1029 | C27: 865
A28: Total Current Assets | B28: 15647 | C28: 15532
A29: Non-Current Assets
A30: Investments - Long-Term | B30: 1145 | C30: 1242
A31: Investments - Available for Sale/Held to Maturity - Long-Term | B31: 1145 | C31: 1242
A32: Investments in Associates, Joint Ventures and Unconsolidated Subsidiaries | B32: 8611 | C32: 8833
A33: Receivables & Loans - Long-Term | B33: 113 | C33: 110
A34: Accounts & Notes Receivable - Trade - Net - Long-Term | B34: 113 | C34: 110
A35: Property, Plant & Equipment - Net - Total | B35: 95373 | C35: 94189
A36: Property, Plant & Equipment - excluding Assets Leased Out - Net - Total | B36: 95373 | C36: 94189
A37: Property, Plant & Equipment - Gross - Total | B37: 176445 | C37: 184585
A38: Property, Plant & Equipment - excluding Assets Leased Out - Gross | B38: 176445 | C38: 184585
A39: Right of Use Tangible Assets - Total - Gross | B39: 1017 | C39: 950
A40: Right of Use Tangible Assets - Operating Lease - Gross | B40: 1017 | C40: 950
A41: Property, Plant & Equipment - Other - Gross | B41: 175428 | C41: 183635
... A47: Total Non-Current Assets | B47: 107133 | C47: 106407
A48: Total Assets
A49: Total Assets | B49: 122780 | C49: 121939
A50: Current Liabilities
A51: Trade Accounts Payable & Accruals - Short-Term | B51: 8300 | C51: 8734
A52: Trade Accounts & Trade Notes Payable - Short-Term | B52: 6044 | C52: 6218
A53: Accrued Expenses - Short-Term | B53: 2256 | C53: 2516
A54: Short-Term Debt & Current Portion of Long-Term Debt | B54: 1035 | C54: 1020
A55: Current Portion of Long-Term Debt including Capitalized Leases | B55: 1035 | C55: 1020
A56: Current Portion of Long-Term Debt excluding Capitalized Leases | B56: 743 | C56: 714
A57: Capitalized Leases - Current Portion | B57: 292 | C57: 306
A58: Income Taxes - Payable - Short-Term | B58: 2460 | C58: 1835
A59: Operating Lease Liabilities - Current Portion/Short-Term | B59: 329 | C59: 383
A60: Total Current Liabilities | B60: 12124 | C60: 11972
A61: Non-Current Liabilities
A62: Debt - Long-Term - Total | B62: 23289 | C62: 22424
A63: Long-Term Debt excluding Capitalized Leases | B63: 22641 | C63: 21929
A64: Debt - Non-Convertible - Long-Term | B64: 22641 | C64: 21929
A65: Capitalized Lease Obligations - Long-Term | B65: 648 | C65: 495
A66: Deferred Tax & Investment Tax Credits - Long-Term | B66: 11426 | C66: 12237
A67: Deferred Tax - Liability - Long-Term | B67: 11426 | C67: 12237
A68: Operating Lease Liabilities - Long-Term | B68: 695 | C68: 567
A69: Other Non-Current Liabilities - Total | B69: 10450 | C69: 10252
A70: Provisions - Long-Term | B70: 9111 | C70: 9183
A71: Post Employment Benefits - Pension & Other - Long-Term | B71: 1022 | C71: 969
A72: Asset Retirement Obligation - Long-Term | B72: 8089 | C72: 8214
A73: Other Non-Current Liabilities | B73: 1339 | C73: 1069
A74: Total Non-Current Liabilities | B74: 45860 | C74: 45480
A75: Total Liabilities
A76: Total Liabilities | B76: 57984 | C76: 57452
A77: Shareholders' Equity
A78: Shareholders' Equity - Attributable to Parent Shareholders - Total | B78: 64796 | C78: 64487
A79: Common Equity Attributable to Parent Shareholders | B79: 64796 | C79: 64487
A80: Common Stock - Treasury/Repurchased | B80: 71152 | C80: 76217
A81: Common Equity - Contributed | B81: 77552 | C81: 77751
A82: Common Stock - Issued & Paid | B82: 23 | C82: 23
A83: Common Stock - Additional Paid in Capital including Option Reserve | B83: 77529 | C83: 77728
A84: Equity - Non-Contributed - Reserves & Retained Earnings | B84: 58396 | C84: 62953
A85: Retained Earnings - Total | B85: 64869 | C85: 68864
A86: Comprehensive Income - Accumulated - Total | B86: -6473 | C86: -5911
A87: Investments - Unrealized Gain/Loss | B87: 3 | C87: 8
A88: Hedging Reserves | B88: 18 | C88: 18
A89: Foreign Currency Translation Adjustment - Accumulated | B89: -6104 | C89: -5602
... A91: Common Equity - Total | B91: 64796 | C91: 64487
A92: Total Shareholders' Equity
A93: Total Shareholders' Equity - including Minority Interest & Hybrid Debt | B93: 64796 | C93: 64487
A94: Total Liabilities & Shareholders' Equity
A95: Total Liabilities & Equity | B95: 122780 | C95: 121939
A96: Share/Per Share - Common
A97: Common Shares - Issued - Total | B97: 2250.67 | C97: 2253.52
A98: Common Shares - Outstanding - Total | B98: 1275.87 | C98: 1225.17
A99: Common Shares - Treasury - Total | B99: 974.81 | C99: 1028.35
A100: Common Shares - Authorized - Issue Specific | B100: 2500 | C100: 2500
A101: Common Shares - Issued - Issue Specific | B101: 2250.67 | C101: 2253.52
A102: Common Shares - Outstanding - Issue Specific | B102: 1275.87 | C102: 1225.17
A103: Common Shares - Treasury - Issue Specific | B103: 974.81 | C103: 1028.35
A104: Share/Per Share - Other
A105: Asset Allocation Factor - Issue Specific | B105: 1 | C105: 1
A106: Right of Use Tangible Assets
...

Sheet Chevron
A1: Company Fundamentals - Balance Sheet
A2: Company Name | B2: Chevron Corporation (CVX.N)
A3: Country of Exchange | B3: United States of America
A4: Country of Headquarters | B4: United States of America
A5: TRBC Industry Group | B5: Oil & Gas
A6: CF Template | B6: IND
A7: Consolidation Basis | B7: Consolidated
A8: Scaling | B8: Millions
A9: Period | B9: Annual
A10: Export Date | B10: 46295.613
A11: Statement Data | B11: 2024 | C11: 2025
A12: Period End Date | B12: 45657 | C12: 46022
A13: Standardized Currency | B13: USD | C13: USD
A14: Balance Sheet - Standardized (Currency: US Dollar)
A15: Field Name | B15: 30-12-2024 | C15: 30-12-2025
A16: Current Assets
A17: Cash & Short-Term Investments | B17: 6785 | C17: 6297
A18: Cash & Cash Equivalents | B18: 6781 | C18: 6293
A19: Short-Term Investments - Total | B19: 4 | C19: 4
A20: Loans & Receivables - Net - Short-Term | B20: 20684 | C20: 18075
A21: Trade Accounts & Trade Notes Receivable - Net | B21: 20684 | C21: 18075
A22: Trade Accounts & Trade Notes Receivable - Gross | B22: 20943 | C22: 18251
A23: Provision - Trade Accounts & Trade Notes Receivable | B23: 259 | C23: 176
A24: Inventories - Total | B24: 9074 | C24: 9711
A25: Inventories - Raw Materials | B25: 2584 | C25: 3071
A26: Inventories - Finished Goods | B26: 6490 | C26: 6640
A27: Prepaid Expenses - Short-Term | B27: 4087 | C27: 4295
A28: Other Current Assets - Total | B28: 281 | C28: 174
... A30: Total Current Assets | B30: 40911 | C30: 38552
A31: Non-Current Assets
A32: Investments - Long-Term | B32: 820 | C32: 830
A33: Investments - Available for Sale/Held to Maturity - Long-Term | B33: 820 | C33: 830
A34: Investments in Associates, Joint Ventures and Unconsolidated Subsidiaries | B34: 46618 | C34: 43037
A35: Receivables & Loans - Long-Term | B35: 877 | C35: 1035
A36: Loans - Long-Term | B36: 877 | C36: 1251
A37: Provision - Doubtful Accounts - Long-Term | C37: 216
A38: Property, Plant & Equipment - Net - Total | B38: 153114 | C38: 225783
A39: Property, Plant & Equipment - excluding Assets Leased Out - Net - Total | B39: 153114 | C39: 225783
A40: Right of Use Tangible Assets - Total - Net | B40: 5315 | C40: 6054
A41: Right of Use Tangible Assets - Operating Lease - Net | B41: 5315 | C41: 6054
A42: Property, Plant & Equipment - Other - Net | B42: 147799 | C42: 219729
A43: Property, Plant & Equipment - Gross - Total | B43: 351248 | C43: 441009
A44: Property, Plant & Equipment - excluding Assets Leased Out - Gross | B44: 351248 | C44: 441009
A45: Right of Use Tangible Assets - Total - Gross | B45: 5315 | C45: 6054
A46: Right of Use Tangible Assets - Operating Lease - Gross | B46: 5315 | C46: 6054
A47: Property, Plant & Equipment - Other - Gross | B47: 345933 | C47: 434955
A48: Property, Plant & Equipment - Accumulated Depreciation & Impairment - Total | B48: 198134 | C48: 215226
A49: Property, Plant & Equipment - excluding Assets Leased Out - Accumulated Depreciation & Impairment - Total | B49: 198134 | C49: 215226
... A58: Total Non-Current Assets | B58: 216027 | C58: 285460
A59: Total Assets
A60: Total Assets | B60: 256938 | C60: 324012
A61: Current Liabilities
A62: Trade Accounts Payable & Accruals - Short-Term | B62: 29046 | C62: 28212
A63: Trade Accounts & Trade Notes Payable - Short-Term | B63: 22079 | C63: 19280
A64: Accrued Expenses - Short-Term | B64: 6967 | C64: 8932
A65: Short-Term Debt & Current Portion of Long-Term Debt | B65: 4406 | C65: 977
A66: Short-Term Debt & Notes Payable | B66: 131 | C66: 96
A67: Current Portion of Long-Term Debt including Capitalized Leases | B67: 4275 | C67: 881
A68: Current Portion of Long-Term Debt excluding Capitalized Leases | B68: 4217 | C68: 95
A69: Capitalized Leases - Current Portion | B69: 58 | C69: 786
A70: Income Taxes - Payable - Short-Term | B70: 1872 | C70: 844
A71: Operating Lease Liabilities - Current Portion/Short-Term | B71: 1519 | C71: 1831
A72: Other Current Liabilities - Total | B72: 1715 | C72: 1523
A73: Other Current Liabilities | B73: 1715 | C73: 1523
A74: Total Current Liabilities | B74: 38558 | C74: 33387
A75: Non-Current Liabilities
A76: Debt - Long-Term - Total | B76: 20135 | C76: 39781
A77: Long-Term Debt excluding Capitalized Leases | B77: 19589 | C77: 39122
A78: Debt - Non-Convertible - Long-Term | B78: 19589 | C78: 39122
A79: Capitalized Lease Obligations - Long-Term | B79: 546 | C79: 659
A80: Deferred Tax & Investment Tax Credits - Long-Term | B80: 19137 | C80: 30014
A81: Deferred Tax - Liability - Long-Term | B81: 19137 | C81: 30014
A82: Operating Lease Liabilities - Long-Term | B82: 3551 | C82: 4154
A83: Other Non-Current Liabilities - Total | B83: 22400 | C83: 24500
A84: Provisions - Long-Term | B84: 3857 | C84: 4111
A85: Post Employment Benefits - Pension & Other - Long-Term | B85: 3857 | C85: 4111
A86: Other Non-Current Liabilities | B86: 18543 | C86: 20389
A87: Total Non-Current Liabilities | B87: 65223 | C87: 98449
A88: Total Liabilities
A89: Total Liabilities | B89: 103781 | C89: 131836
A90: Shareholders' Equity
A91: Shareholders' Equity - Attributable to Parent Shareholders - Total | B91: 152318 | C91: 186450
A92: Preferred Shareholders Equity | B92: 0 | C92: 0
A93: Preferred Stock - Non-Redeemable | B93: 0 | C93: 0
A94: Preferred Stock - Convertible - Non-Redeemable | B94: 0 | C94: 0
A95: Common Equity Attributable to Parent Shareholders | B95: 152318 | C95: 186450
A96: Common Stock - Treasury/Repurchased | B96: 74037 | C96: 51929
A97: Common Equity - Contributed | B97: 23503 | C97: 35718
A98: Common Stock - Issued & Paid | B98: 1832 | C98: 1832
A99: Common Stock - Additional Paid in Capital including Option Reserve | B99: 21671 | C99: 33886
A100: Equity - Non-Contributed - Reserves & Retained Earnings | B100: 202852 | C100: 202661
A101: Retained Earnings - Total | B101: 205852 | C101: 205365
A102: Comprehensive Income - Accumulated - Total | B102: -2760 | C102: -2464
... A109: Minority Interest - Equity | B109: 839 | C109: 5726
A110: Total Shareholders' Equity
A111: Total Shareholders' Equity - including Minority Interest & Hybrid Debt | B111: 153157 | C111: 192176
A112: Total Liabilities & Shareholders' Equity
A113: Total Liabilities & Equity | B113: 256938 | C113: 324012
A114: Share/Per Share - Common
A115: Common Shares - Issued - Total | B115: 2442.68 | C115: 2442.68
...

Sheet Exxon
A1: Company Fundamentals - Balance Sheet
A2: Company Name | B2: Exxonmobil Holdings Corp (XOM.N)
A3: Country of Exchange | B3: United States of America
A4: Country of Headquarters | B4: United States of America
A5: TRBC Industry Group | B5: Oil & Gas
A6: CF Template | B6: IND
A7: Consolidation Basis | B7: Consolidated
A8: Scaling | B8: Millions
A9: Period | B9: Annual
A10: Export Date | B10: 46295.61
A11: Statement Data | B11: 2024 | C11: 2025
A12: Period End Date | B12: 45657 | C12: 46022
A13: Standardized Currency | B13: USD | C13: USD
A14: Balance Sheet - Standardized (Currency: US Dollar)
A15: Field Name | B15: 30-12-2024 | C15: 30-12-2025
A16: Current Assets
A17: Cash & Short-Term Investments | B17: 23029 | C17: 10681
A18: Cash & Cash Equivalents | B18: 23029 | C18: 10681
A19: Loans & Receivables - Net - Short-Term | B19: 43681 | C19: 44562
A20: Trade Accounts & Trade Notes Receivable - Net | B20: 35282 | C20: 35744
A21: Trade Accounts & Trade Notes Receivable - Gross | B21: 35444 | C21: 36014
A22: Provision - Trade Accounts & Trade Notes Receivable | B22: 162 | C22: 270
A23: Loans - Short-Term | B23: 8399 | C23: 8818
A24: Inventories - Total | B24: 23524 | C24: 26302
A25: Inventories - Raw Materials | B25: 4080 | C25: 3323
A26: Inventories - Finished Goods | B26: 19444 | C26: 22979
A27: Other Current Assets - Total | B27: 1756 | C27: 1837
A28: Restricted Accounts - Short-Term | B28: 158 | C28: 0
... A30: Total Current Assets | B30: 91990 | C30: 83382
A31: Non-Current Assets
A32: Investments - Long-Term | B32: 343 | C32: 271
A33: Investments - Available for Sale/Held to Maturity - Long-Term | B33: 343 | C33: 271
A34: Investments in Associates, Joint Ventures and Unconsolidated Subsidiaries | B34: 34010 | C34: 32653
A35: Receivables & Loans - Long-Term | B35: 12847 | C35: 12393
A36: Accounts & Notes Receivable - Trade - Net - Long-Term | B36: 5763 | C36: 6263
A37: Loans - Long-Term | B37: 7084 | C37: 6130
A38: Property, Plant & Equipment - Net - Total | B38: 301441 | C38: 306597
A39: Property, Plant & Equipment - excluding Assets Leased Out - Net - Total | B39: 301441 | C39: 306597
A40: Property, Plant & Equipment - Gross - Total | B40: 561026 | C40: 577283
A41: Property, Plant & Equipment - excluding Assets Leased Out - Gross | B41: 561026 | C41: 577283
A42: Plant, Machinery & Equipment - Gross | B42: 530080 | C42: 544693
A43: Right of Use Tangible Assets - Total - Gross | B43: 7123 | C43: 7224
... A50: Total Non-Current Assets | B50: 361485 | C50: 365598
A51: Total Assets
A52: Total Assets | B52: 453475 | C52: 448980
A53: Current Liabilities
A54: Trade Accounts Payable & Accruals - Short-Term | B54: 49061 | C54: 50268
A55: Trade Accounts & Trade Notes Payable - Short-Term | B55: 36145 | C55: 36049
A56: Accrued Expenses - Short-Term | B56: 12916 | C56: 14219
A57: Short-Term Debt & Current Portion of Long-Term Debt | B57: 4961 | C57: 9303
A58: Short-Term Debt & Notes Payable | B58: 63 | C58: 3062
A59: Current Portion of Long-Term Debt including Capitalized Leases | B59: 4898 | C59: 6241
A60: Current Portion of Long-Term Debt excluding Capitalized Leases | B60: 4775 | C60: 6097
A61: Capitalized Leases - Current Portion | B61: 123 | C61: 144
A62: Income Taxes - Payable - Short-Term | B62: 4055 | C62: 2123
A63: Operating Lease Liabilities - Current Portion/Short-Term | B63: 1852 | C63: 1942
A64: Other Current Liabilities - Total | B64: 10378 | C64: 8694
A65: Other Current Liabilities | B65: 10378 | C65: 8694
A66: Total Current Liabilities | B66: 70307 | C66: 72330
A67: Non-Current Liabilities
A68: Debt - Long-Term - Total | B68: 36870 | C68: 34350
A69: Long-Term Debt excluding Capitalized Leases | B69: 34632 | C69: 31835
A70: Debt - Non-Convertible - Long-Term | B70: 34632 | C70: 31835
A71: Capitalized Lease Obligations - Long-Term | B71: 2238 | C71: 2515
A72: Deferred Tax & Investment Tax Credits - Long-Term | B72: 39042 | C72: 40216
A73: Deferred Tax - Liability - Long-Term | B73: 39042 | C73: 40216
A74: Operating Lease Liabilities - Long-Term | B74: 4626 | C74: 4892
A75: Other Non-Current Liabilities - Total | B75: 32024 | C75: 30566
A76: Provisions - Long-Term | B76: 9700 | C76: 8847
A77: Post Employment Benefits - Pension & Other - Long-Term | B77: 9700 | C77: 8847
A78: Other Non-Current Liabilities | B78: 22324 | C78: 21719
A79: Total Non-Current Liabilities | B79: 112562 | C79: 110024
A80: Total Liabilities
A81: Total Liabilities | B81: 182869 | C81: 182354
A82: Shareholders' Equity
A83: Shareholders' Equity - Attributable to Parent Shareholders - Total | B83: 263705 | C83: 259386
A84: Common Equity Attributable to Parent Shareholders | B84: 263705 | C84: 259386
A85: Common Stock - Treasury/Repurchased | B85: 238817 | C85: 258395
A86: Common Equity - Contributed | B86: 46238 | C86: 46150
A87: Common Stock - Issued & Paid | B87: 46238 | C87: 46150
A88: Equity - Non-Contributed - Reserves & Retained Earnings | B88: 456284 | C88: 471631
A89: Retained Earnings - Total | B89: 470903 | C89: 482494
A90: Comprehensive Income - Accumulated - Total | B90: -14619 | C90: -10863
A91: Foreign Currency Translation Adjustment - Accumulated | B91: -16166 | C91: -13398
A92: Comprehensive Income - Pension Liabilities | B92: 1547 | C92: 2535
A93: Common Equity - Total | B93: 263705 | C93: 259386
A94: Minority Interest - Equity | B94: 6901 | C94: 7240
A95: Total Shareholders' Equity
A96: Total Shareholders' Equity - including Minority Interest & Hybrid Debt | B96: 270606 | C96: 266626
A97: Total Liabilities & Shareholders' Equity
A98: Total Liabilities & Equity | B98: 453475 | C98: 448980
A99: Share/Per Share - Common
A100: Common Shares - Issued - Total | B100: 8019 | C100: 8019
A101: Common Shares - Outstanding - Total | B101: 4353 | C101: 4179
A102: Common Shares - Treasury - Total | B102: 3666 | C102: 3840
A103: Common Shares - Authorized - Issue Specific | B103: 9000 | C103: 9000
A104: Common Shares - Issued - Issue Specific | B104: 8019 | C104: 8019
A105: Common Shares - Outstanding - Issue Specific | B105: 4353 | C105: 4179
A106: Common Shares - Treasury - Issue Specific | B106: 3666 | C106: 3840
A107: Share/Per Share - Other
...

Sheet Valero
A1: Company Fundamentals - Balance Sheet
A2: Company Name | B2: Valero Energy Corp (VLO.N)
A3: Country of Exchange | B3: United States of America
A4: Country of Headquarters | B4: United States of America
A5: TRBC Industry Group | B5: Oil & Gas
A6: CF Template | B6: IND
A7: Consolidation Basis | B7: Consolidated
A8: Scaling | B8: Millions
A9: Period | B9: Annual
A10: Export Date | B10: 46296.613
A11: Statement Data | B11: 2024 | C11: 2025
A12: Period End Date | B12: 45657 | C12: 46022
A13: Standardized Currency | B13: USD | C13: USD
A14: Balance Sheet - Standardized (Currency: US Dollar)
A15: Field Name | B15: 30-12-2024 | C15: 30-12-2025
A16: Current Assets
A17: Cash & Short-Term Investments | B17: 4657 | C17: 4688
A18: Cash & Cash Equivalents | B18: 4657 | C18: 4688
A19: Loans & Receivables - Net - Short-Term | B19: 10708 | C19: 9877
A20: Trade Accounts & Trade Notes Receivable - Net | B20: 3919 | C20: 2974
A21: Trade Accounts & Trade Notes Receivable - Gross | B21: 3939 | C21: 2993
A22: Provision - Trade Accounts & Trade Notes Receivable | B22: 20 | C22: 19
A23: Income Tax - Receivables - Short-Term | B23: 272 | C23: 236
A24: Receivables - Other - Total | B24: 6517 | C24: 6667
A25: Inventories - Total | B25: 7761 | C25: 7591
A26: Inventories - Raw Materials | B26: 364 | C26: 406
A27: Inventories - Other - Total | B27: 7397 | C27: 7185
A28: Prepaid Expenses - Short-Term | B28: 611 | C28: 1054
A29: Total Current Assets | B29: 23737 | C29: 23210
A30: Non-Current Assets
A31: Investments in Associates, Joint Ventures and Unconsolidated Subsidiaries | B31: 695 | C31: 684
A32: Receivables & Loans - Long-Term | B32: 317 | C32: 347
A33: Receivables - Other - Net - Long-Term | B33: 317 | C33: 347
A34: Property, Plant & Equipment - Net - Total | B34: 30412 | C34: 28689
A35: Property, Plant & Equipment - excluding Assets Leased Out - Net - Total | B35: 30412 | C35: 28689
A36: Property, Plant & Equipment - Gross - Total | B36: 53466 | C36: 51163
A37: Property, Plant & Equipment - excluding Assets Leased Out - Gross | B37: 53466 | C37: 51163
A38: Land & Buildings - Gross | B38: 1647 | C38: 1591
A39: Land/Improvements - Gross | B39: 500 | C39: 509
A40: Buildings - Gross | B40: 1147 | C40: 1082
A41: Plant, Machinery & Equipment - Gross | B41: 41160 | C41: 32617
A42: Transportation Equipment - Gross | B42: 6013
A43: Construction in Progress - Gross | B43: 604 | C43: 617
A44: Right of Use Tangible Assets - Total - Gross | B44: 4446 | C44: 4469
A45: Right of Use Tangible Assets - Operating Lease - Gross | B45: 1098 | C45: 1072
A46: Right of Use Tangible Assets - Capital/Finance Lease - Gross | B46: 3348 | C46: 3397
A47: Property, Plant & Equipment - Other - Gross | B47: 5609 | C47: 11869
A48: Property, Plant & Equipment - Accumulated Depreciation & Impairment - Total | B48: 23054 | C48: 22474
A49: Property, Plant & Equipment - excluding Assets Leased Out - Accumulated Depreciation & Impairment - Total | B49: 23054 | C49: 22474
A50: Other Non-Current Assets - Total | B50: 4571 | C50: 4675
A51: Deferred Charges - Long-Term | B51: 3177 | C51: 3699
A52: Other Non-Current Assets | B52: 1394 | C52: 976
A53: Intangible Assets - Total - Net | B53: 411 | C53: 383
A54: Goodwill/Cost in Excess of Assets Purchased - Net | B54: 260 | C54: 260
... A56: Total Non-Current Assets | B56: 36406 | C56: 34778
A57: Total Assets
A58: Total Assets | B58: 60143 | C58: 57988
A59: Current Liabilities
A60: Trade Accounts Payable & Accruals - Short-Term | B60: 13972 | C60: 12488
A61: Trade Accounts & Trade Notes Payable - Short-Term | B61: 12092 | C61: 10139
A62: Accrued Expenses - Short-Term | B62: 1880 | C62: 2349
A63: Short-Term Debt & Current Portion of Long-Term Debt | B63: 743 | C63: 949
A64: Current Portion of Long-Term Debt including Capitalized Leases | B64: 743 | C64: 949
A65: Current Portion of Long-Term Debt excluding Capitalized Leases | B65: 499 | C65: 695
A66: Capitalized Leases - Current Portion | B66: 244 | C66: 254
A67: Income Taxes - Payable - Short-Term | B67: 170 | C67: 68
A68: Operating Lease Liabilities - Current Portion/Short-Term | B68: 378 | C68: 419
A69: Other Current Liabilities - Total | B69: 232 | C69: 185
A70: Deferred Income - Short-Term | B70: 164 | C70: 60
A71: Provisions - Short-Term | C71: 49
A72: Other Current Liabilities | B72: 68 | C72: 76
A73: Total Current Liabilities | B73: 15495 | C73: 14109
A74: Non-Current Liabilities
A75: Accounts Payable including Accrued Expenses - Long-Term | B75: 226 | C75: 200
A76: Accrued Expenses - Long-Term | B76: 226 | C76: 200
A77: Debt - Long-Term - Total | B77: 9720 | C77: 9670
A78: Long-Term Debt excluding Capitalized Leases | B78: 7586 | C78: 7452
A79: Debt - Non-Convertible - Long-Term | B79: 7586 | C79: 7452
A80: Capitalized Lease Obligations - Long-Term | B80: 2134 | C80: 2218
A81: Deferred Tax & Investment Tax Credits - Long-Term | B81: 5267 | C81: 5146
A82: Deferred Tax - Liability - Long-Term | B82: 5267 | C82: 5146
A83: Operating Lease Liabilities - Long-Term | B83: 699 | C83: 665
A84: Other Non-Current Liabilities - Total | B84: 1215 | C84: 1593
A85: Provisions - Long-Term | B85: 684 | C85: 1048
A86: Post Employment Benefits - Pension & Other - Long-Term | B86: 423 | C86: 423
A87: Asset Retirement Obligation - Long-Term | C87: 382
A88: Provisions - Environmental Obligations - Long-Term | B88: 261 | C88: 243
A89: Other Non-Current Liabilities | B89: 531 | C89: 545
A90: Total Non-Current Liabilities | B90: 17127 | C90: 17274
A91: Total Liabilities
A92: Total Liabilities | B92: 32622 | C92: 31383
A93: Shareholders' Equity
A94: Shareholders' Equity - Attributable to Parent Shareholders - Total | B94: 24512 | C94: 23725
A95: Common Equity Attributable to Parent Shareholders | B95: 24512 | C95: 23725
A96: Common Stock - Treasury/Repurchased | B96: 28178 | C96: 30753
A97: Common Equity - Contributed | B97: 6946 | C97: 6988
A98: Common Stock - Issued & Paid | B98: 7 | C98: 7
A99: Common Stock - Additional Paid in Capital including Option Reserve | B99: 6939 | C99: 6981
A100: Equity - Non-Contributed - Reserves & Retained Earnings | B100: 45744 | C100: 47490
A101: Retained Earnings - Total | B101: 47016 | C101: 47959
...

Sheet Biotech>>
C2: Average | D2: =L2 -> IQVIA | E2: =M2 -> Argenx | F2: =N2 -> Beone | G2: =O2 -> ICON | L2: IQVIA | M2: Argenx | N2: Beone | O2: ICON
B4: Balance Sheet | D4: % | E4: % | F4: % | G4: % | K4: Balance Sheet | L4: 2025 | M4: 2025 | N4: 2025 | O4: 2025
B6: Cash & Cash Equivalents | C6: =IFERROR(AVERAGE(D6:G6),0) -> 0.26583922 | D6: =IFERROR(L6/L$18,0) -> 0.06612343 | E6: =IFERROR(M6/M$18,0) -> 0.40209774 | F6: =IFERROR(N6/N$18,0) -> 0.55535093 | G6: =IFERROR(O6/O$18,0) -> 0.039784779 | K6: Cash & Cash Equivalents | L6: =SUMIF(INDIRECT("'"&L$2&"'!$A$1:$A$500"),$K6,INDIRECT("'"&L$2&"'!$C$1:$C$500")) -> 1980 | M6: =SUMIF(INDIRECT("'"&M$2&"'!$A$1:$A$500"),$K6,INDIRECT("'"&M$2&"'!$C$1:$C$500")) -> 3491.29 | N6: =SUMIF(INDIRECT("'"&N$2&"'!$A$1:$A$500"),$K6,INDIRECT("'"&N$2&"'!$C$1:$C$500")) -> 4547.53 | O6: =SUMIF(INDIRECT("'"&O$2&"'!$A$1:$A$500"),$K6,INDIRECT("'"&O$2&"'!$C$1:$C$500")) -> 647.29
B7: Short-Term Investments - Total | C7: =IFERROR(AVERAGE(D7:G7),0) -> 0.028661459 | D7: =IFERROR(L7/L$18,0) -> 0.0053767032 | E7: =IFERROR(M7/M$18,0) -> 0.10926913 | F7: =IFERROR(N7/N$18,0) -> 0 | G7: =IFERROR(O7/O$18,0) -> 0 | K7: Short-Term Investments - Total | L7: =SUMIF(INDIRECT("'"&L$2&"'!$A$1:$A$500"),$K7,INDIRECT("'"&L$2&"'!$C$1:$C$500")) -> 161 | M7: =SUMIF(INDIRECT("'"&M$2&"'!$A$1:$A$500"),$K7,INDIRECT("'"&M$2&"'!$C$1:$C$500")) -> 948.75 | N7: =SUMIF(INDIRECT("'"&N$2&"'!$A$1:$A$500"),$K7,INDIRECT("'"&N$2&"'!$C$1:$C$500")) -> 0 | O7: =SUMIF(INDIRECT("'"&O$2&"'!$A$1:$A$500"),$K7,INDIRECT("'"&O$2&"'!$C$1:$C$500")) -> 0
B8: Trade Accounts & Trade Notes Receivable - Net | C8: =IFERROR(AVERAGE(D8:G8),0) -> 0.12034977 | D8: =IFERROR(L8/L$18,0) -> 0.11354528 | E8: =IFERROR(M8/M$18,0) -> 0.17155628 | F8: =IFERROR(N8/N$18,0) -> 0.10564482 | G8: =IFERROR(O8/O$18,0) -> 0.090652676 | K8: Trade Accounts & Trade Notes Receivable - Net | L8: =SUMIF(INDIRECT("'"&L$2&"'!$A$1:$A$500"),$K8,INDIRECT("'"&L$2&"'!$C$1:$C$500")) -> 3400 | M8: =SUMIF(INDIRECT("'"&M$2&"'!$A$1:$A$500"),$K8,INDIRECT("'"&M$2&"'!$C$1:$C$500")) -> 1489.57 | N8: =SUMIF(INDIRECT("'"&N$2&"'!$A$1:$A$500"),$K8,INDIRECT("'"&N$2&"'!$C$1:$C$500")) -> 865.08 | O8: =SUMIF(INDIRECT("'"&O$2&"'!$A$1:$A$500"),$K8,INDIRECT("'"&O$2&"'!$C$1:$C$500")) -> 1474.9
B9: Inventories - Total | C9: =IFERROR(AVERAGE(D9:G9),0) -> 0.032203793 | D9: =IFERROR(L9/L$18,0) -> 0 | E9: =IFERROR(M9/M$18,0) -> 0.054537246 | F9: =IFERROR(N9/N$18,0) -> 0.074277926 | G9: =IFERROR(O9/O$18,0) -> 0 | K9: Inventories - Total | L9: =SUMIF(INDIRECT("'"&L$2&"'!$A$1:$A$500"),$K9,INDIRECT("'"&L$2&"'!$C$1:$C$500")) -> 0 | M9: =SUMIF(INDIRECT("'"&M$2&"'!$A$1:$A$500"),$K9,INDIRECT("'"&M$2&"'!$C$1:$C$500")) -> 473.53 | N9: =SUMIF(INDIRECT("'"&N$2&"'!$A$1:$A$500"),$K9,INDIRECT("'"&N$2&"'!$C$1:$C$500")) -> 608.23 | O9: =SUMIF(INDIRECT("'"&O$2&"'!$A$1:$A$500"),$K9,INDIRECT("'"&O$2&"'!$C$1:$C$500")) -> 0
B10: Other Current Assets | C10: =IFERROR(AVERAGE(D10:G10),0) -> 0.047883613 | D10: =IFERROR(L10/L$18,0) -> 0.023644136 | E10: =IFERROR(M10/M$18,0) -> 0.057120547 | F10: =IFERROR(N10/N$18,0) -> 0.025981337 | G10: =IFERROR(O10/O$18,0) -> 0.084788433 | K10: Other Current Assets | L10: =SUMIF(INDIRECT("'"&L$2&"'!$A$1:$A$500"),$K11,INDIRECT("'"&L$2&"'!$C$1:$C$500"))-SUM(L6:L9) -> 708 | M10: =SUMIF(INDIRECT("'"&M$2&"'!$A$1:$A$500"),$K11,INDIRECT("'"&M$2&"'!$C$1:$C$500"))-SUM(M6:M9) -> 495.96 | N10: =SUMIF(INDIRECT("'"&N$2&"'!$A$1:$A$500"),$K11,INDIRECT("'"&N$2&"'!$C$1:$C$500"))-SUM(N6:N9) -> 212.75 | O10: =SUMIF(INDIRECT("'"&O$2&"'!$A$1:$A$500"),$K11,INDIRECT("'"&O$2&"'!$C$1:$C$500"))-SUM(O6:O9) -> 1379.49
B11: Total Current Assets | C11: =IFERROR(AVERAGE(D11:G11),0) -> 0.49493785 | D11: =IFERROR(L11/L$18,0) -> 0.20868955 | E11: =IFERROR(M11/M$18,0) -> 0.79458094 | F11: =IFERROR(N11/N$18,0) -> 0.76125502 | G11: =IFERROR(O11/O$18,0) -> 0.21522589 | K11: Total Current Assets | L11: =SUM(L6:L10) -> 6249 | M11: =SUM(M6:M10) -> 6899.1 | N11: =SUM(N6:N10) -> 6233.59 | O11: =SUM(O6:O10) -> 3501.68
K12: Check Current Assets | L12: =ROUND(SUMIF(INDIRECT("'"&L$2&"'!$A$1:$A$500"),$K$11,INDIRECT("'"&L$2&"'!$C$1:$C$500"))-L11,2) -> 0 | M12: =ROUND(SUMIF(INDIRECT("'"&M$2&"'!$A$1:$A$500"),$K$11,INDIRECT("'"&M$2&"'!$C$1:$C$500"))-M11,2) -> 0 | N12: =ROUND(SUMIF(INDIRECT("'"&N$2&"'!$A$1:$A$500"),$K$11,INDIRECT("'"&N$2&"'!$C$1:$C$500"))-N11,2) -> 0 | O12: =ROUND(SUMIF(INDIRECT("'"&O$2&"'!$A$1:$A$500"),$K$11,INDIRECT("'"&O$2&"'!$C$1:$C$500"))-O11,2) -> 0
B13: Investments - Long-Term | C13: =IFERROR(AVERAGE(D13:G13),0) -> 0.004142382 | D13: =IFERROR(L13/L$18,0) -> 0.0036067326 | E13: =IFERROR(M13/M$18,0) -> 0.0054303447 | F13: =IFERROR(N13/N$18,0) -> 0.0075324507 | G13: =IFERROR(O13/O$18,0) -> 0 | K13: Investments - Long-Term | L13: =SUMIF(INDIRECT("'"&L$2&"'!$A$1:$A$500"),$K13,INDIRECT("'"&L$2&"'!$C$1:$C$500")) -> 108 | M13: =SUMIF(INDIRECT("'"&M$2&"'!$A$1:$A$500"),$K13,INDIRECT("'"&M$2&"'!$C$1:$C$500")) -> 47.15 | N13: =SUMIF(INDIRECT("'"&N$2&"'!$A$1:$A$500"),$K13,INDIRECT("'"&N$2&"'!$C$1:$C$500")) -> 61.68 | O13: =SUMIF(INDIRECT("'"&O$2&"'!$A$1:$A$500"),$K13,INDIRECT("'"&O$2&"'!$C$1:$C$500")) -> 0
B14: Property, Plant & Equipment - Net - Total | C14: =IFERROR(AVERAGE(D14:G14),0) -> 0.070967518 | D14: =IFERROR(L14/L$18,0) -> 0.027484638 | E14: =IFERROR(M14/M$18,0) -> 0.0055570336 | F14: =IFERROR(N14/N$18,0) -> 0.21858029 | G14: =IFERROR(O14/O$18,0) -> 0.032248111 | K14: Property, Plant & Equipment - Net - Total | L14: =SUMIF(INDIRECT("'"&L$2&"'!$A$1:$A$500"),$K14,INDIRECT("'"&L$2&"'!$C$1:$C$500")) -> 823 | M14: =SUMIF(INDIRECT("'"&M$2&"'!$A$1:$A$500"),$K14,INDIRECT("'"&M$2&"'!$C$1:$C$500")) -> 48.25 | N14: =SUMIF(INDIRECT("'"&N$2&"'!$A$1:$A$500"),$K14,INDIRECT("'"&N$2&"'!$C$1:$C$500")) -> 1789.86 | O14: =SUMIF(INDIRECT("'"&O$2&"'!$A$1:$A$500"),$K14,INDIRECT("'"&O$2&"'!$C$1:$C$500")) -> 524.67
B15: Intangible Assets - Total - Net | C15: =IFERROR(AVERAGE(D15:G15),0) -> 0.37396698 | D15: =IFERROR(L15/L$18,0) -> 0.72061181 | E15: =IFERROR(M15/M$18,0) -> 0.031338214 | F15: =IFERROR(N15/N$18,0) -> 0.0076570146 | G15: =IFERROR(O15/O$18,0) -> 0.73626089 | K15: Intangible Assets - Total - Net | L15: =SUMIF(INDIRECT("'"&L$2&"'!$A$1:$A$500"),$K15,INDIRECT("'"&L$2&"'!$C$1:$C$500")) -> 21578 | M15: =SUMIF(INDIRECT("'"&M$2&"'!$A$1:$A$500"),$K15,INDIRECT("'"&M$2&"'!$C$1:$C$500")) -> 272.1 | N15: =SUMIF(INDIRECT("'"&N$2&"'!$A$1:$A$500"),$K15,INDIRECT("'"&N$2&"'!$C$1:$C$500")) -> 62.7 | O15: =SUMIF(INDIRECT("'"&O$2&"'!$A$1:$A$500"),$K15,INDIRECT("'"&O$2&"'!$C$1:$C$500")) -> 11978.81
B16: Other Non-Current Assets | C16: =IFERROR(AVERAGE(D16:G16),0) -> 0.055985269 | D16: =IFERROR(L16/L$18,0) -> 0.039607267 | E16: =IFERROR(M16/M$18,0) -> 0.16309347 | F16: =IFERROR(N16/N$18,0) -> 0.0049752277 | G16: =IFERROR(O16/O$18,0) -> 0.016265115 | K16: Other Non-Current Assets | L16: =SUMIF(INDIRECT("'"&L$2&"'!$A$1:$A$500"),$K17,INDIRECT("'"&L$2&"'!$C$1:$C$500"))-SUM(L12:L15) -> 1186 | M16: =SUMIF(INDIRECT("'"&M$2&"'!$A$1:$A$500"),$K17,INDIRECT("'"&M$2&"'!$C$1:$C$500"))-SUM(M12:M15) -> 1416.09 | N16: =SUMIF(INDIRECT("'"&N$2&"'!$A$1:$A$500"),$K17,INDIRECT("'"&N$2&"'!$C$1:$C$500"))-SUM(N12:N15) -> 40.74 | O16: =SUMIF(INDIRECT("'"&O$2&"'!$A$1:$A$500"),$K17,INDIRECT("'"&O$2&"'!$C$1:$C$500"))-SUM(O12:O15) -> 264.63
B17: Total Non-Current Assets | C17: =IFERROR(AVERAGE(D17:G17),0) -> 0.50506215 | D17: =IFERROR(L17/L$18,0) -> 0.79131045 | E17: =IFERROR(M17/M$18,0) -> 0.20541906 | F17: =IFERROR(N17/N$18,0) -> 0.23874498 | G17: =IFERROR(O17/O$18,0) -> 0.78477411 | K17: Total Non-Current Assets | L17: =SUM(L13:L16) -> 23695 | M17: =SUM(M13:M16) -> 1783.59 | N17: =SUM(N13:N16) -> 1954.98 | O17: =SUM(O13:O16) -> 12768.11
B18: Total Assets | C18: =IFERROR(AVERAGE(D18:G18),0) -> 1 | D18: =IFERROR(L18/L$18,0) -> 1 | E18: =IFERROR(M18/M$18,0) -> 1 | F18: =IFERROR(N18/N$18,0) -> 1 | G18: =IFERROR(O18/O$18,0) -> 1 | K18: Total Assets | L18: =L17+L11 -> 29944 | M18: =M17+M11 -> 8682.69 | N18: =N17+N11 -> 8188.57 | O18: =O17+O11 -> 16269.79
K19: Check Total Assets | L19: =ROUND(SUMIF(INDIRECT("'"&L$2&"'!$A$1:$A$500"),$K$18,INDIRECT("'"&L$2&"'!$C$1:$C$500"))-L18,2) -> 0 | M19: =ROUND(SUMIF(INDIRECT("'"&M$2&"'!$A$1:$A$500"),$K$18,INDIRECT("'"&M$2&"'!$C$1:$C$500"))-M18,2) -> 0.01 | N19: =ROUND(SUMIF(INDIRECT("'"&N$2&"'!$A$1:$A$500"),$K$18,INDIRECT("'"&N$2&"'!$C$1:$C$500"))-N18,2) -> 0 | O19: =ROUND(SUMIF(INDIRECT("'"&O$2&"'!$A$1:$A$500"),$K$18,INDIRECT("'"&O$2&"'!$C$1:$C$500"))-O18,2) -> -0.01
B20: Trade Accounts & Trade Notes Payable - Short-Term | C20: =IFERROR(AVERAGE(D20:G20),0) -> 0.040048569 | D20: =IFERROR(L20/L$18,0) -> 0.026048624 | E20: =IFERROR(M20/M$18,0) -> 0.063836207 | F20: =IFERROR(N20/N$18,0) -> 0.058501057 | G20: =IFERROR(O20/O$18,0) -> 0.011808388 | K20: Trade Accounts & Trade Notes Payable - Short-Term | L20: =SUMIF(INDIRECT("'"&L$2&"'!$A$1:$A$500"),$K20,INDIRECT("'"&L$2&"'!$C$1:$C$500")) -> 780 | M20: =SUMIF(INDIRECT("'"&M$2&"'!$A$1:$A$500"),$K20,INDIRECT("'"&M$2&"'!$C$1:$C$500")) -> 554.27 | N20: =SUMIF(INDIRECT("'"&N$2&"'!$A$1:$A$500"),$K20,INDIRECT("'"&N$2&"'!$C$1:$C$500")) -> 479.04 | O20: =SUMIF(INDIRECT("'"&O$2&"'!$A$1:$A$500"),$K20,INDIRECT("'"&O$2&"'!$C$1:$C$500")) -> 192.12
B21: Short-Term Debt & Current Portion of Long-Term Debt | C21: =IFERROR(AVERAGE(D21:G21),0) -> 0.027344937 | D21: =IFERROR(L21/L$18,0) -> 0.06164841 | E21: =IFERROR(M21/M$18,0) -> 0.0012473093 | F21: =IFERROR(N21/N$18,0) -> 0.013923066 | G21: =IFERROR(O21/O$18,0) -> 0.032560961 | K21: Short-Term Debt & Current Portion of Long-Term Debt | L21: =SUMIF(INDIRECT("'"&L$2&"'!$A$1:$A$500"),$K21,INDIRECT("'"&L$2&"'!$C$1:$C$500")) -> 1846 | M21: =SUMIF(INDIRECT("'"&M$2&"'!$A$1:$A$500"),$K21,INDIRECT("'"&M$2&"'!$C$1:$C$500")) -> 10.83 | N21: =SUMIF(INDIRECT("'"&N$2&"'!$A$1:$A$500"),$K21,INDIRECT("'"&N$2&"'!$C$1:$C$500")) -> 114.01 | O21: =SUMIF(INDIRECT("'"&O$2&"'!$A$1:$A$500"),$K21,INDIRECT("'"&O$2&"'!$C$1:$C$500")) -> 529.76
B22: Other Current Liabilities | C22: =IFERROR(AVERAGE(D22:G22),0) -> 0.14517893 | D22: =IFERROR(L22/L$18,0) -> 0.19075608 | E22: =IFERROR(M22/M$18,0) -> 0.086964984 | F22: =IFERROR(N22/N$18,0) -> 0.15091524 | G22: =IFERROR(O22/O$18,0) -> 0.15207941 | K22: Other Current Liabilities | L22: =SUMIF(INDIRECT("'"&L$2&"'!$A$1:$A$500"),$K23,INDIRECT("'"&L$2&"'!$C$1:$C$500"))-SUM(L20:L21) -> 5712 | M22: =SUMIF(INDIRECT("'"&M$2&"'!$A$1:$A$500"),$K23,INDIRECT("'"&M$2&"'!$C$1:$C$500"))-SUM(M20:M21) -> 755.09 | N22: =SUMIF(INDIRECT("'"&N$2&"'!$A$1:$A$500"),$K23,INDIRECT("'"&N$2&"'!$C$1:$C$500"))-SUM(N20:N21) -> 1235.78 | O22: =SUMIF(INDIRECT("'"&O$2&"'!$A$1:$A$500"),$K23,INDIRECT("'"&O$2&"'!$C$1:$C$500"))-SUM(O20:O21) -> 2474.3
B23: Total Current Liabilities | C23: =IFERROR(AVERAGE(D23:G23),0) -> 0.21257243 | D23: =IFERROR(L23/L$18,0) -> 0.27845311 | E23: =IFERROR(M23/M$18,0) -> 0.1520485 | F23: =IFERROR(N23/N$18,0) -> 0.22333936 | G23: =IFERROR(O23/O$18,0) -> 0.19644876 | K23: Total Current Liabilities | L23: =SUM(L20:L22) -> 8338 | M23: =SUM(M20:M22) -> 1320.19 | N23: =SUM(N20:N22) -> 1828.83 | O23: =SUM(O20:O22) -> 3196.18
K24: Check Current Liabilities | L24: =ROUND(SUMIF(INDIRECT("'"&L$2&"'!$A$1:$A$500"),$K$23,INDIRECT("'"&L$2&"'!$C$1:$C$500"))-L23,2) -> 0 | M24: =ROUND(SUMIF(INDIRECT("'"&M$2&"'!$A$1:$A$500"),$K$23,INDIRECT("'"&M$2&"'!$C$1:$C$500"))-M23,2) -> 0 | N24: =ROUND(SUMIF(INDIRECT("'"&N$2&"'!$A$1:$A$500"),$K$23,INDIRECT("'"&N$2&"'!$C$1:$C$500"))-N23,2) -> 0 | O24: =ROUND(SUMIF(INDIRECT("'"&O$2&"'!$A$1:$A$500"),$K$23,INDIRECT("'"&O$2&"'!$C$1:$C$500"))-O23,2) -> 0
B25: Debt - Long-Term - Total | C25: =IFERROR(AVERAGE(D25:G25),0) -> 0.21819869 | D25: =IFERROR(L25/L$18,0) -> 0.47074539 | E25: =IFERROR(M25/M$18,0) -> 0.0041841872 | F25: =IFERROR(N25/N$18,0) -> 0.2213036 | G25: =IFERROR(O25/O$18,0) -> 0.17656159 | K25: Debt - Long-Term - Total | L25: =SUMIF(INDIRECT("'"&L$2&"'!$A$1:$A$500"),$K25,INDIRECT("'"&L$2&"'!$C$1:$C$500")) -> 14096 | M25: =SUMIF(INDIRECT("'"&M$2&"'!$A$1:$A$500"),$K25,INDIRECT("'"&M$2&"'!$C$1:$C$500")) -> 36.33 | N25: =SUMIF(INDIRECT("'"&N$2&"'!$A$1:$A$500"),$K25,INDIRECT("'"&N$2&"'!$C$1:$C$500")) -> 1812.16 | O25: =SUMIF(INDIRECT("'"&O$2&"'!$A$1:$A$500"),$K25,INDIRECT("'"&O$2&"'!$C$1:$C$500")) -> 2872.62
B26: Other Non-Current Liabilities | C26: =IFERROR(AVERAGE(D26:G26),0) -> 0.027724485 | D26: =IFERROR(L26/L$18,0) -> 0.029388191 | E26: =IFERROR(M26/M$18,0) -> 0.00035588049 | F26: =IFERROR(N26/N$18,0) -> 0.019223137 | G26: =IFERROR(O26/O$18,0) -> 0.061930732 | K26: Other Non-Current Liabilities | L26: =SUMIF(INDIRECT("'"&L$2&"'!$A$1:$A$500"),$K27,INDIRECT("'"&L$2&"'!$C$1:$C$500"))-L25 -> 880 | M26: =SUMIF(INDIRECT("'"&M$2&"'!$A$1:$A$500"),$K27,INDIRECT("'"&M$2&"'!$C$1:$C$500"))-M25 -> 3.09 | N26: =SUMIF(INDIRECT("'"&N$2&"'!$A$1:$A$500"),$K27,INDIRECT("'"&N$2&"'!$C$1:$C$500"))-N25 -> 157.41 | O26: =SUMIF(INDIRECT("'"&O$2&"'!$A$1:$A$500"),$K27,INDIRECT("'"&O$2&"'!$C$1:$C$500"))-O25 -> 1007.6
B27: Total Non-Current Liabilities | C27: =IFERROR(AVERAGE(D27:G27),0) -> 0.24592318 | D27: =IFERROR(L27/L$18,0) -> 0.50013358 | E27: =IFERROR(M27/M$18,0) -> 0.0045400677 | F27: =IFERROR(N27/N$18,0) -> 0.24052673 | G27: =IFERROR(O27/O$18,0) -> 0.23849232 | K27: Total Non-Current Liabilities | L27: =SUM(L25:L26) -> 14976 | M27: =SUM(M25:M26) -> 39.42 | N27: =SUM(N25:N26) -> 1969.57 | O27: =SUM(O25:O26) -> 3880.22
B28: Total Liabilities | C28: =IFERROR(AVERAGE(D28:G28),0) -> 0.45849561 | D28: =IFERROR(L28/L$18,0) -> 0.7785867 | E28: =IFERROR(M28/M$18,0) -> 0.15658857 | F28: =IFERROR(N28/N$18,0) -> 0.4638661 | G28: =IFERROR(O28/O$18,0) -> 0.43494108 | K28: Total Liabilities | L28: =SUM(L27,L23) -> 23314 | M28: =SUM(M27,M23) -> 1359.61 | N28: =SUM(N27,N23) -> 3798.4 | O28: =SUM(O27,O23) -> 7076.4
K29: Check Total Liabilities | L29: =ROUND(SUMIF(INDIRECT("'"&L$2&"'!$A$1:$A$500"),$K$28,INDIRECT("'"&L$2&"'!$C$1:$C$500"))-L28,2) -> 0 | M29: =ROUND(SUMIF(INDIRECT("'"&M$2&"'!$A$1:$A$500"),$K$28,INDIRECT("'"&M$2&"'!$C$1:$C$500"))-M28,2) -> 0 | N29: =ROUND(SUMIF(INDIRECT("'"&N$2&"'!$A$1:$A$500"),$K$28,INDIRECT("'"&N$2&"'!$C$1:$C$500"))-N28,2) -> 0 | O29: =ROUND(SUMIF(INDIRECT("'"&O$2&"'!$A$1:$A$500"),$K$28,INDIRECT("'"&O$2&"'!$C$1:$C$500"))-O28,2) -> 0
B30: Common Equity - Total | C30: =IFERROR(AVERAGE(D30:G30),0) -> 0.54044421 | D30: =IFERROR(L30/L$18,0) -> 0.21717205 | E30: =IFERROR(M30/M$18,0) -> 0.84341258 | F30: =IFERROR(N30/N$18,0) -> 0.5361339 | G30: =IFERROR(O30/O$18,0) -> 0.56505831 | K30: Common Equity - Total | L30: =SUMIF(INDIRECT("'"&L$2&"'!$A$1:$A$500"),$K30,INDIRECT("'"&L$2&"'!$C$1:$C$500")) -> 6503 | M30: =SUMIF(INDIRECT("'"&M$2&"'!$A$1:$A$500"),$K30,INDIRECT("'"&M$2&"'!$C$1:$C$500")) -> 7323.09 | N30: =SUMIF(INDIRECT("'"&N$2&"'!$A$1:$A$500"),$K30,INDIRECT("'"&N$2&"'!$C$1:$C$500")) -> 4390.17 | O30: =SUMIF(INDIRECT("'"&O$2&"'!$A$1:$A$500"),$K30,INDIRECT("'"&O$2&"'!$C$1:$C$500")) -> 9193.38
B31: Other Shareholders' Equity | C31: =IFERROR(AVERAGE(D31:G31),0) -> 0.0010603126 | D31: =IFERROR(L31/L$18,0) -> 0.0042412503 | E31: =IFERROR(M31/M$18,0) -> 0 | F31: =IFERROR(N31/N$18,0) -> 0 | G31: =IFERROR(O31/O$18,0) -> 0 | K31: Other Shareholders' Equity | L31: =SUMIF(INDIRECT("'"&L$2&"'!$A$1:$A$500"),$K32,INDIRECT("'"&L$2&"'!$C$1:$C$500"))-L30 -> 127 | M31: =SUMIF(INDIRECT("'"&M$2&"'!$A$1:$A$500"),$K32,INDIRECT("'"&M$2&"'!$C$1:$C$500"))-M30 -> 0 | N31: =SUMIF(INDIRECT("'"&N$2&"'!$A$1:$A$500"),$K32,INDIRECT("'"&N$2&"'!$C$1:$C$500"))-N30 -> 0 | O31: =SUMIF(INDIRECT("'"&O$2&"'!$A$1:$A$500"),$K32,INDIRECT("'"&O$2&"'!$C$1:$C$500"))-O30 -> 0
B32: Total Shareholders' Equity - including Minority Interest & Hybrid Debt | C32: =IFERROR(AVERAGE(D32:G32),0) -> 0.54150452 | D32: =IFERROR(L32/L$18,0) -> 0.2214133 | E32: =IFERROR(M32/M$18,0) -> 0.84341258 | F32: =IFERROR(N32/N$18,0) -> 0.5361339 | G32: =IFERROR(O32/O$18,0) -> 0.56505831 | K32: Total Shareholders' Equity - including Minority Interest & Hybrid Debt | L32: =SUM(L30:L31) -> 6630 | M32: =SUM(M30:M31) -> 7323.09 | N32: =SUM(N30:N31) -> 4390.17 | O32: =SUM(O30:O31) -> 9193.38
B33: Total Liabilities & Equity | C33: =IFERROR(AVERAGE(D33:G33),0) -> 1.0000001 | D33: =IFERROR(L33/L$18,0) -> 1 | E33: =IFERROR(M33/M$18,0) -> 1.0000012 | F33: =IFERROR(N33/N$18,0) -> 1 | G33: =IFERROR(O33/O$18,0) -> 0.99999939 | K33: Total Liabilities & Equity | L33: =L32+L28 -> 29944 | M33: =M32+M28 -> 8682.7 | N33: =N32+N28 -> 8188.57 | O33: =O32+O28 -> 16269.78
B34: Check | K34: Check Balance | L34: =ROUND(L18-L33,2) -> 0 | M34: =ROUND(M18-M33,2) -> -0.01 | N34: =ROUND(N18-N33,2) -> 0 | O34: =ROUND(O18-O33,2) -> 0.01
B36: Financial Statement | K36: Financial Statement | L36: 2025 | M36: 2025 | N36: 2025 | O36: 2025
B37: Revenue from Business Activities - Total | C37: =IFERROR(AVERAGE(D37:G37),0) -> 1 | D37: =IFERROR(L37/L$37,0) -> 1 | E37: =IFERROR(M37/M$37,0) -> 1 | F37: =IFERROR(N37/N$37,0) -> 1 | G37: =IFERROR(O37/O$37,0) -> 1 | K37: Revenue from Business Activities - Total | L37: =SUMIF(INDIRECT("'"&L$2&"'!$A$1:$A$500"),$K37,INDIRECT("'"&L$2&"'!$C$1:$C$500")) -> 16310 | M37: =SUMIF(INDIRECT("'"&M$2&"'!$A$1:$A$500"),$K37,INDIRECT("'"&M$2&"'!$C$1:$C$500")) -> 4151.32 | N37: =SUMIF(INDIRECT("'"&N$2&"'!$A$1:$A$500"),$K37,INDIRECT("'"&N$2&"'!$C$1:$C$500")) -> 5343.03 | O37: =SUMIF(INDIRECT("'"&O$2&"'!$A$1:$A$500"),$K37,INDIRECT("'"&O$2&"'!$C$1:$C$500")) -> 8251.34
B38: Cost of Sales | C38: =IFERROR(AVERAGE(D38:G38),0) -> 0.43841282 | D38: =IFERROR(L38/L$37,0) -> 0.73721643 | E38: =IFERROR(M38/M$37,0) -> 0.10856065 | F38: =IFERROR(N38/N$37,0) -> 0.12512376 | G38: =IFERROR(O38/O$37,0) -> 0.78275044 | K38: Cost of Operating Revenue | L38: =SUMIF(INDIRECT("'"&L$2&"'!$A$1:$A$500"),$K38,INDIRECT("'"&L$2&"'!$C$1:$C$500")) -> 12024 | M38: =SUMIF(INDIRECT("'"&M$2&"'!$A$1:$A$500"),$K38,INDIRECT("'"&M$2&"'!$C$1:$C$500")) -> 450.67 | N38: =SUMIF(INDIRECT("'"&N$2&"'!$A$1:$A$500"),$K38,INDIRECT("'"&N$2&"'!$C$1:$C$500")) -> 668.54 | O38: =SUMIF(INDIRECT("'"&O$2&"'!$A$1:$A$500"),$K38,INDIRECT("'"&O$2&"'!$C$1:$C$500")) -> 6458.74
B39: Gross Profit - Industrials/Property - Total | C39: =IFERROR(AVERAGE(D39:G39),0) -> 0.56158718 | D39: =IFERROR(L39/L$37,0) -> 0.26278357 | E39: =IFERROR(M39/M$37,0) -> 0.89143935 | F39: =IFERROR(N39/N$37,0) -> 0.87487624 | G39: =IFERROR(O39/O$37,0) -> 0.21724956 | K39: Gross Profit - Industrials/Property - Total | L39: =L37-L38 -> 4286 | M39: =M37-M38 -> 3700.65 | N39: =N37-N38 -> 4674.49 | O39: =O37-O38 -> 1792.6
B40: Selling, General & Administrative Expenses excluding Research & Development Expenses | C40: =IFERROR(AVERAGE(D40:G40),0) -> 0.2347643 | D40: =IFERROR(L40/L$37,0) -> 0.12256284 | E40: =IFERROR(M40/M$37,0) -> 0.33237621 | F40: =IFERROR(N40/N$37,0) -> 0.38957109 | G40: =IFERROR(O40/O$37,0) -> 0.094547068 | K40: Selling, General & Administrative Expenses excluding Research & Development Expenses | L40: =SUMIF( INDIRECT("'"&L$2&"'!$A$1:$A$500"), $K40, INDIRECT("'"&L$2&"'!$C$1:$C$500") ) -> 1999 | M40: =SUMIF( INDIRECT("'"&M$2&"'!$A$1:$A$500"), $K40, INDIRECT("'"&M$2&"'!$C$1:$C$500") ) -> 1379.8 | N40: =SUMIF( INDIRECT("'"&N$2&"'!$A$1:$A$500"), $K40, INDIRECT("'"&N$2&"'!$C$1:$C$500") ) -> 2081.49 | O40: =SUMIF( INDIRECT("'"&O$2&"'!$A$1:$A$500"), $K40, INDIRECT("'"&O$2&"'!$C$1:$C$500") ) -> 780.14
B41: Research & Development Expense - Supplemental | C41: =IFERROR(AVERAGE(D41:G41),0) -> 0.18178826 | D41: =IFERROR(L41/L$37,0) -> 0 | E41: =IFERROR(M41/M$37,0) -> 0.3255326 | F41: =IFERROR(N41/N$37,0) -> 0.40162043 | G41: =IFERROR(O41/O$37,0) -> 0 | K41: Research & Development Expense - Supplemental | L41: =SUMIF( INDIRECT("'"&L$2&"'!$A$1:$A$500"), $K41, INDIRECT("'"&L$2&"'!$C$1:$C$500") ) -> 0 | M41: =SUMIF( INDIRECT("'"&M$2&"'!$A$1:$A$500"), $K41, INDIRECT("'"&M$2&"'!$C$1:$C$500") ) -> 1351.39 | N41: =SUMIF( INDIRECT("'"&N$2&"'!$A$1:$A$500"), $K41, INDIRECT("'"&N$2&"'!$C$1:$C$500") ) -> 2145.87 | O41: =SUMIF( INDIRECT("'"&O$2&"'!$A$1:$A$500"), $K41, INDIRECT("'"&O$2&"'!$C$1:$C$500") ) -> 0
B42: — | C42: =IFERROR(AVERAGE(D42:G42),0) -> -0.0051284893 | D42: =IFERROR(L42/L$37,0) -> 0 | E42: =IFERROR(M42/M$37,0) -> -0.020513957 | F42: =IFERROR(N42/N$37,0) -> 0 | G42: =IFERROR(O42/O$37,0) -> 4.1333955e-17 | K42: Other | L42: =SUMIF(INDIRECT("'"&L$2&"'!$A$1:$A$500"),$K$43,INDIRECT("'"&L$2&"'!$C$1:$C$500"))-L38-L40-L41 -> 0 | M42: =SUMIF(INDIRECT("'"&M$2&"'!$A$1:$A$500"),$K$43,INDIRECT("'"&M$2&"'!$C$1:$C$500"))-M38-M40-M41 -> -85.16 | N42: =SUMIF(INDIRECT("'"&N$2&"'!$A$1:$A$500"),$K$43,INDIRECT("'"&N$2&"'!$C$1:$C$500"))-N38-N40-N41 -> 0 | O42: =SUMIF(INDIRECT("'"&O$2&"'!$A$1:$A$500"),$K$43,INDIRECT("'"&O$2&"'!$C$1:$C$500"))-O38-O40-O41 -> 3.4106051e-13
B43: Operating Expenses - Total | C43: =IFERROR(AVERAGE(D43:G43),0) -> 0.84983689 | D43: =IFERROR(L43/L$37,0) -> 0.85977928 | E43: =IFERROR(M43/M$37,0) -> 0.7459555 | F43: =IFERROR(N43/N$37,0) -> 0.91631527 | G43: =IFERROR(O43/O$37,0) -> 0.87729751 | K43: Operating Expenses - Total | L43: =SUM(L38,L40:L42) -> 14023 | M43: =SUM(M38,M40:M42) -> 3096.7 | N43: =SUM(N38,N40:N42) -> 4895.9 | O43: =SUM(O38,O40:O42) -> 7238.88
B44: Earnings before Interest & Taxes (EBIT) | C44: =IFERROR(AVERAGE(D44:G44),0) -> 0.15016311 | D44: =IFERROR(L44/L$37,0) -> 0.14022072 | E44: =IFERROR(M44/M$37,0) -> 0.2540445 | F44: =IFERROR(N44/N$37,0) -> 0.083684726 | G44: =IFERROR(O44/O$37,0) -> 0.12270249 | K44: Earnings before Interest & Taxes (EBIT) | L44: =L37-L43 -> 2287 | M44: =M37-M43 -> 1054.62 | N44: =N37-N43 -> 447.13 | O44: =O37-O43 -> 1012.46
B45: Depreciation, Depletion & Amortization - Total | C45: =IFERROR(AVERAGE(D45:G45),0) -> 0.037461328 | D45: =IFERROR(L45/L$37,0) -> 0.070141018 | E45: =IFERROR(M45/M$37,0) -> 0.0067689313 | F45: =IFERROR(N45/N$37,0) -> 0.026518661 | G45: =IFERROR(O45/O$37,0) -> 0.046416703 | K45: Depreciation, Depletion & Amortization - Total | L45: =SUMIF( INDIRECT("'"&L$2&"'!$A$1:$A$500"), $K45, INDIRECT("'"&L$2&"'!$C$1:$C$500") ) -> 1144 | M45: =SUMIF( INDIRECT("'"&M$2&"'!$A$1:$A$500"), $K45, INDIRECT("'"&M$2&"'!$C$1:$C$500") ) -> 28.1 | N45: =SUMIF( INDIRECT("'"&N$2&"'!$A$1:$A$500"), $K45, INDIRECT("'"&N$2&"'!$C$1:$C$500") ) -> 141.69 | O45: =SUMIF( INDIRECT("'"&O$2&"'!$A$1:$A$500"), $K45, INDIRECT("'"&O$2&"'!$C$1:$C$500") ) -> 383
B46: Earnings before Interest, Taxes, Depreciation & Amortization (EBITDA) | C46: =IFERROR(AVERAGE(D46:G46),0) -> 0.18762444 | D46: =IFERROR(L46/L$37,0) -> 0.21036174 | E46: =IFERROR(M46/M$37,0) -> 0.26081343 | F46: =IFERROR(N46/N$37,0) -> 0.11020339 | G46: =IFERROR(O46/O$37,0) -> 0.1691192 | K46: Earnings before Interest, Taxes, Depreciation & Amortization (EBITDA) | L46: =L44+L45 -> 3431 | M46: =M44+M45 -> 1082.72 | N46: =N44+N45 -> 588.82 | O46: =O44+O45 -> 1395.46
B47: Interest Expense - Net of (Interest Income) | C47: =IFERROR(AVERAGE(D47:G47),0) -> 0.0061025372 | D47: =IFERROR(L47/L$37,0) -> 0.041937462 | E47: =IFERROR(M47/M$37,0) -> -0.038303479 | F47: =IFERROR(N47/N$37,0) -> -0.0022964498 | G47: =IFERROR(O47/O$37,0) -> 0.023072616 | K47: Interest Expense - Net of (Interest Income) | L47: =SUMIF( INDIRECT("'"&L$2&"'!$A$1:$A$500"), $K47, INDIRECT("'"&L$2&"'!$C$1:$C$500") ) -> 684 | M47: =SUMIF( INDIRECT("'"&M$2&"'!$A$1:$A$500"), $K47, INDIRECT("'"&M$2&"'!$C$1:$C$500") ) -> -159.01 | N47: =SUMIF( INDIRECT("'"&N$2&"'!$A$1:$A$500"), $K47, INDIRECT("'"&N$2&"'!$C$1:$C$500") ) -> -12.27 | O47: =SUMIF( INDIRECT("'"&O$2&"'!$A$1:$A$500"), $K47, INDIRECT("'"&O$2&"'!$C$1:$C$500") ) -> 190.38
B48: Other | C48: =IFERROR(AVERAGE(D48:G48),0) -> -0.015519741 | D48: =IFERROR(L48/L$37,0) -> -0.00073574494 | E48: =IFERROR(M48/M$37,0) -> 0.015652853 | F48: =IFERROR(N48/N$37,0) -> -0.0079636461 | G48: =IFERROR(O48/O$37,0) -> -0.069032424 | K48: Other | L48: =SUMIF(INDIRECT("'"&L$2&"'!$A$1:$A$500"),$K$49,INDIRECT("'"&L$2&"'!$C$1:$C$500"))-L44+L47 -> -12 | M48: =SUMIF(INDIRECT("'"&M$2&"'!$A$1:$A$500"),$K$49,INDIRECT("'"&M$2&"'!$C$1:$C$500"))-M44+M47 -> 64.98 | N48: =SUMIF(INDIRECT("'"&N$2&"'!$A$1:$A$500"),$K$49,INDIRECT("'"&N$2&"'!$C$1:$C$500"))-N44+N47 -> -42.55 | O48: =SUMIF(INDIRECT("'"&O$2&"'!$A$1:$A$500"),$K$49,INDIRECT("'"&O$2&"'!$C$1:$C$500"))-O44+O47 -> -569.61
B49: Income before Taxes | C49: =IFERROR(AVERAGE(D49:G49),0) -> 0.12854083 | D49: =IFERROR(L49/L$37,0) -> 0.097547517 | E49: =IFERROR(M49/M$37,0) -> 0.30800083 | F49: =IFERROR(N49/N$37,0) -> 0.078017529 | G49: =IFERROR(O49/O$37,0) -> 0.030597454 | K49: Income before Taxes | L49: =L44-L47+L48 -> 1591 | M49: =M44-M47+M48 -> 1278.61 | N49: =N44-N47+N48 -> 416.85 | O49: =O44-O47+O48 -> 252.47
B50: Income Taxes | C50: =IFERROR(AVERAGE(D50:G50),0) -> 0.009833625 | D50: =IFERROR(L50/L$37,0) -> 0.015450644 | E50: =IFERROR(M50/M$37,0) -> -0.0032351156 | F50: =IFERROR(N50/N$37,0) -> 0.024315791 | G50: =IFERROR(O50/O$37,0) -> 0.0028031811 | K50: Income Taxes | L50: =SUMIF(INDIRECT("'"&L$2&"'!$A$1:$A$500"),$K$50,INDIRECT("'"&L$2&"'!$C$1:$C$500")) -> 252 | M50: =SUMIF(INDIRECT("'"&M$2&"'!$A$1:$A$500"),$K$50,INDIRECT("'"&M$2&"'!$C$1:$C$500")) -> -13.43 | N50: =SUMIF(INDIRECT("'"&N$2&"'!$A$1:$A$500"),$K$50,INDIRECT("'"&N$2&"'!$C$1:$C$500")) -> 129.92 | O50: =SUMIF(INDIRECT("'"&O$2&"'!$A$1:$A$500"),$K$50,INDIRECT("'"&O$2&"'!$C$1:$C$500")) -> 23.13
B51: Other | C51: =IFERROR(AVERAGE(D51:G51),0) -> 0.00032188841 | D51: =IFERROR(L51/L$37,0) -> 0.0012875536 | E51: =IFERROR(M51/M$37,0) -> 0 | F51: =IFERROR(N51/N$37,0) -> 0 | G51: =IFERROR(O51/O$37,0) -> 0 | K51: Other | L51: =SUMIF(INDIRECT("'"&L$2&"'!$A$1:$A$500"),$K$52,INDIRECT("'"&L$2&"'!$C$1:$C$500"))-(L49-L50) -> 21 | M51: =SUMIF(INDIRECT("'"&M$2&"'!$A$1:$A$500"),$K$52,INDIRECT("'"&M$2&"'!$C$1:$C$500"))-(M49-M50) -> 0 | N51: =SUMIF(INDIRECT("'"&N$2&"'!$A$1:$A$500"),$K$52,INDIRECT("'"&N$2&"'!$C$1:$C$500"))-(N49-N50) -> 0 | O51: =SUMIF(INDIRECT("'"&O$2&"'!$A$1:$A$500"),$K$52,INDIRECT("'"&O$2&"'!$C$1:$C$500"))-(O49-O50) -> 0
B52: Net Income after Minority Interest | C52: =IFERROR(AVERAGE(D52:G52),0) -> 0.1190291 | D52: =IFERROR(L52/L$37,0) -> 0.083384427 | E52: =IFERROR(M52/M$37,0) -> 0.31123594 | F52: =IFERROR(N52/N$37,0) -> 0.053701739 | G52: =IFERROR(O52/O$37,0) -> 0.027794273 | K52: Net Income after Minority Interest | L52: =L49-L50+L51 -> 1360 | M52: =M49-M50+M51 -> 1292.04 | N52: =N49-N50+N51 -> 286.93 | O52: =O49-O50+O51 -> 229.34
K53: Check Net Income | L53: =ROUND(SUMIF(INDIRECT("'"&L$2&"'!$A$1:$A$500"),$K$52,INDIRECT("'"&L$2&"'!$C$1:$C$500"))-L52,2) -> 0 | M53: =ROUND(SUMIF(INDIRECT("'"&M$2&"'!$A$1:$A$500"),$K$52,INDIRECT("'"&M$2&"'!$C$1:$C$500"))-M52,2) -> 0 | N53: =ROUND(SUMIF(INDIRECT("'"&N$2&"'!$A$1:$A$500"),$K$52,INDIRECT("'"&N$2&"'!$C$1:$C$500"))-N52,2) -> 0 | O53: =ROUND(SUMIF(INDIRECT("'"&O$2&"'!$A$1:$A$500"),$K$52,INDIRECT("'"&O$2&"'!$C$1:$C$500"))-O52,2) -> 0
B55: Indicadores de Liquidez (Liquidity Ratios) | K55: Indicadores de Liquidez (Liquidity Ratios)
B56: Razón corriente (CR) | C56: =IFERROR(AVERAGE(D56:G56),0) -> 2.6198486 | D56: =L56 -> 0.7494603 | E56: =M56 -> 5.2258387 | F56: =N56 -> 3.4085125 | G56: =O56 -> 1.0955829 | K56: Razón corriente (CR) | L56: =IFERROR(L11/L23,0) -> 0.7494603 | M56: =IFERROR(M11/M23,0) -> 5.2258387 | N56: =IFERROR(N11/N23,0) -> 3.4085125 | O56: =IFERROR(O11/O23,0) -> 1.0955829
B57: Prueba ácida (QR) | C57: =IFERROR(AVERAGE(D57:G57),0) -> 2.1949024 | D57: =L57 -> 0.66454785 | E57: =M57 -> 4.4914823 | F57: =N57 -> 2.9596026 | G57: =O57 -> 0.663977 | K57: Prueba ácida (QR) | L57: =IFERROR(SUM(L6:L8)/L23,0) -> 0.66454785 | M57: =IFERROR(SUM(M6:M8)/M23,0) -> 4.4914823 | N57: =IFERROR(SUM(N6:N8)/N23,0) -> 2.9596026 | O57: =IFERROR(SUM(O6:O8)/O23,0) -> 0.663977
B58: Capital de trabajo neto (NWC) (USD mm) | C58: =IFERROR(AVERAGE(D58:G58),0) -> 2050.0425 | D58: =L58 -> -2089 | E58: =M58 -> 5578.91 | F58: =N58 -> 4404.76 | G58: =O58 -> 305.5 | K58: Capital de trabajo neto (NWC) (USD mm) | L58: =L11-L23 -> -2089 | M58: =M11-M23 -> 5578.91 | N58: =N11-N23 -> 4404.76 | O58: =O11-O23 -> 305.5
B59: Administración de Activos (Efficiency Ratios) | C59: =IFERROR(AVERAGE(D59:G59),0) -> 0 | D59: =L59 -> 0 | E59: =M59 -> 0 | K59: Administración de Activos (Efficiency Ratios)
B60: Rotación de inventario (ITR) | C60: =IFERROR(AVERAGE(D60:G60),0) -> 0.55883642 | D60: =L60 -> 0 | E60: =M60 -> 1.0233662 | F60: =N60 -> 1.2119795 | G60: =O60 -> 0 | K60: Rotación de inventario (ITR) | L60: =IFERROR(L38/AVERAGE(L9,SUMIF(INDIRECT("'"&L$2&"'!$A$1:$A$500"),$K$9,INDIRECT("'"&L$2&"'!$B$1:$B$500"))),0) -> 0 | M60: =IFERROR(M38/AVERAGE(M9,SUMIF(INDIRECT("'"&M$2&"'!$A$1:$A$500"),$K$9,INDIRECT("'"&M$2&"'!$B$1:$B$500"))),0) -> 1.0233662 | N60: =IFERROR(N38/AVERAGE(N9,SUMIF(INDIRECT("'"&N$2&"'!$A$1:$A$500"),$K$9,INDIRECT("'"&N$2&"'!$B$1:$B$500"))),0) -> 1.2119795 | O60: =IFERROR(O38/AVERAGE(O9,SUMIF(INDIRECT("'"&O$2&"'!$A$1:$A$500"),$K$9,INDIRECT("'"&O$2&"'!$B$1:$B$500"))),0) -> 0
B61: Rotación de activos fijos netos (FAT) | C61: =IFERROR(AVERAGE(D61:G61),0) -> 31.141838 | D61: =L61 -> 19.81774 | E61: =M61 -> 86.03772 | F61: =N61 -> 2.9851664 | G61: =O61 -> 15.726723 | K61: Rotación de activos fijos netos (FAT) | L61: =IFERROR(L37/L14,0) -> 19.81774 | M61: =IFERROR(M37/M14,0) -> 86.03772 | N61: =IFERROR(N37/N14,0) -> 2.9851664 | O61: =IFERROR(O37/O14,0) -> 15.726723
B62: Rotación de activos totales (ATR) | C62: =IFERROR(AVERAGE(D62:G62),0) -> 0.5456134 | D62: =L62 -> 0.54468341 | E62: =M62 -> 0.4781145 | F62: =N62 -> 0.65249854 | G62: =O62 -> 0.50715713 | K62: Rotación de activos totales (ATR) | L62: =IFERROR(L37/L18,0) -> 0.54468341 | M62: =IFERROR(M37/M18,0) -> 0.4781145 | N62: =IFERROR(N37/N18,0) -> 0.65249854 | O62: =IFERROR(O37/O18,0) -> 0.50715713
B63: Días promedio de cartera (DSO) | C63: =IFERROR(AVERAGE(D63:G63),0) -> 82.849007 | D63: =L63 -> 76.088289 | E63: =M63 -> 130.96872 | F63: =N63 -> 59.096468 | G63: =O63 -> 65.242555 | K63: Días promedio de cartera (DSO) | L63: =IFERROR(L8/(L37/365),0) -> 76.088289 | M63: =IFERROR(M8/(M37/365),0) -> 130.96872 | N63: =IFERROR(N8/(N37/365),0) -> 59.096468 | O63: =IFERROR(O8/(O37/365),0) -> 65.242555
B64: Días promedio de inventario (DIO) | C64: =IFERROR(AVERAGE(D64:G64),0) -> 178.89681 | D64: =L64 -> 0 | E64: =M64 -> 383.51443 | F64: =N64 -> 332.0728 | G64: =O64 -> 0 | K64: Días promedio de inventario (DIO) | L64: =IFERROR(L9/(L38/365),0) -> 0 | M64: =IFERROR(M9/(M38/365),0) -> 383.51443 | N64: =IFERROR(N9/(N38/365),0) -> 332.0728 | O64: =IFERROR(O9/(O38/365),0) -> 0
B65: Periodo promedio de pago (DPO) | C65: =IFERROR(AVERAGE(D65:G65),0) -> 186.24512 | D65: =L65 -> 23.677645 | E65: =M65 -> 448.90618 | F65: =N65 -> 261.53947 | G65: =O65 -> 10.857195 | K65: Periodo promedio de pago (DPO) | L65: =IFERROR(L20/(L38/365),0) -> 23.677645 | M65: =IFERROR(M20/(M38/365),0) -> 448.90618 | N65: =IFERROR(N20/(N38/365),0) -> 261.53947 | O65: =IFERROR(O20/(O38/365),0) -> 10.857195
B66: Ciclo operativo (OC) | C66: =IFERROR(AVERAGE(D66:G66),0) -> 261.74582 | D66: =L66 -> 76.088289 | E66: =M66 -> 514.48315 | F66: =N66 -> 391.16927 | G66: =O66 -> 65.242555 | K66: Ciclo operativo (OC) | L66: =L63+L64 -> 76.088289 | M66: =M63+M64 -> 514.48315 | N66: =N63+N64 -> 391.16927 | O66: =O63+O64 -> 65.242555
B67: Ciclo de efectivo (CC) | C67: =IFERROR(AVERAGE(D67:G67),0) -> 75.500691 | D67: =L67 -> 52.410645 | E67: =M67 -> 65.576966 | F67: =N67 -> 129.62979 | G67: =O67 -> 54.385359 | K67: Ciclo de efectivo (CC) | L67: =L63+L64-L65 -> 52.410645 | M67: =M63+M64-M65 -> 65.576966 | N67: =N63+N64-N65 -> 129.62979 | O67: =O63+O64-O65 -> 54.385359
B68: Administración de Pasivos (Leverage Ratios) | K68: Administración de Pasivos (Leverage Ratios)
B69: Nivel de endeudamiento (Debt to Assets) | C69: =IFERROR(AVERAGE(D69:G69),0) -> 0.45849561 | D69: =L69 -> 0.7785867 | E69: =M69 -> 0.15658857 | F69: =N69 -> 0.4638661 | G69: =O69 -> 0.43494108 | K69: Nivel de endeudamiento (Debt to Assets) | L69: =IFERROR(L28/L18,0) -> 0.7785867 | M69: =IFERROR(M28/M18,0) -> 0.15658857 | N69: =IFERROR(N28/N18,0) -> 0.4638661 | O69: =IFERROR(O28/O18,0) -> 0.43494108
B70: Cobertura de intereses (Interest Coverage) | C70: =IFERROR(AVERAGE(D70:G70),0) -> -8.6029145 | D70: =L70 -> 3.3435673 | E70: =M70 -> -6.6324131 | F70: =N70 -> -36.440913 | G70: =O70 -> 5.3181006 | K70: Cobertura de intereses (Interest Coverage) | L70: =IFERROR(L44/L47,0) -> 3.3435673 | M70: =IFERROR(M44/M47,0) -> -6.6324131 | N70: =IFERROR(N44/N47,0) -> -36.440913 | O70: =IFERROR(O44/O47,0) -> 5.3181006
B71: Indicadores de Rentabilidad (Profitability Ratios) | K71: Indicadores de Rentabilidad (Profitability Ratios)
B72: Margen neto (NPM) | C72: =IFERROR(AVERAGE(D72:G72),0) -> 0.1190291 | D72: =L72 -> 0.083384427 | E72: =M72 -> 0.31123594 | F72: =N72 -> 0.053701739 | G72: =O72 -> 0.027794273 | K72: Margen neto (NPM) | L72: =IFERROR(L52/L37,0) -> 0.083384427 | M72: =IFERROR(M52/M37,0) -> 0.31123594 | N72: =IFERROR(N52/N37,0) -> 0.053701739 | O72: =IFERROR(O52/O37,0) -> 0.027794273
B73: Margen operacional (OM) | C73: =IFERROR(AVERAGE(D73:G73),0) -> 0.15016311 | D73: =L73 -> 0.14022072 | E73: =M73 -> 0.2540445 | F73: =N73 -> 0.083684726 | G73: =O73 -> 0.12270249 | K73: Margen operacional (OM) | L73: =IFERROR(L44/L37,0) -> 0.14022072 | M73: =IFERROR(M44/M37,0) -> 0.2540445 | N73: =IFERROR(N44/N37,0) -> 0.083684726 | O73: =IFERROR(O44/O37,0) -> 0.12270249
B74: ROA | C74: =IFERROR(AVERAGE(D74:G74),0) -> 0.060840226 | D74: =L74 -> 0.045418114 | E74: =M74 -> 0.14880642 | F74: =N74 -> 0.035040306 | G74: =O74 -> 0.014096064 | K74: ROA | L74: =IFERROR(L52/L18,0) -> 0.045418114 | M74: =IFERROR(M52/M18,0) -> 0.14880642 | N74: =IFERROR(N52/N18,0) -> 0.035040306 | O74: =IFERROR(O52/O18,0) -> 0.014096064
B75: ROE | C75: =IFERROR(AVERAGE(D75:G75),0) -> 0.11796638 | D75: =L75 -> 0.20512821 | E75: =M75 -> 0.17643372 | F75: =N75 -> 0.065357378 | G75: =O75 -> 0.024946211 | K75: ROE | L75: =IFERROR(L52/L32,0) -> 0.20512821 | M75: =IFERROR(M52/M32,0) -> 0.17643372 | N75: =IFERROR(N52/N32,0) -> 0.065357378 | O75: =IFERROR(O52/O32,0) -> 0.024946211
B76: ROC | C76: =IFERROR(AVERAGE(D76:G76),0) -> 0.087902452 | D76: =L76 -> 0.085272014 | E76: =M76 -> 0.14459446 | F76: =N76 -> 0.048726415 | G76: =O76 -> 0.073016923 | K76: ROC | L76: =IFERROR((L44*(1-IFERROR(L50/L49,0)))/(L21+L25+L32),0) -> 0.085272014 | M76: =IFERROR((M44*(1-IFERROR(M50/M49,0)))/(M21+M25+M32),0) -> 0.14459446 | N76: =IFERROR((N44*(1-IFERROR(N50/N49,0)))/(N21+N25+N32),0) -> 0.048726415 | O76: =IFERROR((O44*(1-IFERROR(O50/O49,0)))/(O21+O25+O32),0) -> 0.073016923
B77: ROIC | C77: =IFERROR(AVERAGE(D77:G77),0) -> 0.15430129 | D77: =L77 -> 0.09807194 | E77: =M77 -> 0.27528791 | F77: =N77 -> 0.16983275 | G77: =O77 -> 0.07401255 | K77: ROIC | L77: =IFERROR((L44*(1-IFERROR(L50/L49,0)))/(L17+(L11-L6-L23)),0) -> 0.09807194 | M77: =IFERROR((M44*(1-IFERROR(M50/M49,0)))/(M17+(M11-M6-M23)),0) -> 0.27528791 | N77: =IFERROR((N44*(1-IFERROR(N50/N49,0)))/(N17+(N11-N6-N23)),0) -> 0.16983275 | O77: =IFERROR((O44*(1-IFERROR(O50/O49,0)))/(O17+(O11-O6-O23)),0) -> 0.07401255
B78: ROCE | C78: =IFERROR(AVERAGE(D78:G78),0) -> 0.088143292 | D78: =L78 -> 0.089084509 | E78: =M78 -> 0.14474666 | F78: =N78 -> 0.048393898 | G78: =O78 -> 0.070348101 | K78: ROCE | L78: =IFERROR((L44*(1-IFERROR(L50/L49,0)))/(L18-L23),0) -> 0.089084509 | M78: =IFERROR((M44*(1-IFERROR(M50/M49,0)))/(M18-M23),0) -> 0.14474666 | N78: =IFERROR((N44*(1-IFERROR(N50/N49,0)))/(N18-N23),0) -> 0.048393898 | O78: =IFERROR((O44*(1-IFERROR(O50/O49,0)))/(O18-O23),0) -> 0.070348101

Sheet IQVIA
A1: Company Fundamentals - Balance Sheet
A2: Company Name | B2: IQVIA Holdings Inc. (IQV.N)
A3: Country of Exchange | B3: United States of America
A4: Country of Headquarters | B4: United States of America
A5: TRBC Industry Group | B5: Biotechnology & Medical Research
A6: CF Template | B6: IND
A7: Consolidation Basis | B7: Consolidated
A8: Scaling | B8: Millions
A9: Period | B9: Annual
A10: Export Date | B10: 46295.606
A11: Statement Data | B11: 2024 | C11: 2025
A12: Period End Date | B12: 45657 | C12: 46022
A13: Standardized Currency | B13: USD | C13: USD
A14: Balance Sheet - Standardized (Currency: US Dollar)
A15: Field Name | B15: 30-12-2024 | C15: 30-12-2025
A16: Current Assets
A17: Cash & Short-Term Investments | B17: 1843 | C17: 2141
A18: Cash & Cash Equivalents | B18: 1702 | C18: 1980
A19: Short-Term Investments - Total | B19: 141 | C19: 161
A20: Loans & Receivables - Net - Short-Term | B20: 3240 | C20: 3427
A21: Trade Accounts & Trade Notes Receivable - Net | B21: 3204 | C21: 3400
A22: Trade Accounts & Trade Notes Receivable - Gross | B22: 3246 | C22: 3451
A23: Provision - Trade Accounts & Trade Notes Receivable | B23: 42 | C23: 51
A24: Income Tax - Receivables - Short-Term | B24: 36 | C24: 27
A25: Prepaid Expenses - Short-Term | B25: 154 | C25: 162
A26: Other Current Assets - Total | B26: 592 | C26: 519
A27: Other Current Assets | B27: 592 | C27: 519
A28: Total Current Assets | B28: 5829 | C28: 6249
A29: Non-Current Assets
A30: Investments - Long-Term | B30: 108 | C30: 108
A31: Investments - Available for Sale/Held to Maturity - Long-Term | B31: 108 | C31: 108
A32: Investments in Associates, Joint Ventures and Unconsolidated Subsidiaries | B32: 266 | C32: 324
A33: Property, Plant & Equipment - Net - Total | B33: 773 | C33: 823
A34: Property, Plant & Equipment - excluding Assets Leased Out - Net - Total | B34: 773 | C34: 823
A35: Property, Plant & Equipment - Gross - Total | B35: 1592 | C35: 1728
A36: Property, Plant & Equipment - excluding Assets Leased Out - Gross | B36: 1592 | C36: 1728
A37: Land & Buildings - Gross | B37: 367 | C37: 385
A38: Plant, Machinery & Equipment - Gross | B38: 925 | C38: 991
A39: Transportation Equipment - Gross | B39: 85 | C39: 88
A40: Right of Use Tangible Assets - Total - Gross | B40: 238 | C40: 290
A41: Right of Use Tangible Assets - Operating Lease - Gross | B41: 238 | C41: 290
... A54: Total Non-Current Assets | B54: 21070 | C54: 23695
A55: Total Assets
A56: Total Assets | B56: 26899 | C56: 29944
A57: Current Liabilities
A58: Trade Accounts Payable & Accruals - Short-Term | B58: 3244 | C58: 3242
A59: Trade Accounts & Trade Notes Payable - Short-Term | B59: 736 | C59: 780
A60: Accrued Expenses - Short-Term | B60: 2508 | C60: 2462
A61: Short-Term Debt & Current Portion of Long-Term Debt | B61: 1151 | C61: 1846
A62: Current Portion of Long-Term Debt including Capitalized Leases | B62: 1151 | C62: 1846
A63: Current Portion of Long-Term Debt excluding Capitalized Leases | B63: 1145 | C63: 1840
A64: Capitalized Leases - Current Portion | B64: 6 | C64: 6
A65: Income Taxes - Payable - Short-Term | B65: 156 | C65: 140
A66: Operating Lease Liabilities - Current Portion/Short-Term | B66: 99 | C66: 93
A67: Other Current Liabilities - Total | B67: 2307 | C67: 3017
A68: Deferred Income - Short-Term | B68: 1779 | C68: 2118
A69: Other Current Liabilities | B69: 528 | C69: 899
A70: Total Current Liabilities | B70: 6957 | C70: 8338
A71: Non-Current Liabilities
A72: Debt - Long-Term - Total | B72: 13056 | C72: 14096
A73: Long-Term Debt excluding Capitalized Leases | B73: 12838 | C73: 13884
A74: Debt - Non-Convertible - Long-Term | B74: 12838 | C74: 13884
A75: Capitalized Lease Obligations - Long-Term | B75: 218 | C75: 212
A76: Deferred Tax & Investment Tax Credits - Long-Term | B76: 196 | C76: 179
A77: Deferred Tax - Liability - Long-Term | B77: 196 | C77: 179
A78: Operating Lease Liabilities - Long-Term | B78: 173 | C78: 225
A79: Other Non-Current Liabilities - Total | B79: 450 | C79: 476
A80: Other Non-Current Liabilities | B80: 450 | C80: 476
A81: Total Non-Current Liabilities | B81: 13875 | C81: 14976
A82: Total Liabilities
A83: Total Liabilities | B83: 20832 | C83: 23314
A84: Shareholders' Equity
A85: Shareholders' Equity - Attributable to Parent Shareholders - Total | B85: 6067 | C85: 6503
A86: Common Equity Attributable to Parent Shareholders | B86: 6067 | C86: 6503
A87: Common Stock - Treasury/Repurchased | B87: 10103 | C87: 11357
A88: Common Equity - Contributed | B88: 11143 | C88: 11378
A89: Common Stock - Issued & Paid | B89: 3 | C89: 3
A90: Common Stock - Additional Paid in Capital including Option Reserve | B90: 11140 | C90: 11375
A91: Equity - Non-Contributed - Reserves & Retained Earnings | B91: 5027 | C91: 6482
A92: Retained Earnings - Total | B92: 6065 | C92: 7425
A93: Comprehensive Income - Accumulated - Total | B93: -1038 | C93: -943
A94: Hedging Reserves | B94: -5 | C94: -43
A95: Foreign Currency Translation Adjustment - Accumulated | B95: -1092 | C95: -1126
A96: Comprehensive Income - Pension Liabilities | B96: 15 | C96: 40
... A98: Common Equity - Total | B98: 6067 | C98: 6503
A99: Minority Interest - Equity | C99: 127
A100: Total Shareholders' Equity
A101: Total Shareholders' Equity - including Minority Interest & Hybrid Debt | B101: 6067 | C101: 6630
A102: Total Liabilities & Shareholders' Equity
A103: Total Liabilities & Equity | B103: 26899 | C103: 29944
A104: Share/Per Share - Common
A105: Common Shares - Issued - Total | B105: 258.2 | C105: 259.1
A106: Common Shares - Outstanding - Total | B106: 176.1 | C106: 169.6
A107: Common Shares - Treasury - Total | B107: 82.1 | C107: 89.5
A108: Common Shares - Authorized - Issue Specific | B108: 400 | C108: 400
A109: Common Shares - Issued - Issue Specific | B109: 258.2 | C109: 259.1
A110: Common Shares - Outstanding - Issue Specific | B110: 176.1 | C110: 169.6
A111: Common Shares - Treasury - Issue Specific | B111: 82.1 | C111: 89.5
A112: Share/Per Share - Other
A113: Asset Allocation Factor - Issue Specific | B113: 1 | C113: 1
...

Sheet Argenx
A1: Company Fundamentals - Balance Sheet
A2: Company Name | B2: argenx SE (ARGX.O)
A3: Country of Exchange | B3: United States of America
A4: Country of Headquarters | B4: Netherlands
A5: TRBC Industry Group | B5: Biotechnology & Medical Research
A6: CF Template | B6: IND
A7: Consolidation Basis | B7: Consolidated
A8: Scaling | B8: Millions
A9: Period | B9: Annual
A10: Export Date | B10: 46296.857
A11: Statement Data | B11: 2024 | C11: 2025
A12: Period End Date | B12: 45657 | C12: 46022
A13: Standardized Currency | B13: USD | C13: USD
A14: Balance Sheet - Standardized (Currency: US Dollar)
A15: Field Name | B15: 30-12-2024 | C15: 30-12-2025
A16: Current Assets
A17: Cash & Short-Term Investments | B17: 3378.83 | C17: 4440.04
A18: Cash & Cash Equivalents | B18: 1499.94 | C18: 3491.29
A19: Short-Term Investments - Total | B19: 1878.89 | C19: 948.75
A20: Financial Assets - Short-Term | B20: 1878.89 | C20: 948.75
A21: Loans & Receivables - Net - Short-Term | B21: 909.1 | C21: 1657.06
A22: Trade Accounts & Trade Notes Receivable - Net | B22: 817.71 | C22: 1489.57
A23: Income Tax - Receivables - Short-Term | B23: 40.89 | C23: 123.12
A24: Receivables - Other - Total | B24: 50.5 | C24: 44.36
A25: Inventories - Total | B25: 407.23 | C25: 473.53
A26: Inventories - Raw Materials | B26: 337.83 | C26: 335.54
A27: Inventories - Work in Progress | B27: 26.36 | C27: 55.54
A28: Inventories - Finished Goods | B28: 43.04 | C28: 82.46
... A30: Total Current Assets | B30: 4883.1 | C30: 6899.1
A31: Non-Current Assets
A32: Investments - Long-Term | B32: 40.43 | C32: 47.15
A33: Financial Assets - Long-Term | B33: 40.43 | C33: 47.15
A34: Investments in Associates, Joint Ventures and Unconsolidated Subsidiaries | B34: 9.27 | C34: 3.38
A35: Receivables & Loans - Long-Term | B35: 94.85 | C35: 86.21
A36: Receivables - Other - Net - Long-Term | B36: 94.85 | C36: 86.21
A37: Property, Plant & Equipment - Net - Total | B37: 43.52 | C37: 48.25
A38: Property, Plant & Equipment - excluding Assets Leased Out - Net - Total | B38: 43.52 | C38: 48.25
A39: Land & Buildings - Net | B39: 1.18 | C39: 4.57
A40: Leasehold Improvements - Net | B40: 1.18 | C40: 4.57
A41: Plant, Machinery & Equipment - Net | B41: 1.81 | C41: 2.89
A42: Computer Software & Equipment - Net | B42: 1.81 | C42: 2.89
A43: Property, Plant & Equipment - Under Capital Lease - Net | B43: 0.13 | C43: 0.09
... A69: Intangible Assets - excluding Goodwill - Net - Total | B69: 181.45 | C69: 272.1
A70: Computer Software - Intangible Assets - Net | B70: 2.23
A71: Research & Development Costs - Net | B71: 179.22 | C71: 255.19
A72: Intangible Assets - Other - Net | B72: 0 | C72: 16.91
A73: Intangible Assets - Gross - Total | B73: 197.02 | C73: 302.54
A74: Intangible Assets - excluding Goodwill - Gross | B74: 197.02 | C74: 302.54
A75: Computer Software - Intangible Assets - Gross | B75: 4.34
A76: Research & Development Costs - Gross | B76: 192.68 | C76: 277.91
A77: Intangible Assets - Other - Gross - Total | B77: 0 | C77: 24.63
A78: Intangible Assets - Accumulated Amortization & Impairment - Total | B78: 15.57 | C78: 30.43
A79: Intangible Assets - excluding Goodwill - Accumulated Amortization & Impairment - Total | B79: 15.57 | C79: 30.43
A80: Computer Software - Intangible Assets - Accumulated Amortization & Impairment | B80: 2.11
A81: Research & Development Costs - Accumulated Amortization & Impairment | B81: 13.46 | C81: 22.72
A82: Intangible Assets - Other - Accumulated Amortization & Impairment | B82: 0 | C82: 7.72
A83: Total Non-Current Assets | B83: 1319.42 | C83: 1783.59
A84: Total Assets
A85: Total Assets | B85: 6202.52 | C85: 8682.7
A86: Current Liabilities
A87: Trade Accounts Payable & Accruals - Short-Term | B87: 633.52 | C87: 1168.64
A88: Trade Accounts & Trade Notes Payable - Short-Term | B88: 342.23 | C88: 554.27
A89: Accrued Expenses - Short-Term | B89: 291.29 | C89: 614.38
A90: Short-Term Debt & Current Portion of Long-Term Debt | B90: 6.53 | C90: 10.83
A91: Current Portion of Long-Term Debt including Capitalized Leases | B91: 6.53 | C91: 10.83
A92: Capitalized Leases - Current Portion | B92: 6.53 | C92: 10.83
A93: Income Taxes - Payable - Short-Term | B93: 13.39 | C93: 42.21
A94: Other Current Liabilities - Total | B94: 16.47 | C94: 98.5
A95: Other Current Liabilities | B95: 16.47 | C95: 98.5
A96: Total Current Liabilities | B96: 669.92 | C96: 1320.19
A97: Non-Current Liabilities
A98: Debt - Long-Term - Total | B98: 32.52 | C98: 36.33
A99: Capitalized Lease Obligations - Long-Term | B99: 32.52 | C99: 36.33
A100: Other Non-Current Liabilities - Total | B100: 1.8 | C100: 3.09
A101: Provisions - Long-Term | B101: 1.8 | C101: 3.09
A102: Post Employment Benefits - Pension & Other - Long-Term | B102: 1.8 | C102: 3.09
A103: Total Non-Current Liabilities | B103: 34.32 | C103: 39.42
A104: Total Liabilities
A105: Total Liabilities | B105: 704.24 | C105: 1359.61
A106: Shareholders' Equity
A107: Shareholders' Equity - Attributable to Parent Shareholders - Total | B107: 5498.28 | C107: 7323.09
A108: Common Equity Attributable to Parent Shareholders | B108: 5498.28 | C108: 7323.09
A109: Common Equity - Contributed | B109: 5956.14 | C109: 6193.91
A110: Common Stock - Issued & Paid | B110: 7.23 | C110: 7.35
A111: Common Stock - Additional Paid in Capital including Option Reserve | B111: 5948.92 | C111: 6186.55
A112: Equity - Non-Contributed - Reserves & Retained Earnings | B112: -457.86 | C112: 1129.18
A113: Retained Earnings - Total | B113: -1571.8 | C113: -279.77
A114: Comprehensive Income - Accumulated - Total | B114: 126.83 | C114: 138.57
A115: Foreign Currency Translation Adjustment - Accumulated | B115: 126.83 | C115: 138.57
A116: Other Reserves/Equity - Total | B116: 987.11 | C116: 1270.38
A117: Common Equity - Total | B117: 5498.28 | C117: 7323.09
A118: Total Shareholders' Equity
A119: Total Shareholders' Equity - including Minority Interest & Hybrid Debt | B119: 5498.28 | C119: 7323.09
A120: Total Liabilities & Shareholders' Equity
A121: Total Liabilities & Equity | B121: 6202.52 | C121: 8682.7
A122: Share/Per Share - Common
A123: Common Shares - Issued - Total | B123: 60.76 | C123: 61.88
A124: Common Shares - Outstanding - Total | B124: 60.76 | C124: 61.88
A125: Common Shares - Treasury - Total | B125: 0 | C125: 0
A126: Common Shares - Issued - Issue Specific | B126: 60.76 | C126: 61.88
...

Sheet Beone
A1: Company Fundamentals - Balance Sheet
A2: Company Name | B2: BeOne Medicines AG (ONC.O)
A3: Country of Exchange | B3: United States of America
A4: Country of Headquarters | B4: Switzerland
A5: TRBC Industry Group | B5: Biotechnology & Medical Research
A6: CF Template | B6: IND
A7: Consolidation Basis | B7: Consolidated
A8: Scaling | B8: Millions
A9: Period | B9: Annual
A10: Export Date | B10: 46296.86
A11: Statement Data | B11: 2024 | C11: 2025
A12: Period End Date | B12: 45657 | C12: 46022
A13: Standardized Currency | B13: USD | C13: USD
A14: Balance Sheet - Standardized (Currency: US Dollar)
A15: Field Name | B15: 30-12-2024 | C15: 30-12-2025
A16: Current Assets
A17: Cash & Short-Term Investments | B17: 2627.41 | C17: 4547.53
A18: Cash & Cash Equivalents | B18: 2627.41 | C18: 4547.53
A19: Loans & Receivables - Net - Short-Term | B19: 709.11 | C19: 886.86
A20: Trade Accounts & Trade Notes Receivable - Net | B20: 676.28 | C20: 865.08
A21: Receivables - Other - Total | B21: 32.83 | C21: 21.78
A22: Inventories - Total | B22: 494.99 | C22: 608.23
A23: Inventories - Raw Materials | B23: 170.58
A24: Inventories - Work in Progress | B24: 60.12
A25: Inventories - Finished Goods | B25: 264.28
A26: Prepaid Expenses - Short-Term | B26: 134.9 | C26: 130.73
A27: Other Current Assets - Total | B27: 25.19 | C27: 60.24
A28: Restricted Accounts - Short-Term | B28: 9.31 | C28: 41.28
A29: Other Current Assets | B29: 15.88 | C29: 18.96
A30: Total Current Assets | B30: 3991.59 | C30: 6233.59
A31: Non-Current Assets
A32: Investments - Long-Term | B32: 128.93 | C32: 61.68
A33: Investments - Available for Sale/Held to Maturity - Long-Term | B33: 128.93 | C33: 61.68
A34: Property, Plant & Equipment - Net - Total | B34: 1717.73 | C34: 1789.86
A35: Property, Plant & Equipment - excluding Assets Leased Out - Net - Total | B35: 1717.73 | C35: 1789.86
A36: Property, Plant & Equipment - Gross - Total | B36: 2116.84 | C36: 2318.56
A37: Property, Plant & Equipment - excluding Assets Leased Out - Gross | B37: 2116.84 | C37: 2318.56
A38: Land & Buildings - Gross | B38: 738.02 | C38: 1335.84
A39: Land/Improvements - Gross | B39: 65.49 | C39: 71.43
A40: Buildings - Gross | B40: 607.86 | C40: 1187.84
A41: Leasehold Improvements - Gross | B41: 64.68 | C41: 76.57
A42: Plant, Machinery & Equipment - Gross | B42: 585.49 | C42: 707.38
A43: Computer Software & Equipment - Gross | B43: 100.35 | C43: 124.14
... A65: Total Non-Current Assets | B65: 1929.32 | C65: 1954.98
A66: Total Assets
A67: Total Assets | B67: 5920.91 | C67: 8188.57
A68: Current Liabilities
A69: Trade Accounts Payable & Accruals - Short-Term | B69: 1186.75 | C69: 1554.59
A70: Trade Accounts & Trade Notes Payable - Short-Term | B70: 405 | C70: 479.04
A71: Accrued Expenses - Short-Term | B71: 781.76 | C71: 1075.56
A72: Short-Term Debt & Current Portion of Long-Term Debt | B72: 851.53 | C72: 114.01
A73: Current Portion of Long-Term Debt including Capitalized Leases | B73: 851.53 | C73: 114.01
A74: Current Portion of Long-Term Debt excluding Capitalized Leases | B74: 851.53 | C74: 114.01
A75: Income Taxes - Payable - Short-Term | B75: 25.93 | C75: 41.63
A76: Operating Lease Liabilities - Current Portion/Short-Term | B76: 17.58 | C76: 20.7
A77: Other Current Liabilities - Total | B77: 133.11 | C77: 97.91
A78: Other Current Liabilities | B78: 133.11 | C78: 97.91
A79: Total Current Liabilities | B79: 2214.9 | C79: 1828.83
A80: Non-Current Liabilities
A81: Debt - Long-Term - Total | B81: 166.48 | C81: 1812.16
A82: Long-Term Debt excluding Capitalized Leases | B82: 166.48 | C82: 1812.16
A83: Debt - Non-Convertible - Long-Term | B83: 166.48 | C83: 1812.16
A84: Deferred Tax & Investment Tax Credits - Long-Term | B84: 42.01 | C84: 53.21
A85: Deferred Tax - Liability - Long-Term | B85: 42.01 | C85: 53.21
A86: Operating Lease Liabilities - Long-Term | B86: 44.28 | C86: 52.94
A87: Other Non-Current Liabilities - Total | B87: 90.7 | C87: 51.27
A88: Provisions - Long-Term | B88: 20.2 | C88: 21.74
A89: Post Employment Benefits - Pension & Other - Long-Term | B89: 16.41 | C89: 18.17
A90: Asset Retirement Obligation - Long-Term | B90: 3.79 | C90: 3.57
A91: Other Non-Current Liabilities | B91: 70.5 | C91: 29.53
A92: Total Non-Current Liabilities | B92: 343.47 | C92: 1969.57
A93: Total Liabilities
A94: Total Liabilities | B94: 2558.36 | C94: 3798.4
A95: Shareholders' Equity
A96: Shareholders' Equity - Attributable to Parent Shareholders - Total | B96: 3362.55 | C96: 4390.17
A97: Common Equity Attributable to Parent Shareholders | B97: 3362.55 | C97: 4390.17
A98: Common Equity - Contributed | B98: 12088.05 | C98: 12759.28
A99: Common Stock - Issued & Paid | B99: 0.14 | C99: 0.14
A100: Common Stock - Additional Paid in Capital including Option Reserve | B100: 12087.91 | C100: 12759.14
A101: Equity - Non-Contributed - Reserves & Retained Earnings | B101: -8725.5 | C101: -8369.11
A102: Retained Earnings - Total | B102: -8606.84 | C102: -8319.9
A103: Comprehensive Income - Accumulated - Total | B103: -148.99 | C103: -78.18
A104: Investments - Unrealized Gain/Loss | B104: 0
A105: Foreign Currency Translation Adjustment - Accumulated | B105: -135.55
A106: Comprehensive Income - Pension Liabilities | B106: -13.44
A107: Other Reserves/Equity - Total | B107: 30.32 | C107: 28.98
A108: Common Equity - Total | B108: 3362.55 | C108: 4390.17
A109: Total Shareholders' Equity
A110: Total Shareholders' Equity - including Minority Interest & Hybrid Debt | B110: 3362.55 | C110: 4390.17
A111: Total Liabilities & Shareholders' Equity
A112: Total Liabilities & Equity | B112: 5920.91 | C112: 8188.57
A113: Share/Per Share - Common
A114: Common Shares - Issued - Total | B114: 1387.37 | C114: 1540.98
A115: Common Shares - Outstanding - Total | B115: 1387.37 | C115: 1441.08
A116: Common Shares - Treasury - Total | B116: 0 | C116: 99.9
A117: Common Shares - Authorized - Issue Specific | B117: 9500 | C117: 9500
A118: Common Shares - Issued - Issue Specific | B118: 1272.31 | C118: 1425.92
A119: Common Shares - Outstanding - Issue Specific | B119: 1272.31 | C119: 1326.02
A120: Common Shares - Treasury - Issue Specific | B120: 0 | C120: 99.9
A121: Common Shares - Issued - Issue Specific | B121: 115.06 | C121: 115.06
...

Sheet ICON
A1: Company Fundamentals - Balance Sheet
A2: Company Name | B2: ICON PLC (ICLR.OQ)
A3: Country of Exchange | B3: United States of America
A4: Country of Headquarters | B4: Ireland
A5: TRBC Industry Group | B5: Biotechnology & Medical Research
A6: CF Template | B6: IND
A7: Consolidation Basis | B7: Consolidated
A8: Scaling | B8: Millions
A9: Period | B9: Annual
A10: Export Date | B10: 46296.619
A11: Statement Data | B11: 2024 | C11: 2025
A12: Period End Date | B12: 45657 | C12: 46022
A13: Standardized Currency | B13: USD | C13: USD
A14: Balance Sheet - Standardized (Currency: US Dollar)
A15: Field Name | B15: 30-12-2024 | C15: 30-12-2025
A16: Current Assets
A17: Cash & Short-Term Investments | B17: 538.79 | C17: 647.29
A18: Cash & Cash Equivalents | B18: 538.79 | C18: 647.29
A19: Short-Term Investments - Total | B19: 0 | C19: 0
A20: Loans & Receivables - Net - Short-Term | B20: 2595.95 | C20: 2749.06
A21: Trade Accounts & Trade Notes Receivable - Net | B21: 1392.76 | C21: 1474.9
A22: Trade Accounts & Trade Notes Receivable - Gross | B22: 1428.43 | C22: 1517.22
A23: Provision - Trade Accounts & Trade Notes Receivable | B23: 35.66 | C23: 42.32
A24: Income Tax - Receivables - Short-Term | B24: 83.52 | C24: 60.82
A25: Receivables - Other - Total | B25: 1119.66 | C25: 1213.34
A26: Prepaid Expenses - Short-Term | B26: 140.44 | C26: 105.32
A27: Total Current Assets | B27: 3275.17 | C27: 3501.68
A28: Non-Current Assets
A29: Investments in Associates, Joint Ventures and Unconsolidated Subsidiaries | B29: 57.95 | C29: 82.05
A30: Receivables & Loans - Long-Term | B30: 84.19 | C30: 75.71
A31: Receivables - Other - Net - Long-Term | B31: 84.19 | C31: 75.71
A32: Property, Plant & Equipment - Net - Total | B32: 530.48 | C32: 524.67
A33: Property, Plant & Equipment - excluding Assets Leased Out - Net - Total | B33: 530.48 | C33: 524.67
A34: Property, Plant & Equipment - Gross - Total | B34: 1076.5 | C34: 1228.14
A35: Property, Plant & Equipment - excluding Assets Leased Out - Gross | B35: 1076.5 | C35: 1228.14
A36: Land & Buildings - Gross | B36: 131.89 | C36: 159.27
A37: Land/Improvements - Gross | B37: 3.72 | C37: 3.72
A38: Buildings - Gross | B38: 66.13 | C38: 83.27
A39: Leasehold Improvements - Gross | B39: 62.03 | C39: 72.28
A40: Plant, Machinery & Equipment - Gross | B40: 745.16 | C40: 879.31
... A53: Total Non-Current Assets | B53: 13359.65 | C53: 12768.11
A54: Total Assets
A55: Total Assets | B55: 16634.82 | C55: 16269.78
A56: Current Liabilities
A57: Trade Accounts Payable & Accruals - Short-Term | B57: 391.6 | C57: 432.34
A58: Trade Accounts & Trade Notes Payable - Short-Term | B58: 173.03 | C58: 192.12
A59: Accrued Expenses - Short-Term | B59: 218.57 | C59: 240.22
A60: Short-Term Debt & Current Portion of Long-Term Debt | B60: 29.76 | C60: 529.76
A61: Current Portion of Long-Term Debt including Capitalized Leases | B61: 29.76 | C61: 529.76
A62: Current Portion of Long-Term Debt excluding Capitalized Leases | B62: 29.76 | C62: 529.76
A63: Income Taxes - Payable - Short-Term | B63: 55.26 | C63: 19
A64: Operating Lease Liabilities - Current Portion/Short-Term | B64: 36.78 | C64: 36.28
A65: Other Current Liabilities - Total | B65: 2122.09 | C65: 2178.79
A66: Deferred Income - Short-Term | B66: 1467.67 | C66: 1550.47
A67: Other Current Liabilities | B67: 654.42 | C67: 628.32
A68: Total Current Liabilities | B68: 2635.49 | C68: 3196.18
A69: Non-Current Liabilities
A70: Debt - Long-Term - Total | B70: 3396.4 | C70: 2872.62
A71: Long-Term Debt excluding Capitalized Leases | B71: 3396.4 | C71: 2872.62
A72: Debt - Non-Convertible - Long-Term | B72: 3396.4 | C72: 2872.62
A73: Deferred Tax & Investment Tax Credits - Long-Term | B73: 811.23 | C73: 714.43
A74: Deferred Tax - Liability - Long-Term | B74: 811.23 | C74: 714.43
A75: Operating Lease Liabilities - Long-Term | B75: 140.09 | C75: 117.12
A76: Other Non-Current Liabilities - Total | B76: 210.26 | C76: 176.06
A77: Other Non-Current Liabilities | B77: 210.26 | C77: 176.06
A78: Total Non-Current Liabilities | B78: 4557.98 | C78: 3880.22
A79: Total Liabilities
A80: Total Liabilities | B80: 7193.47 | C80: 7076.4
A81: Shareholders' Equity
A82: Shareholders' Equity - Attributable to Parent Shareholders - Total | B82: 9441.35 | C82: 9193.38
A83: Common Equity Attributable to Parent Shareholders | B83: 9441.35 | C83: 9193.38
A84: Common Equity - Contributed | B84: 7026.82 | C84: 7138.26
A85: Common Stock - Issued & Paid | B85: 6.59 | C85: 6.31
A86: Common Stock - Additional Paid in Capital including Option Reserve | B86: 7020.23 | C86: 7131.96
A87: Equity - Non-Contributed - Reserves & Retained Earnings | B87: 2414.54 | C87: 2055.12
A88: Retained Earnings - Total | B88: 2644.47 | C88: 2123.66
A89: Comprehensive Income - Accumulated - Total | B89: -229.93 | C89: -68.53
A90: Hedging Reserves | B90: 2.42 | C90: 0
A91: Foreign Currency Translation Adjustment - Accumulated | B91: -234.07 | C91: -74.62
A92: Comprehensive Income - Pension Liabilities | B92: 1.73 | C92: 6.09
A93: Common Equity - Total | B93: 9441.35 | C93: 9193.38
A94: Total Shareholders' Equity
A95: Total Shareholders' Equity - including Minority Interest & Hybrid Debt | B95: 9441.35 | C95: 9193.38
A96: Total Liabilities & Shareholders' Equity
A97: Total Liabilities & Equity | B97: 16634.82 | C97: 16269.78
A98: Share/Per Share - Common
A99: Common Shares - Issued - Total | B99: 80.76 | C99: 76.57
A100: Common Shares - Outstanding - Total | B100: 80.76 | C100: 76.57
A101: Common Shares - Treasury - Total | B101: 0 | C101: 0
A102: Common Shares - Authorized - Issue Specific | B102: 100 | C102: 100
A103: Common Shares - Issued - Issue Specific | B103: 80.76 | C103: 76.57
A104: Common Shares - Outstanding - Issue Specific | B104: 80.76 | C104: 76.57
A105: Common Shares - Treasury - Issue Specific | B105: 0 | C105: 0
A106: Share/Per Share - Other
A107: Asset Allocation Factor - Issue Specific | B107: 1 | C107: 1
A108: Right of Use Tangible Assets
A109: Right of Use Tangible Assets - Total - Net - Supplemental | B109: 147.6 | C109: 128.95
A110: Right of Use Tangible Assets - Operating Lease - Net - Supplemental | B110: 147.6 | C110: 128.95
A111: Property, Plant & Equipment - excluding Right of Use Tangible Assets & Capital Leases - Net | B111: 382.88 | C111: 395.72
A112: Right of Use Liabilities
...

Sheet Technology>>
C2: Average | D2: =L2 -> NVIDIA | E2: =M2 -> Intel | F2: =N2 -> Broadcom | G2: =O2 -> Micron | L2: NVIDIA | M2: Intel | N2: Broadcom | O2: Micron
B4: Balance Sheet | D4: % | E4: % | F4: % | G4: % | K4: Balance Sheet | L4: 2025 | M4: 2025 | N4: 2025 | O4: 2025
B6: Cash & Cash Equivalents | C6: =IFERROR(AVERAGE(D6:G6),0) -> 0.088860134 | D6: =IFERROR(L6/L$18,0) -> 0.076961676 | E6: =IFERROR(M6/M$18,0) -> 0.067469458 | F6: =IFERROR(N6/N$18,0) -> 0.094557314 | G6: =IFERROR(O6/O$18,0) -> 0.11645209 | K6: Cash & Cash Equivalents | L6: =SUMIF(INDIRECT("'"&L$2&"'!$A$1:$A$500"),$K6,INDIRECT("'"&L$2&"'!$C$1:$C$500")) -> 8589 | M6: =SUMIF(INDIRECT("'"&M$2&"'!$A$1:$A$500"),$K6,INDIRECT("'"&M$2&"'!$C$1:$C$500")) -> 14265 | N6: =SUMIF(INDIRECT("'"&N$2&"'!$A$1:$A$500"),$K6,INDIRECT("'"&N$2&"'!$C$1:$C$500")) -> 16178 | O6: =SUMIF(INDIRECT("'"&O$2&"'!$A$1:$A$500"),$K6,INDIRECT("'"&O$2&"'!$C$1:$C$500")) -> 9642
B7: Short-Term Investments - Total | C7: =IFERROR(AVERAGE(D7:G7),0) -> 0.10693765 | D7: =IFERROR(L7/L$18,0) -> 0.31022123 | E7: =IFERROR(M7/M$18,0) -> 0.10949775 | F7: =IFERROR(N7/N$18,0) -> 0 | G7: =IFERROR(O7/O$18,0) -> 0.008031595 | K7: Short-Term Investments - Total | L7: =SUMIF(INDIRECT("'"&L$2&"'!$A$1:$A$500"),$K7,INDIRECT("'"&L$2&"'!$C$1:$C$500")) -> 34621 | M7: =SUMIF(INDIRECT("'"&M$2&"'!$A$1:$A$500"),$K7,INDIRECT("'"&M$2&"'!$C$1:$C$500")) -> 23151 | N7: =SUMIF(INDIRECT("'"&N$2&"'!$A$1:$A$500"),$K7,INDIRECT("'"&N$2&"'!$C$1:$C$500")) -> 0 | O7: =SUMIF(INDIRECT("'"&O$2&"'!$A$1:$A$500"),$K7,INDIRECT("'"&O$2&"'!$C$1:$C$500")) -> 665
B8: Trade Accounts & Trade Notes Receivable - Net | C8: =IFERROR(AVERAGE(D8:G8),0) -> 0.08827602 | D8: =IFERROR(L8/L$18,0) -> 0.20667378 | E8: =IFERROR(M8/M$18,0) -> 0.018157396 | F8: =IFERROR(N8/N$18,0) -> 0.041761158 | G8: =IFERROR(O8/O$18,0) -> 0.086511751 | K8: Trade Accounts & Trade Notes Receivable - Net | L8: =SUMIF(INDIRECT("'"&L$2&"'!$A$1:$A$500"),$K8,INDIRECT("'"&L$2&"'!$C$1:$C$500")) -> 23065 | M8: =SUMIF(INDIRECT("'"&M$2&"'!$A$1:$A$500"),$K8,INDIRECT("'"&M$2&"'!$C$1:$C$500")) -> 3839 | N8: =SUMIF(INDIRECT("'"&N$2&"'!$A$1:$A$500"),$K8,INDIRECT("'"&N$2&"'!$C$1:$C$500")) -> 7145 | O8: =SUMIF(INDIRECT("'"&O$2&"'!$A$1:$A$500"),$K8,INDIRECT("'"&O$2&"'!$C$1:$C$500")) -> 7163
B9: Inventories - Total | C9: =IFERROR(AVERAGE(D9:G9),0) -> 0.064861903 | D9: =IFERROR(L9/L$18,0) -> 0.090321771 | E9: =IFERROR(M9/M$18,0) -> 0.054949889 | F9: =IFERROR(N9/N$18,0) -> 0.013267716 | G9: =IFERROR(O9/O$18,0) -> 0.10090823 | K9: Inventories - Total | L9: =SUMIF(INDIRECT("'"&L$2&"'!$A$1:$A$500"),$K9,INDIRECT("'"&L$2&"'!$C$1:$C$500")) -> 10080 | M9: =SUMIF(INDIRECT("'"&M$2&"'!$A$1:$A$500"),$K9,INDIRECT("'"&M$2&"'!$C$1:$C$500")) -> 11618 | N9: =SUMIF(INDIRECT("'"&N$2&"'!$A$1:$A$500"),$K9,INDIRECT("'"&N$2&"'!$C$1:$C$500")) -> 2270 | O9: =SUMIF(INDIRECT("'"&O$2&"'!$A$1:$A$500"),$K9,INDIRECT("'"&O$2&"'!$C$1:$C$500")) -> 8355
B10: Other Current Assets | C10: =IFERROR(AVERAGE(D10:G10),0) -> 0.039079975 | D10: =IFERROR(L10/L$18,0) -> 0.03379002 | E10: =IFERROR(M10/M$18,0) -> 0.051151923 | F10: =IFERROR(N10/N$18,0) -> 0.034951956 | G10: =IFERROR(O10/O$18,0) -> 0.036426001 | K10: Other Current Assets | L10: =SUMIF(INDIRECT("'"&L$2&"'!$A$1:$A$500"),$K11,INDIRECT("'"&L$2&"'!$C$1:$C$500"))-SUM(L6:L9) -> 3771 | M10: =SUMIF(INDIRECT("'"&M$2&"'!$A$1:$A$500"),$K11,INDIRECT("'"&M$2&"'!$C$1:$C$500"))-SUM(M6:M9) -> 10815 | N10: =SUMIF(INDIRECT("'"&N$2&"'!$A$1:$A$500"),$K11,INDIRECT("'"&N$2&"'!$C$1:$C$500"))-SUM(N6:N9) -> 5980 | O10: =SUMIF(INDIRECT("'"&O$2&"'!$A$1:$A$500"),$K11,INDIRECT("'"&O$2&"'!$C$1:$C$500"))-SUM(O6:O9) -> 3016
B11: Total Current Assets | C11: =IFERROR(AVERAGE(D11:G11),0) -> 0.38801568 | D11: =IFERROR(L11/L$18,0) -> 0.71796848 | E11: =IFERROR(M11/M$18,0) -> 0.30122642 | F11: =IFERROR(N11/N$18,0) -> 0.18453814 | G11: =IFERROR(O11/O$18,0) -> 0.34832967 | K11: Total Current Assets | L11: =SUM(L6:L10) -> 80126 | M11: =SUM(M6:M10) -> 63688 | N11: =SUM(N6:N10) -> 31573 | O11: =SUM(O6:O10) -> 28841
K12: Check Current Assets | L12: =ROUND(SUMIF(INDIRECT("'"&L$2&"'!$A$1:$A$500"),$K$11,INDIRECT("'"&L$2&"'!$C$1:$C$500"))-L11,2) -> 0 | M12: =ROUND(SUMIF(INDIRECT("'"&M$2&"'!$A$1:$A$500"),$K$11,INDIRECT("'"&M$2&"'!$C$1:$C$500"))-M11,2) -> 0 | N12: =ROUND(SUMIF(INDIRECT("'"&N$2&"'!$A$1:$A$500"),$K$11,INDIRECT("'"&N$2&"'!$C$1:$C$500"))-N11,2) -> 0 | O12: =ROUND(SUMIF(INDIRECT("'"&O$2&"'!$A$1:$A$500"),$K$11,INDIRECT("'"&O$2&"'!$C$1:$C$500"))-O11,2) -> 0
B13: Investments - Long-Term | C13: =IFERROR(AVERAGE(D13:G13),0) -> 0.022570739 | D13: =IFERROR(L13/L$18,0) -> 0.03034919 | E13: =IFERROR(M13/M$18,0) -> 0.040259378 | F13: =IFERROR(N13/N$18,0) -> 0 | G13: =IFERROR(O13/O$18,0) -> 0.019674388 | K13: Investments - Long-Term | L13: =SUMIF(INDIRECT("'"&L$2&"'!$A$1:$A$500"),$K13,INDIRECT("'"&L$2&"'!$C$1:$C$500")) -> 3387 | M13: =SUMIF(INDIRECT("'"&M$2&"'!$A$1:$A$500"),$K13,INDIRECT("'"&M$2&"'!$C$1:$C$500")) -> 8512 | N13: =SUMIF(INDIRECT("'"&N$2&"'!$A$1:$A$500"),$K13,INDIRECT("'"&N$2&"'!$C$1:$C$500")) -> 0 | O13: =SUMIF(INDIRECT("'"&O$2&"'!$A$1:$A$500"),$K13,INDIRECT("'"&O$2&"'!$C$1:$C$500")) -> 1629
B14: Property, Plant & Equipment - Net - Total | C14: =IFERROR(AVERAGE(D14:G14),0) -> 0.29175239 | D14: =IFERROR(L14/L$18,0) -> 0.072364943 | E14: =IFERROR(M14/M$18,0) -> 0.50056993 | F14: =IFERROR(N14/N$18,0) -> 0.022490824 | G14: =IFERROR(O14/O$18,0) -> 0.57158385 | K14: Property, Plant & Equipment - Net - Total | L14: =SUMIF(INDIRECT("'"&L$2&"'!$A$1:$A$500"),$K14,INDIRECT("'"&L$2&"'!$C$1:$C$500")) -> 8076 | M14: =SUMIF(INDIRECT("'"&M$2&"'!$A$1:$A$500"),$K14,INDIRECT("'"&M$2&"'!$C$1:$C$500")) -> 105835 | N14: =SUMIF(INDIRECT("'"&N$2&"'!$A$1:$A$500"),$K14,INDIRECT("'"&N$2&"'!$C$1:$C$500")) -> 3848 | O14: =SUMIF(INDIRECT("'"&O$2&"'!$A$1:$A$500"),$K14,INDIRECT("'"&O$2&"'!$C$1:$C$500")) -> 47326
B15: Intangible Assets - Total - Net | C15: =IFERROR(AVERAGE(D15:G15),0) -> 0.239886 | D15: =IFERROR(L15/L$18,0) -> 0.053718157 | E15: =IFERROR(M15/M$18,0) -> 0.12620785 | F15: =IFERROR(N15/N$18,0) -> 0.76025764 | G15: =IFERROR(O15/O$18,0) -> 0.019360371 | K15: Intangible Assets - Total - Net | L15: =SUMIF(INDIRECT("'"&L$2&"'!$A$1:$A$500"),$K15,INDIRECT("'"&L$2&"'!$C$1:$C$500")) -> 5995 | M15: =SUMIF(INDIRECT("'"&M$2&"'!$A$1:$A$500"),$K15,INDIRECT("'"&M$2&"'!$C$1:$C$500")) -> 26684 | N15: =SUMIF(INDIRECT("'"&N$2&"'!$A$1:$A$500"),$K15,INDIRECT("'"&N$2&"'!$C$1:$C$500")) -> 130074 | O15: =SUMIF(INDIRECT("'"&O$2&"'!$A$1:$A$500"),$K15,INDIRECT("'"&O$2&"'!$C$1:$C$500")) -> 1603
B16: Other Non-Current Assets | C16: =IFERROR(AVERAGE(D16:G16),0) -> 0.057775191 | D16: =IFERROR(L16/L$18,0) -> 0.12559923 | E16: =IFERROR(M16/M$18,0) -> 0.031736422 | F16: =IFERROR(N16/N$18,0) -> 0.032713394 | G16: =IFERROR(O16/O$18,0) -> 0.041051716 | K16: Other Non-Current Assets | L16: =SUMIF(INDIRECT("'"&L$2&"'!$A$1:$A$500"),$K17,INDIRECT("'"&L$2&"'!$C$1:$C$500"))-SUM(L12:L15) -> 14017 | M16: =SUMIF(INDIRECT("'"&M$2&"'!$A$1:$A$500"),$K17,INDIRECT("'"&M$2&"'!$C$1:$C$500"))-SUM(M12:M15) -> 6710 | N16: =SUMIF(INDIRECT("'"&N$2&"'!$A$1:$A$500"),$K17,INDIRECT("'"&N$2&"'!$C$1:$C$500"))-SUM(N12:N15) -> 5597 | O16: =SUMIF(INDIRECT("'"&O$2&"'!$A$1:$A$500"),$K17,INDIRECT("'"&O$2&"'!$C$1:$C$500"))-SUM(O12:O15) -> 3399
B17: Total Non-Current Assets | C17: =IFERROR(AVERAGE(D17:G17),0) -> 0.61198432 | D17: =IFERROR(L17/L$18,0) -> 0.28203152 | E17: =IFERROR(M17/M$18,0) -> 0.69877358 | F17: =IFERROR(N17/N$18,0) -> 0.81546186 | G17: =IFERROR(O17/O$18,0) -> 0.65167033 | K17: Total Non-Current Assets | L17: =SUM(L13:L16) -> 31475 | M17: =SUM(M13:M16) -> 147741 | N17: =SUM(N13:N16) -> 139519 | O17: =SUM(O13:O16) -> 53957
B18: Total Assets | C18: =IFERROR(AVERAGE(D18:G18),0) -> 1 | D18: =IFERROR(L18/L$18,0) -> 1 | E18: =IFERROR(M18/M$18,0) -> 1 | F18: =IFERROR(N18/N$18,0) -> 1 | G18: =IFERROR(O18/O$18,0) -> 1 | K18: Total Assets | L18: =L17+L11 -> 111601 | M18: =M17+M11 -> 211429 | N18: =N17+N11 -> 171092 | O18: =O17+O11 -> 82798
K19: Check Total Assets | L19: =ROUND(SUMIF(INDIRECT("'"&L$2&"'!$A$1:$A$500"),$K$18,INDIRECT("'"&L$2&"'!$C$1:$C$500"))-L18,2) -> 0 | M19: =ROUND(SUMIF(INDIRECT("'"&M$2&"'!$A$1:$A$500"),$K$18,INDIRECT("'"&M$2&"'!$C$1:$C$500"))-M18,2) -> 0 | N19: =ROUND(SUMIF(INDIRECT("'"&N$2&"'!$A$1:$A$500"),$K$18,INDIRECT("'"&N$2&"'!$C$1:$C$500"))-N18,2) -> 0 | O19: =ROUND(SUMIF(INDIRECT("'"&O$2&"'!$A$1:$A$500"),$K$18,INDIRECT("'"&O$2&"'!$C$1:$C$500"))-O18,2) -> 0
B20: Trade Accounts & Trade Notes Payable - Short-Term | C20: =IFERROR(AVERAGE(D20:G20),0) -> 0.038486151 | D20: =IFERROR(L20/L$18,0) -> 0.056540712 | E20: =IFERROR(M20/M$18,0) -> 0.046739094 | F20: =IFERROR(N20/N$18,0) -> 0.0091179015 | G20: =IFERROR(O20/O$18,0) -> 0.041546897 | K20: Trade Accounts & Trade Notes Payable - Short-Term | L20: =SUMIF(INDIRECT("'"&L$2&"'!$A$1:$A$500"),$K20,INDIRECT("'"&L$2&"'!$C$1:$C$500")) -> 6310 | M20: =SUMIF(INDIRECT("'"&M$2&"'!$A$1:$A$500"),$K20,INDIRECT("'"&M$2&"'!$C$1:$C$500")) -> 9882 | N20: =SUMIF(INDIRECT("'"&N$2&"'!$A$1:$A$500"),$K20,INDIRECT("'"&N$2&"'!$C$1:$C$500")) -> 1560 | O20: =SUMIF(INDIRECT("'"&O$2&"'!$A$1:$A$500"),$K20,INDIRECT("'"&O$2&"'!$C$1:$C$500")) -> 3440
B21: Short-Term Debt & Current Portion of Long-Term Debt | C21: =IFERROR(AVERAGE(D21:G21),0) -> 0.0093649772 | D21: =IFERROR(L21/L$18,0) -> 0 | E21: =IFERROR(M21/M$18,0) -> 0.012273624 | F21: =IFERROR(N21/N$18,0) -> 0.018422837 | G21: =IFERROR(O21/O$18,0) -> 0.0067634484 | K21: Short-Term Debt & Current Portion of Long-Term Debt | L21: =SUMIF(INDIRECT("'"&L$2&"'!$A$1:$A$500"),$K21,INDIRECT("'"&L$2&"'!$C$1:$C$500")) -> 0 | M21: =SUMIF(INDIRECT("'"&M$2&"'!$A$1:$A$500"),$K21,INDIRECT("'"&M$2&"'!$C$1:$C$500")) -> 2595 | N21: =SUMIF(INDIRECT("'"&N$2&"'!$A$1:$A$500"),$K21,INDIRECT("'"&N$2&"'!$C$1:$C$500")) -> 3152 | O21: =SUMIF(INDIRECT("'"&O$2&"'!$A$1:$A$500"),$K21,INDIRECT("'"&O$2&"'!$C$1:$C$500")) -> 560
B22: Other Current Liabilities | C22: =IFERROR(AVERAGE(D22:G22),0) -> 0.09154847 | D22: =IFERROR(L22/L$18,0) -> 0.10516931 | E22: =IFERROR(M22/M$18,0) -> 0.090328195 | F22: =IFERROR(N22/N$18,0) -> 0.080670049 | G22: =IFERROR(O22/O$18,0) -> 0.090026329 | K22: Other Current Liabilities | L22: =SUMIF(INDIRECT("'"&L$2&"'!$A$1:$A$500"),$K23,INDIRECT("'"&L$2&"'!$C$1:$C$500"))-SUM(L20:L21) -> 11737 | M22: =SUMIF(INDIRECT("'"&M$2&"'!$A$1:$A$500"),$K23,INDIRECT("'"&M$2&"'!$C$1:$C$500"))-SUM(M20:M21) -> 19098 | N22: =SUMIF(INDIRECT("'"&N$2&"'!$A$1:$A$500"),$K23,INDIRECT("'"&N$2&"'!$C$1:$C$500"))-SUM(N20:N21) -> 13802 | O22: =SUMIF(INDIRECT("'"&O$2&"'!$A$1:$A$500"),$K23,INDIRECT("'"&O$2&"'!$C$1:$C$500"))-SUM(O20:O21) -> 7454
B23: Total Current Liabilities | C23: =IFERROR(AVERAGE(D23:G23),0) -> 0.1393996 | D23: =IFERROR(L23/L$18,0) -> 0.16171002 | E23: =IFERROR(M23/M$18,0) -> 0.14934091 | F23: =IFERROR(N23/N$18,0) -> 0.10821079 | G23: =IFERROR(O23/O$18,0) -> 0.13833667 | K23: Total Current Liabilities | L23: =SUM(L20:L22) -> 18047 | M23: =SUM(M20:M22) -> 31575 | N23: =SUM(N20:N22) -> 18514 | O23: =SUM(O20:O22) -> 11454
K24: Check Current Liabilities | L24: =ROUND(SUMIF(INDIRECT("'"&L$2&"'!$A$1:$A$500"),$K$23,INDIRECT("'"&L$2&"'!$C$1:$C$500"))-L23,2) -> 0 | M24: =ROUND(SUMIF(INDIRECT("'"&M$2&"'!$A$1:$A$500"),$K$23,INDIRECT("'"&M$2&"'!$C$1:$C$500"))-M23,2) -> 0 | N24: =ROUND(SUMIF(INDIRECT("'"&N$2&"'!$A$1:$A$500"),$K$23,INDIRECT("'"&N$2&"'!$C$1:$C$500"))-N23,2) -> 0 | O24: =ROUND(SUMIF(INDIRECT("'"&O$2&"'!$A$1:$A$500"),$K$23,INDIRECT("'"&O$2&"'!$C$1:$C$500"))-O23,2) -> 0
B25: Debt - Long-Term - Total | C25: =IFERROR(AVERAGE(D25:G25),0) -> 0.20402456 | D25: =IFERROR(L25/L$18,0) -> 0.075832654 | E25: =IFERROR(M25/M$18,0) -> 0.20868944 | F25: =IFERROR(N25/N$18,0) -> 0.36228462 | G25: =IFERROR(O25/O$18,0) -> 0.16929153 | K25: Debt - Long-Term - Total | L25: =SUMIF(INDIRECT("'"&L$2&"'!$A$1:$A$500"),$K25,INDIRECT("'"&L$2&"'!$C$1:$C$500")) -> 8463 | M25: =SUMIF(INDIRECT("'"&M$2&"'!$A$1:$A$500"),$K25,INDIRECT("'"&M$2&"'!$C$1:$C$500")) -> 44123 | N25: =SUMIF(INDIRECT("'"&N$2&"'!$A$1:$A$500"),$K25,INDIRECT("'"&N$2&"'!$C$1:$C$500")) -> 61984 | O25: =SUMIF(INDIRECT("'"&O$2&"'!$A$1:$A$500"),$K25,INDIRECT("'"&O$2&"'!$C$1:$C$500")) -> 14017
B26: Other Non-Current Liabilities | C26: =IFERROR(AVERAGE(D26:G26),0) -> 0.047132057 | D26: =IFERROR(L26/L$18,0) -> 0.051648283 | E26: =IFERROR(M26/M$18,0) -> 0.044322207 | F26: =IFERROR(N26/N$18,0) -> 0.05436841 | G26: =IFERROR(O26/O$18,0) -> 0.038189328 | K26: Other Non-Current Liabilities | L26: =SUMIF(INDIRECT("'"&L$2&"'!$A$1:$A$500"),$K27,INDIRECT("'"&L$2&"'!$C$1:$C$500"))-L25 -> 5764 | M26: =SUMIF(INDIRECT("'"&M$2&"'!$A$1:$A$500"),$K27,INDIRECT("'"&M$2&"'!$C$1:$C$500"))-M25 -> 9371 | N26: =SUMIF(INDIRECT("'"&N$2&"'!$A$1:$A$500"),$K27,INDIRECT("'"&N$2&"'!$C$1:$C$500"))-N25 -> 9302 | O26: =SUMIF(INDIRECT("'"&O$2&"'!$A$1:$A$500"),$K27,INDIRECT("'"&O$2&"'!$C$1:$C$500"))-O25 -> 3162
B27: Total Non-Current Liabilities | C27: =IFERROR(AVERAGE(D27:G27),0) -> 0.25115662 | D27: =IFERROR(L27/L$18,0) -> 0.12748094 | E27: =IFERROR(M27/M$18,0) -> 0.25301165 | F27: =IFERROR(N27/N$18,0) -> 0.41665303 | G27: =IFERROR(O27/O$18,0) -> 0.20748086 | K27: Total Non-Current Liabilities | L27: =SUM(L25:L26) -> 14227 | M27: =SUM(M25:M26) -> 53494 | N27: =SUM(N25:N26) -> 71286 | O27: =SUM(O25:O26) -> 17179
B28: Total Liabilities | C28: =IFERROR(AVERAGE(D28:G28),0) -> 0.39055622 | D28: =IFERROR(L28/L$18,0) -> 0.28919096 | E28: =IFERROR(M28/M$18,0) -> 0.40235256 | F28: =IFERROR(N28/N$18,0) -> 0.52486382 | G28: =IFERROR(O28/O$18,0) -> 0.34581753 | K28: Total Liabilities | L28: =SUM(L27,L23) -> 32274 | M28: =SUM(M27,M23) -> 85069 | N28: =SUM(N27,N23) -> 89800 | O28: =SUM(O27,O23) -> 28633
K29: Check Total Liabilities | L29: =ROUND(SUMIF(INDIRECT("'"&L$2&"'!$A$1:$A$500"),$K$28,INDIRECT("'"&L$2&"'!$C$1:$C$500"))-L28,2) -> 0 | M29: =ROUND(SUMIF(INDIRECT("'"&M$2&"'!$A$1:$A$500"),$K$28,INDIRECT("'"&M$2&"'!$C$1:$C$500"))-M28,2) -> 0 | N29: =ROUND(SUMIF(INDIRECT("'"&N$2&"'!$A$1:$A$500"),$K$28,INDIRECT("'"&N$2&"'!$C$1:$C$500"))-N28,2) -> 0 | O29: =ROUND(SUMIF(INDIRECT("'"&O$2&"'!$A$1:$A$500"),$K$28,INDIRECT("'"&O$2&"'!$C$1:$C$500"))-O28,2) -> 0
B30: Common Equity - Total | C30: =IFERROR(AVERAGE(D30:G30),0) -> 0.59516121 | D30: =IFERROR(L30/L$18,0) -> 0.71080904 | E30: =IFERROR(M30/M$18,0) -> 0.54051715 | F30: =IFERROR(N30/N$18,0) -> 0.47513618 | G30: =IFERROR(O30/O$18,0) -> 0.65418247 | K30: Common Equity - Total | L30: =SUMIF(INDIRECT("'"&L$2&"'!$A$1:$A$500"),$K30,INDIRECT("'"&L$2&"'!$C$1:$C$500")) -> 79327 | M30: =SUMIF(INDIRECT("'"&M$2&"'!$A$1:$A$500"),$K30,INDIRECT("'"&M$2&"'!$C$1:$C$500")) -> 114281 | N30: =SUMIF(INDIRECT("'"&N$2&"'!$A$1:$A$500"),$K30,INDIRECT("'"&N$2&"'!$C$1:$C$500")) -> 81292 | O30: =SUMIF(INDIRECT("'"&O$2&"'!$A$1:$A$500"),$K30,INDIRECT("'"&O$2&"'!$C$1:$C$500")) -> 54165
B31: Other Shareholders' Equity | C31: =IFERROR(AVERAGE(D31:G31),0) -> 0.014282572 | D31: =IFERROR(L31/L$18,0) -> 0 | E31: =IFERROR(M31/M$18,0) -> 0.05713029 | F31: =IFERROR(N31/N$18,0) -> 0 | G31: =IFERROR(O31/O$18,0) -> 0 | K31: Other Shareholders' Equity | L31: =SUMIF(INDIRECT("'"&L$2&"'!$A$1:$A$500"),$K32,INDIRECT("'"&L$2&"'!$C$1:$C$500"))-L30 -> 0 | M31: =SUMIF(INDIRECT("'"&M$2&"'!$A$1:$A$500"),$K32,INDIRECT("'"&M$2&"'!$C$1:$C$500"))-M30 -> 12079 | N31: =SUMIF(INDIRECT("'"&N$2&"'!$A$1:$A$500"),$K32,INDIRECT("'"&N$2&"'!$C$1:$C$500"))-N30 -> 0 | O31: =SUMIF(INDIRECT("'"&O$2&"'!$A$1:$A$500"),$K32,INDIRECT("'"&O$2&"'!$C$1:$C$500"))-O30 -> 0
B32: Total Shareholders' Equity - including Minority Interest & Hybrid Debt | C32: =IFERROR(AVERAGE(D32:G32),0) -> 0.60944378 | D32: =IFERROR(L32/L$18,0) -> 0.71080904 | E32: =IFERROR(M32/M$18,0) -> 0.59764744 | F32: =IFERROR(N32/N$18,0) -> 0.47513618 | G32: =IFERROR(O32/O$18,0) -> 0.65418247 | K32: Total Shareholders' Equity - including Minority Interest & Hybrid Debt | L32: =SUM(L30:L31) -> 79327 | M32: =SUM(M30:M31) -> 126360 | N32: =SUM(N30:N31) -> 81292 | O32: =SUM(O30:O31) -> 54165
B33: Total Liabilities & Equity | C33: =IFERROR(AVERAGE(D33:G33),0) -> 1 | D33: =IFERROR(L33/L$18,0) -> 1 | E33: =IFERROR(M33/M$18,0) -> 1 | F33: =IFERROR(N33/N$18,0) -> 1 | G33: =IFERROR(O33/O$18,0) -> 1 | K33: Total Liabilities & Equity | L33: =L32+L28 -> 111601 | M33: =M32+M28 -> 211429 | N33: =N32+N28 -> 171092 | O33: =O32+O28 -> 82798
B34: Check | K34: Check Balance | L34: =ROUND(L18-L33,2) -> 0 | M34: =ROUND(M18-M33,2) -> 0 | N34: =ROUND(N18-N33,2) -> 0 | O34: =ROUND(O18-O33,2) -> 0
B36: Financial Statement | K36: Financial Statement | L36: 2025 | M36: 2025 | N36: 2025 | O36: 2025
B37: Revenue from Business Activities - Total | C37: =IFERROR(AVERAGE(D37:G37),0) -> 1 | D37: =IFERROR(L37/L$37,0) -> 1 | E37: =IFERROR(M37/M$37,0) -> 1 | F37: =IFERROR(N37/N$37,0) -> 1 | G37: =IFERROR(O37/O$37,0) -> 1 | K37: Revenue from Business Activities - Total | L37: =SUMIF(INDIRECT("'"&L$2&"'!$A$1:$A$500"),$K37,INDIRECT("'"&L$2&"'!$C$1:$C$500")) -> 130497 | M37: =SUMIF(INDIRECT("'"&M$2&"'!$A$1:$A$500"),$K37,INDIRECT("'"&M$2&"'!$C$1:$C$500")) -> 52853 | N37: =SUMIF(INDIRECT("'"&N$2&"'!$A$1:$A$500"),$K37,INDIRECT("'"&N$2&"'!$C$1:$C$500")) -> 63887 | O37: =SUMIF(INDIRECT("'"&O$2&"'!$A$1:$A$500"),$K37,INDIRECT("'"&O$2&"'!$C$1:$C$500")) -> 37378
B38: Cost of Sales | C38: =IFERROR(AVERAGE(D38:G38),0) -> 0.46436961 | D38: =IFERROR(L38/L$37,0) -> 0.25011303 | E38: =IFERROR(M38/M$37,0) -> 0.65233762 | F38: =IFERROR(N38/N$37,0) -> 0.35293565 | G38: =IFERROR(O38/O$37,0) -> 0.60209214 | K38: Cost of Operating Revenue | L38: =SUMIF(INDIRECT("'"&L$2&"'!$A$1:$A$500"),$K38,INDIRECT("'"&L$2&"'!$C$1:$C$500")) -> 32639 | M38: =SUMIF(INDIRECT("'"&M$2&"'!$A$1:$A$500"),$K38,INDIRECT("'"&M$2&"'!$C$1:$C$500")) -> 34478 | N38: =SUMIF(INDIRECT("'"&N$2&"'!$A$1:$A$500"),$K38,INDIRECT("'"&N$2&"'!$C$1:$C$500")) -> 22548 | O38: =SUMIF(INDIRECT("'"&O$2&"'!$A$1:$A$500"),$K38,INDIRECT("'"&O$2&"'!$C$1:$C$500")) -> 22505
B39: Gross Profit - Industrials/Property - Total | C39: =IFERROR(AVERAGE(D39:G39),0) -> 0.53563039 | D39: =IFERROR(L39/L$37,0) -> 0.74988697 | E39: =IFERROR(M39/M$37,0) -> 0.34766238 | F39: =IFERROR(N39/N$37,0) -> 0.64706435 | G39: =IFERROR(O39/O$37,0) -> 0.39790786 | K39: Gross Profit - Industrials/Property - Total | L39: =L37-L38 -> 97858 | M39: =M37-M38 -> 18375 | N39: =N37-N38 -> 41339 | O39: =O37-O38 -> 14873
B40: Selling, General & Administrative Expenses excluding Research & Development Expenses | C40: =IFERROR(AVERAGE(D40:G40),0) -> 0.053097745 | D40: =IFERROR(L40/L$37,0) -> 0.026751573 | E40: =IFERROR(M40/M$37,0) -> 0.087487938 | F40: =IFERROR(N40/N$37,0) -> 0.065913253 | G40: =IFERROR(O40/O$37,0) -> 0.032238215 | K40: Selling, General & Administrative Expenses excluding Research & Development Expenses | L40: =SUMIF( INDIRECT("'"&L$2&"'!$A$1:$A$500"), $K40, INDIRECT("'"&L$2&"'!$C$1:$C$500") ) -> 3491 | M40: =SUMIF( INDIRECT("'"&M$2&"'!$A$1:$A$500"), $K40, INDIRECT("'"&M$2&"'!$C$1:$C$500") ) -> 4624 | N40: =SUMIF( INDIRECT("'"&N$2&"'!$A$1:$A$500"), $K40, INDIRECT("'"&N$2&"'!$C$1:$C$500") ) -> 4211 | O40: =SUMIF( INDIRECT("'"&O$2&"'!$A$1:$A$500"), $K40, INDIRECT("'"&O$2&"'!$C$1:$C$500") ) -> 1205
B41: Research & Development Expense - Supplemental | C41: =IFERROR(AVERAGE(D41:G41),0) -> 0.15824983 | D41: =IFERROR(L41/L$37,0) -> 0.098960129 | E41: =IFERROR(M41/M$37,0) -> 0.26060962 | F41: =IFERROR(N41/N$37,0) -> 0.17181899 | G41: =IFERROR(O41/O$37,0) -> 0.10161057 | K41: Research & Development Expense - Supplemental | L41: =SUMIF( INDIRECT("'"&L$2&"'!$A$1:$A$500"), $K41, INDIRECT("'"&L$2&"'!$C$1:$C$500") ) -> 12914 | M41: =SUMIF( INDIRECT("'"&M$2&"'!$A$1:$A$500"), $K41, INDIRECT("'"&M$2&"'!$C$1:$C$500") ) -> 13774 | N41: =SUMIF( INDIRECT("'"&N$2&"'!$A$1:$A$500"), $K41, INDIRECT("'"&N$2&"'!$C$1:$C$500") ) -> 10977 | O41: =SUMIF( INDIRECT("'"&O$2&"'!$A$1:$A$500"), $K41, INDIRECT("'"&O$2&"'!$C$1:$C$500") ) -> 3798
B42: — | C42: =IFERROR(AVERAGE(D42:G42),0) -> 2.6753705e-05 | D42: =IFERROR(L42/L$37,0) -> 0 | E42: =IFERROR(M42/M$37,0) -> 0 | F42: =IFERROR(N42/N$37,0) -> 0 | G42: =IFERROR(O42/O$37,0) -> 0.00010701482 | K42: Other | L42: =SUMIF(INDIRECT("'"&L$2&"'!$A$1:$A$500"),$K$43,INDIRECT("'"&L$2&"'!$C$1:$C$500"))-L38-L40-L41 -> 0 | M42: =SUMIF(INDIRECT("'"&M$2&"'!$A$1:$A$500"),$K$43,INDIRECT("'"&M$2&"'!$C$1:$C$500"))-M38-M40-M41 -> 0 | N42: =SUMIF(INDIRECT("'"&N$2&"'!$A$1:$A$500"),$K$43,INDIRECT("'"&N$2&"'!$C$1:$C$500"))-N38-N40-N41 -> 0 | O42: =SUMIF(INDIRECT("'"&O$2&"'!$A$1:$A$500"),$K$43,INDIRECT("'"&O$2&"'!$C$1:$C$500"))-O38-O40-O41 -> 4
B43: Operating Expenses - Total | C43: =IFERROR(AVERAGE(D43:G43),0) -> 0.67574394 | D43: =IFERROR(L43/L$37,0) -> 0.37582473 | E43: =IFERROR(M43/M$37,0) -> 1.0004352 | F43: =IFERROR(N43/N$37,0) -> 0.5906679 | G43: =IFERROR(O43/O$37,0) -> 0.73604794 | K43: Operating Expenses - Total | L43: =SUM(L38,L40:L42) -> 49044 | M43: =SUM(M38,M40:M42) -> 52876 | N43: =SUM(N38,N40:N42) -> 37736 | O43: =SUM(O38,O40:O42) -> 27512
B44: Earnings before Interest & Taxes (EBIT) | C44: =IFERROR(AVERAGE(D44:G44),0) -> 0.32425606 | D44: =IFERROR(L44/L$37,0) -> 0.62417527 | E44: =IFERROR(M44/M$37,0) -> -0.00043516924 | F44: =IFERROR(N44/N$37,0) -> 0.4093321 | G44: =IFERROR(O44/O$37,0) -> 0.26395206 | K44: Earnings before Interest & Taxes (EBIT) | L44: =L37-L43 -> 81453 | M44: =M37-M43 -> -23 | N44: =N37-N43 -> 26151 | O44: =O37-O43 -> 9866
B45: Depreciation, Depletion & Amortization - Total | C45: =IFERROR(AVERAGE(D45:G45),0) -> 0.14946432 | D45: =IFERROR(L45/L$37,0) -> 0.014506081 | E45: =IFERROR(M45/M$37,0) -> 0.22148222 | F45: =IFERROR(N45/N$37,0) -> 0.13735189 | G45: =IFERROR(O45/O$37,0) -> 0.2245171 | K45: Depreciation, Depletion & Amortization - Total | L45: =SUMIF( INDIRECT("'"&L$2&"'!$A$1:$A$500"), $K45, INDIRECT("'"&L$2&"'!$C$1:$C$500") ) -> 1893 | M45: =SUMIF( INDIRECT("'"&M$2&"'!$A$1:$A$500"), $K45, INDIRECT("'"&M$2&"'!$C$1:$C$500") ) -> 11706 | N45: =SUMIF( INDIRECT("'"&N$2&"'!$A$1:$A$500"), $K45, INDIRECT("'"&N$2&"'!$C$1:$C$500") ) -> 8775 | O45: =SUMIF( INDIRECT("'"&O$2&"'!$A$1:$A$500"), $K45, INDIRECT("'"&O$2&"'!$C$1:$C$500") ) -> 8392
B46: Earnings before Interest, Taxes, Depreciation & Amortization (EBITDA) | C46: =IFERROR(AVERAGE(D46:G46),0) -> 0.47372039 | D46: =IFERROR(L46/L$37,0) -> 0.63868135 | E46: =IFERROR(M46/M$37,0) -> 0.22104706 | F46: =IFERROR(N46/N$37,0) -> 0.54668399 | G46: =IFERROR(O46/O$37,0) -> 0.48846915 | K46: Earnings before Interest, Taxes, Depreciation & Amortization (EBITDA) | L46: =L44+L45 -> 83346 | M46: =M44+M45 -> 11683 | N46: =N44+N45 -> 34926 | O46: =O44+O45 -> 18258
B47: Interest Expense - Net of (Interest Income) | C47: =IFERROR(AVERAGE(D47:G47),0) -> 0.0085252794 | D47: =IFERROR(L47/L$37,0) -> -0.011793375 | E47: =IFERROR(M47/M$37,0) -> 0.0015893138 | F47: =IFERROR(N47/N$37,0) -> 0.044813499 | G47: =IFERROR(O47/O$37,0) -> -0.0005083204 | K47: Interest Expense - Net of (Interest Income) | L47: =SUMIF( INDIRECT("'"&L$2&"'!$A$1:$A$500"), $K47, INDIRECT("'"&L$2&"'!$C$1:$C$500") ) -> -1539 | M47: =SUMIF( INDIRECT("'"&M$2&"'!$A$1:$A$500"), $K47, INDIRECT("'"&M$2&"'!$C$1:$C$500") ) -> 84 | N47: =SUMIF( INDIRECT("'"&N$2&"'!$A$1:$A$500"), $K47, INDIRECT("'"&N$2&"'!$C$1:$C$500") ) -> 2863 | O47: =SUMIF( INDIRECT("'"&O$2&"'!$A$1:$A$500"), $K47, INDIRECT("'"&O$2&"'!$C$1:$C$500") ) -> -19
B48: Other | C48: =IFERROR(AVERAGE(D48:G48),0) -> 0.0061192932 | D48: =IFERROR(L48/L$37,0) -> 0.0079235538 | E48: =IFERROR(M48/M$37,0) -> 0.031483549 | F48: =IFERROR(N48/N$37,0) -> -0.0087498239 | G48: =IFERROR(O48/O$37,0) -> -0.0061801059 | K48: Other | L48: =SUMIF(INDIRECT("'"&L$2&"'!$A$1:$A$500"),$K$49,INDIRECT("'"&L$2&"'!$C$1:$C$500"))-L44+L47 -> 1034 | M48: =SUMIF(INDIRECT("'"&M$2&"'!$A$1:$A$500"),$K$49,INDIRECT("'"&M$2&"'!$C$1:$C$500"))-M44+M47 -> 1664 | N48: =SUMIF(INDIRECT("'"&N$2&"'!$A$1:$A$500"),$K$49,INDIRECT("'"&N$2&"'!$C$1:$C$500"))-N44+N47 -> -559 | O48: =SUMIF(INDIRECT("'"&O$2&"'!$A$1:$A$500"),$K$49,INDIRECT("'"&O$2&"'!$C$1:$C$500"))-O44+O47 -> -231
B49: Income before Taxes | C49: =IFERROR(AVERAGE(D49:G49),0) -> 0.32185008 | D49: =IFERROR(L49/L$37,0) -> 0.6438922 | E49: =IFERROR(M49/M$37,0) -> 0.029459066 | F49: =IFERROR(N49/N$37,0) -> 0.35576878 | G49: =IFERROR(O49/O$37,0) -> 0.25828027 | K49: Income before Taxes | L49: =L44-L47+L48 -> 84026 | M49: =M44-M47+M48 -> 1557 | N49: =N44-N47+N48 -> 22729 | O49: =O44-O47+O48 -> 9654
B50: Income Taxes | C50: =IFERROR(AVERAGE(D50:G50),0) -> 0.034559032 | D50: =IFERROR(L50/L$37,0) -> 0.085411925 | E50: =IFERROR(M50/M$37,0) -> 0.028967135 | F50: =IFERROR(N50/N$37,0) -> -0.0062140968 | G50: =IFERROR(O50/O$37,0) -> 0.030071165 | K50: Income Taxes | L50: =SUMIF(INDIRECT("'"&L$2&"'!$A$1:$A$500"),$K$50,INDIRECT("'"&L$2&"'!$C$1:$C$500")) -> 11146 | M50: =SUMIF(INDIRECT("'"&M$2&"'!$A$1:$A$500"),$K$50,INDIRECT("'"&M$2&"'!$C$1:$C$500")) -> 1531 | N50: =SUMIF(INDIRECT("'"&N$2&"'!$A$1:$A$500"),$K$50,INDIRECT("'"&N$2&"'!$C$1:$C$500")) -> -397 | O50: =SUMIF(INDIRECT("'"&O$2&"'!$A$1:$A$500"),$K$50,INDIRECT("'"&O$2&"'!$C$1:$C$500")) -> 1124
B51: Other | C51: =IFERROR(AVERAGE(D51:G51),0) -> -0.0013257236 | D51: =IFERROR(L51/L$37,0) -> 0 | E51: =IFERROR(M51/M$37,0) -> -0.0055436777 | F51: =IFERROR(N51/N$37,0) -> 0 | G51: =IFERROR(O51/O$37,0) -> 0.00024078335 | K51: Other | L51: =SUMIF(INDIRECT("'"&L$2&"'!$A$1:$A$500"),$K$52,INDIRECT("'"&L$2&"'!$C$1:$C$500"))-(L49-L50) -> 0 | M51: =SUMIF(INDIRECT("'"&M$2&"'!$A$1:$A$500"),$K$52,INDIRECT("'"&M$2&"'!$C$1:$C$500"))-(M49-M50) -> -293 | N51: =SUMIF(INDIRECT("'"&N$2&"'!$A$1:$A$500"),$K$52,INDIRECT("'"&N$2&"'!$C$1:$C$500"))-(N49-N50) -> 0 | O51: =SUMIF(INDIRECT("'"&O$2&"'!$A$1:$A$500"),$K$52,INDIRECT("'"&O$2&"'!$C$1:$C$500"))-(O49-O50) -> 9
B52: Net Income after Minority Interest | C52: =IFERROR(AVERAGE(D52:G52),0) -> 0.28596532 | D52: =IFERROR(L52/L$37,0) -> 0.55848027 | E52: =IFERROR(M52/M$37,0) -> -0.0050517473 | F52: =IFERROR(N52/N$37,0) -> 0.36198288 | G52: =IFERROR(O52/O$37,0) -> 0.22844989 | K52: Net Income after Minority Interest | L52: =L49-L50+L51 -> 72880 | M52: =M49-M50+M51 -> -267 | N52: =N49-N50+N51 -> 23126 | O52: =O49-O50+O51 -> 8539
K53: Check Net Income | L53: =ROUND(SUMIF(INDIRECT("'"&L$2&"'!$A$1:$A$500"),$K$52,INDIRECT("'"&L$2&"'!$C$1:$C$500"))-L52,2) -> 0 | M53: =ROUND(SUMIF(INDIRECT("'"&M$2&"'!$A$1:$A$500"),$K$52,INDIRECT("'"&M$2&"'!$C$1:$C$500"))-M52,2) -> 0 | N53: =ROUND(SUMIF(INDIRECT("'"&N$2&"'!$A$1:$A$500"),$K$52,INDIRECT("'"&N$2&"'!$C$1:$C$500"))-N52,2) -> 0 | O53: =ROUND(SUMIF(INDIRECT("'"&O$2&"'!$A$1:$A$500"),$K$52,INDIRECT("'"&O$2&"'!$C$1:$C$500"))-O52,2) -> 0
B55: Indicadores de Liquidez (Liquidity Ratios) | K55: Indicadores de Liquidez (Liquidity Ratios)
B56: Razón corriente (CR) | C56: =IFERROR(AVERAGE(D56:G56),0) -> 2.6700583 | D56: =L56 -> 4.4398515 | E56: =M56 -> 2.0170388 | F56: =N56 -> 1.7053581 | G56: =O56 -> 2.517985 | K56: Razón corriente (CR) | L56: =IFERROR(L11/L23,0) -> 4.4398515 | M56: =IFERROR(M11/M23,0) -> 2.0170388 | N56: =IFERROR(N11/N23,0) -> 1.7053581 | O56: =IFERROR(O11/O23,0) -> 2.517985
B57: Prueba ácida (QR) | C57: =IFERROR(AVERAGE(D57:G57),0) -> 1.940977 | D57: =L57 -> 3.6723555 | E57: =M57 -> 1.3065717 | F57: =N57 -> 1.2597494 | G57: =O57 -> 1.5252314 | K57: Prueba ácida (QR) | L57: =IFERROR(SUM(L6:L8)/L23,0) -> 3.6723555 | M57: =IFERROR(SUM(M6:M8)/M23,0) -> 1.3065717 | N57: =IFERROR(SUM(N6:N8)/N23,0) -> 1.2597494 | O57: =IFERROR(SUM(O6:O8)/O23,0) -> 1.5252314
B58: Capital de trabajo neto (NWC) (USD mm) | C58: =IFERROR(AVERAGE(D58:G58),0) -> 31159.5 | D58: =L58 -> 62079 | E58: =M58 -> 32113 | F58: =N58 -> 13059 | G58: =O58 -> 17387 | K58: Capital de trabajo neto (NWC) (USD mm) | L58: =L11-L23 -> 62079 | M58: =M11-M23 -> 32113 | N58: =N11-N23 -> 13059 | O58: =O11-O23 -> 17387
B59: Administración de Activos (Efficiency Ratios) | C59: =IFERROR(AVERAGE(D59:G59),0) -> 0 | D59: =L59 -> 0 | E59: =M59 -> 0 | F59: =N59 -> 0 | K59: Administración de Activos (Efficiency Ratios)
B60: Rotación de inventario (ITR) | C60: =IFERROR(AVERAGE(D60:G60),0) -> 5.2367649 | D60: =L60 -> 4.2493165 | E60: =M60 -> 2.8953645 | F60: =N60 -> 11.190074 | G60: =O60 -> 2.6123041 | K60: Rotación de inventario (ITR) | L60: =IFERROR(L38/AVERAGE(L9,SUMIF(INDIRECT("'"&L$2&"'!$A$1:$A$500"),$K$9,INDIRECT("'"&L$2&"'!$B$1:$B$500"))),0) -> 4.2493165 | M60: =IFERROR(M38/AVERAGE(M9,SUMIF(INDIRECT("'"&M$2&"'!$A$1:$A$500"),$K$9,INDIRECT("'"&M$2&"'!$B$1:$B$500"))),0) -> 2.8953645 | N60: =IFERROR(N38/AVERAGE(N9,SUMIF(INDIRECT("'"&N$2&"'!$A$1:$A$500"),$K$9,INDIRECT("'"&N$2&"'!$B$1:$B$500"))),0) -> 11.190074 | O60: =IFERROR(O38/AVERAGE(O9,SUMIF(INDIRECT("'"&O$2&"'!$A$1:$A$500"),$K$9,INDIRECT("'"&O$2&"'!$B$1:$B$500"))),0) -> 2.6123041
B61: Rotación de activos fijos netos (FAT) | C61: =IFERROR(AVERAGE(D61:G61),0) -> 8.5126145 | D61: =L61 -> 16.158618 | E61: =M61 -> 0.49939056 | F61: =N61 -> 16.602651 | G61: =O61 -> 0.78979842 | K61: Rotación de activos fijos netos (FAT) | L61: =IFERROR(L37/L14,0) -> 16.158618 | M61: =IFERROR(M37/M14,0) -> 0.49939056 | N61: =IFERROR(N37/N14,0) -> 16.602651 | O61: =IFERROR(O37/O14,0) -> 0.78979842
B62: Rotación de activos totales (ATR) | C62: =IFERROR(AVERAGE(D62:G62),0) -> 0.56103517 | D62: =L62 -> 1.1693175 | E62: =M62 -> 0.2499799 | F62: =N62 -> 0.37340729 | G62: =O62 -> 0.45143603 | K62: Rotación de activos totales (ATR) | L62: =IFERROR(L37/L18,0) -> 1.1693175 | M62: =IFERROR(M37/M18,0) -> 0.2499799 | N62: =IFERROR(N37/N18,0) -> 0.37340729 | O62: =IFERROR(O37/O18,0) -> 0.45143603
B63: Días promedio de cartera (DSO) | C63: =IFERROR(AVERAGE(D63:G63),0) -> 50.448262 | D63: =L63 -> 64.512786 | E63: =M63 -> 26.511929 | F63: =N63 -> 40.820903 | G63: =O63 -> 69.947429 | K63: Días promedio de cartera (DSO) | L63: =IFERROR(L8/(L37/365),0) -> 64.512786 | M63: =IFERROR(M8/(M37/365),0) -> 26.511929 | N63: =IFERROR(N8/(N37/365),0) -> 40.820903 | O63: =IFERROR(O8/(O37/365),0) -> 69.947429
B64: Días promedio de inventario (DIO) | C64: =IFERROR(AVERAGE(D64:G64),0) -> 101.99254 | D64: =L64 -> 112.72404 | E64: =M64 -> 122.9935 | F64: =N64 -> 36.746053 | G64: =O64 -> 135.50655 | K64: Días promedio de inventario (DIO) | L64: =IFERROR(L9/(L38/365),0) -> 112.72404 | M64: =IFERROR(M9/(M38/365),0) -> 122.9935 | N64: =IFERROR(N9/(N38/365),0) -> 36.746053 | O64: =IFERROR(O9/(O38/365),0) -> 135.50655
B65: Periodo promedio de pago (DPO) | C65: =IFERROR(AVERAGE(D65:G65),0) -> 64.056151 | D65: =L65 -> 70.564356 | E65: =M65 -> 104.61541 | F65: =N65 -> 25.252794 | G65: =O65 -> 55.792046 | K65: Periodo promedio de pago (DPO) | L65: =IFERROR(L20/(L38/365),0) -> 70.564356 | M65: =IFERROR(M20/(M38/365),0) -> 104.61541 | N65: =IFERROR(N20/(N38/365),0) -> 25.252794 | O65: =IFERROR(O20/(O38/365),0) -> 55.792046
B66: Ciclo operativo (OC) | C66: =IFERROR(AVERAGE(D66:G66),0) -> 152.4408 | D66: =L66 -> 177.23683 | E66: =M66 -> 149.50543 | F66: =N66 -> 77.566955 | G66: =O66 -> 205.45398 | K66: Ciclo operativo (OC) | L66: =L63+L64 -> 177.23683 | M66: =M63+M64 -> 149.50543 | N66: =N63+N64 -> 77.566955 | O66: =O63+O64 -> 205.45398
B67: Ciclo de efectivo (CC) | C67: =IFERROR(AVERAGE(D67:G67),0) -> 88.384649 | D67: =L67 -> 106.67247 | E67: =M67 -> 44.890025 | F67: =N67 -> 52.314161 | G67: =O67 -> 149.66194 | K67: Ciclo de efectivo (CC) | L67: =L63+L64-L65 -> 106.67247 | M67: =M63+M64-M65 -> 44.890025 | N67: =N63+N64-N65 -> 52.314161 | O67: =O63+O64-O65 -> 149.66194
B68: Administración de Pasivos (Leverage Ratios) | K68: Administración de Pasivos (Leverage Ratios)
B69: Nivel de endeudamiento (Debt to Assets) | C69: =IFERROR(AVERAGE(D69:G69),0) -> 0.39055622 | D69: =L69 -> 0.28919096 | E69: =M69 -> 0.40235256 | F69: =N69 -> 0.52486382 | G69: =O69 -> 0.34581753 | K69: Nivel de endeudamiento (Debt to Assets) | L69: =IFERROR(L28/L18,0) -> 0.28919096 | M69: =IFERROR(M28/M18,0) -> 0.40235256 | N69: =IFERROR(N28/N18,0) -> 0.52486382 | O69: =IFERROR(O28/O18,0) -> 0.34581753
B70: Cobertura de intereses (Interest Coverage) | C70: =IFERROR(AVERAGE(D70:G70),0) -> -140.83219 | D70: =L70 -> -52.925926 | E70: =M70 -> -0.27380952 | F70: =N70 -> 9.134125 | G70: =O70 -> -519.26316 | K70: Cobertura de intereses (Interest Coverage) | L70: =IFERROR(L44/L47,0) -> -52.925926 | M70: =IFERROR(M44/M47,0) -> -0.27380952 | N70: =IFERROR(N44/N47,0) -> 9.134125 | O70: =IFERROR(O44/O47,0) -> -519.26316
B71: Indicadores de Rentabilidad (Profitability Ratios) | K71: Indicadores de Rentabilidad (Profitability Ratios)
B72: Margen neto (NPM) | C72: =IFERROR(AVERAGE(D72:G72),0) -> 0.28596532 | D72: =L72 -> 0.55848027 | E72: =M72 -> -0.0050517473 | F72: =N72 -> 0.36198288 | G72: =O72 -> 0.22844989 | K72: Margen neto (NPM) | L72: =IFERROR(L52/L37,0) -> 0.55848027 | M72: =IFERROR(M52/M37,0) -> -0.0050517473 | N72: =IFERROR(N52/N37,0) -> 0.36198288 | O72: =IFERROR(O52/O37,0) -> 0.22844989
B73: Margen operacional (OM) | C73: =IFERROR(AVERAGE(D73:G73),0) -> 0.32425606 | D73: =L73 -> 0.62417527 | E73: =M73 -> -0.00043516924 | F73: =N73 -> 0.4093321 | G73: =O73 -> 0.26395206 | K73: Margen operacional (OM) | L73: =IFERROR(L44/L37,0) -> 0.62417527 | M73: =IFERROR(M44/M37,0) -> -0.00043516924 | N73: =IFERROR(N44/N37,0) -> 0.4093321 | O73: =IFERROR(O44/O37,0) -> 0.26395206
B74: ROA | C74: =IFERROR(AVERAGE(D74:G74),0) -> 0.22251887 | D74: =L74 -> 0.65304074 | E74: =M74 -> -0.0012628353 | F74: =N74 -> 0.13516704 | G74: =O74 -> 0.10313051 | K74: ROA | L74: =IFERROR(L52/L18,0) -> 0.65304074 | M74: =IFERROR(M52/M18,0) -> -0.0012628353 | N74: =IFERROR(N52/N18,0) -> 0.13516704 | O74: =IFERROR(O52/O18,0) -> 0.10313051
B75: ROE | C75: =IFERROR(AVERAGE(D75:G75),0) -> 0.33968609 | D75: =L75 -> 0.91872881 | E75: =M75 -> -0.0021130104 | F75: =N75 -> 0.28448064 | G75: =O75 -> 0.15764793 | K75: ROE | L75: =IFERROR(L52/L32,0) -> 0.91872881 | M75: =IFERROR(M52/M32,0) -> -0.0021130104 | N75: =IFERROR(N52/N32,0) -> 0.28448064 | O75: =IFERROR(O52/O32,0) -> 0.15764793
B76: ROC | C76: =IFERROR(AVERAGE(D76:G76),0) -> 0.27831607 | D76: =L76 -> 0.80474208 | E76: =M76 -> -2.2190685e-06 | F76: =N76 -> 0.18171232 | G76: =O76 -> 0.1268121 | K76: ROC | L76: =IFERROR((L44*(1-IFERROR(L50/L49,0)))/(L21+L25+L32),0) -> 0.80474208 | M76: =IFERROR((M44*(1-IFERROR(M50/M49,0)))/(M21+M25+M32),0) -> -2.2190685e-06 | N76: =IFERROR((N44*(1-IFERROR(N50/N49,0)))/(N21+N25+N32),0) -> 0.18171232 | O76: =IFERROR((O44*(1-IFERROR(O50/O49,0)))/(O21+O25+O32),0) -> 0.1268121
B77: ROIC | C77: =IFERROR(AVERAGE(D77:G77),0) -> 0.2919623 | D77: =L77 -> 0.83149893 | E77: =M77 -> -2.319429e-06 | F77: =N77 -> 0.19507163 | G77: =O77 -> 0.14128095 | K77: ROIC | L77: =IFERROR((L44*(1-IFERROR(L50/L49,0)))/(L17+(L11-L6-L23)),0) -> 0.83149893 | M77: =IFERROR((M44*(1-IFERROR(M50/M49,0)))/(M17+(M11-M6-M23)),0) -> -2.319429e-06 | N77: =IFERROR((N44*(1-IFERROR(N50/N49,0)))/(N17+(N11-N6-N23)),0) -> 0.19507163 | O77: =IFERROR((O44*(1-IFERROR(O50/O49,0)))/(O17+(O11-O6-O23)),0) -> 0.14128095
B78: ROCE | C78: =IFERROR(AVERAGE(D78:G78),0) -> 0.26293342 | D78: =L78 -> 0.75516073 | E78: =M78 -> -2.1354651e-06 | F78: =N78 -> 0.17438799 | G78: =O78 -> 0.12218711 | K78: ROCE | L78: =IFERROR((L44*(1-IFERROR(L50/L49,0)))/(L18-L23),0) -> 0.75516073 | M78: =IFERROR((M44*(1-IFERROR(M50/M49,0)))/(M18-M23),0) -> -2.1354651e-06 | N78: =IFERROR((N44*(1-IFERROR(N50/N49,0)))/(N18-N23),0) -> 0.17438799 | O78: =IFERROR((O44*(1-IFERROR(O50/O49,0)))/(O18-O23),0) -> 0.12218711

Sheet NVIDIA
A1: Company Fundamentals - Balance Sheet
A2: Company Name | B2: NVIDIA Corporation (NVDA.OQ)
A3: Country of Exchange | B3: United States of America
A4: Country of Headquarters | B4: United States of America
A5: TRBC Industry Group | B5: Semiconductors & Semiconductor Equipment
A6: CF Template | B6: IND
A7: Consolidation Basis | B7: Consolidated
A8: Scaling | B8: Millions
A9: Period | B9: Annual
A10: Export Date | B10: 46295.602
A11: Statement Data | B11: 2024 | C11: 2025
A12: Period End Date | B12: 45319 | C12: 45683
A13: Standardized Currency | B13: USD | C13: USD
A14: Balance Sheet - Standardized (Currency: US Dollar)
A15: Field Name | B15: 27-01-2024 | C15: 25-01-2025
A16: Current Assets
A17: Cash & Short-Term Investments | B17: 25984 | C17: 43210
A18: Cash & Cash Equivalents | B18: 7280 | C18: 8589
A19: Short-Term Investments - Total | B19: 18704 | C19: 34621
A20: Loans & Receivables - Net - Short-Term | B20: 9999 | C20: 23065
A21: Trade Accounts & Trade Notes Receivable - Net | B21: 9999 | C21: 23065
A22: Trade Accounts & Trade Notes Receivable - Gross | B22: 10003 | C22: 23069
A23: Provision - Trade Accounts & Trade Notes Receivable | B23: 4 | C23: 4
A24: Inventories - Total | B24: 5282 | C24: 10080
A25: Inventories - Raw Materials | B25: 1719 | C25: 3408
A26: Inventories - Work in Progress | B26: 1505 | C26: 3399
A27: Inventories - Finished Goods | B27: 2058 | C27: 3273
A28: Prepaid Expenses - Short-Term | B28: 3080 | C28: 3771
A29: Total Current Assets | B29: 44345 | C29: 80126
A30: Non-Current Assets
A31: Investments - Long-Term | C31: 3387
A32: Investments - Available for Sale/Held to Maturity - Long-Term | C32: 3387
A33: Investments in Associates, Joint Ventures and Unconsolidated Subsidiaries | B33: 1546
A34: Receivables & Loans - Long-Term | C34: 750
A35: Receivables - Other - Net - Long-Term | C35: 750
A36: Property, Plant & Equipment - Net - Total | B36: 5260 | C36: 8076
A37: Property, Plant & Equipment - excluding Assets Leased Out - Net - Total | B37: 5260 | C37: 8076
A38: Property, Plant & Equipment - Gross - Total | B38: 8769 | C38: 12477
A39: Property, Plant & Equipment - excluding Assets Leased Out - Gross | B39: 8769 | C39: 12477
A40: Land & Buildings - Gross | B40: 2034 | C40: 2587
A41: Land/Improvements - Gross | B41: 218 | C41: 511
A42: Buildings - Gross | B42: 1816 | C42: 2076
A43: Plant, Machinery & Equipment - Gross | B43: 5200 | C43: 7568
A44: Construction in Progress - Gross | B44: 189 | C44: 529
A45: Right of Use Tangible Assets - Total - Gross | B45: 1346 | C45: 1793
A46: Right of Use Tangible Assets - Operating Lease - Gross | B46: 1346 | C46: 1793
A47: Property, Plant & Equipment - Accumulated Depreciation & Impairment - Total | B47: 3509 | C47: 4401
... A58: Total Non-Current Assets | B58: 21383 | C58: 31475
A59: Total Assets
A60: Total Assets | B60: 65728 | C60: 111601
A61: Current Liabilities
A62: Trade Accounts Payable & Accruals - Short-Term | B62: 7479 | C62: 14440
A63: Trade Accounts & Trade Notes Payable - Short-Term | B63: 2699 | C63: 6310
A64: Accrued Expenses - Short-Term | B64: 4780 | C64: 8130
A65: Short-Term Debt & Current Portion of Long-Term Debt | B65: 1250 | C65: 0
A66: Current Portion of Long-Term Debt including Capitalized Leases | B66: 1250 | C66: 0
A67: Current Portion of Long-Term Debt excluding Capitalized Leases | B67: 1250 | C67: 0
A68: Income Taxes - Payable - Short-Term | B68: 296 | C68: 881
A69: Operating Lease Liabilities - Current Portion/Short-Term | B69: 228 | C69: 288
A70: Other Current Liabilities - Total | B70: 1378 | C70: 2438
A71: Deferred Income - Short-Term | B71: 764 | C71: 837
A72: Provisions - Short-Term | B72: 415 | C72: 1373
A73: Other Current Liabilities | B73: 199 | C73: 228
A74: Total Current Liabilities | B74: 10631 | C74: 18047
A75: Non-Current Liabilities
A76: Debt - Long-Term - Total | B76: 8459 | C76: 8463
A77: Long-Term Debt excluding Capitalized Leases | B77: 8459 | C77: 8463
A78: Debt - Non-Convertible - Long-Term | B78: 8459 | C78: 8463
A79: Deferred Tax & Investment Tax Credits - Long-Term | B79: 462 | C79: 886
A80: Deferred Tax - Liability - Long-Term | B80: 462 | C80: 886
A81: Operating Lease Liabilities - Long-Term | B81: 1119 | C81: 1519
A82: Other Non-Current Liabilities - Total | B82: 2079 | C82: 3359
A83: Deferred Revenue - Long-Term | B83: 573 | C83: 976
A84: Other Non-Current Liabilities | B84: 1506 | C84: 2383
A85: Total Non-Current Liabilities | B85: 12119 | C85: 14227
A86: Total Liabilities
A87: Total Liabilities | B87: 22750 | C87: 32274
A88: Shareholders' Equity
A89: Shareholders' Equity - Attributable to Parent Shareholders - Total | B89: 42978 | C89: 79327
A90: Preferred Shareholders Equity | C90: 0
A91: Preferred Stock - Non-Redeemable | C91: 0
A92: Common Equity Attributable to Parent Shareholders | B92: 42978 | C92: 79327
A93: Common Equity - Contributed | B93: 13134 | C93: 11261
A94: Common Stock - Issued & Paid | B94: 2 | C94: 24
A95: Common Stock - Additional Paid in Capital including Option Reserve | B95: 13132 | C95: 11237
A96: Equity - Non-Contributed - Reserves & Retained Earnings | B96: 29844 | C96: 68066
A97: Retained Earnings - Total | B97: 29817 | C97: 68038
A98: Comprehensive Income - Accumulated - Total | B98: 27 | C98: 28
A99: Common Equity - Total | B99: 42978 | C99: 79327
A100: Total Shareholders' Equity
A101: Total Shareholders' Equity - including Minority Interest & Hybrid Debt | B101: 42978 | C101: 79327
A102: Total Liabilities & Shareholders' Equity
A103: Total Liabilities & Equity | B103: 65728 | C103: 111601
A104: Share/Per Share - Common
A105: Common Shares - Issued - Total | B105: 24640 | C105: 24477
A106: Common Shares - Outstanding - Total | B106: 24640 | C106: 24477
A107: Common Shares - Treasury - Total | B107: 0 | C107: 0
A108: Common Shares - Authorized - Issue Specific | B108: 80000 | C108: 80000
A109: Common Shares - Issued - Issue Specific | B109: 24640 | C109: 24477
A110: Common Shares - Outstanding - Issue Specific | B110: 24640 | C110: 24477
...

Sheet Intel
A1: Company Fundamentals - Balance Sheet
A2: Company Name | B2: Intel Corp (INTC.OQ)
A3: Country of Exchange | B3: United States of America
A4: Country of Headquarters | B4: United States of America
A5: TRBC Industry Group | B5: Semiconductors & Semiconductor Equipment
A6: CF Template | B6: IND
A7: Consolidation Basis | B7: Consolidated
A8: Scaling | B8: Millions
A9: Period | B9: Annual
A10: Export Date | B10: 46296.629
A11: Statement Data | B11: 2024 | C11: 2025
A12: Period End Date | B12: 45654 | C12: 46018
A13: Standardized Currency | B13: USD | C13: USD
A14: Balance Sheet - Standardized (Currency: US Dollar)
A15: Field Name | B15: 27-12-2024 | C15: 26-12-2025
A16: Current Assets
A17: Cash & Short-Term Investments | B17: 22062 | C17: 37416
A18: Cash & Cash Equivalents | B18: 8249 | C18: 14265
A19: Short-Term Investments - Total | B19: 13813 | C19: 23151
A20: Loans & Receivables - Net - Short-Term | B20: 6078 | C20: 11439
A21: Trade Accounts & Trade Notes Receivable - Net | B21: 3478 | C21: 3839
A22: Income Tax - Receivables - Short-Term | B22: 2600 | C22: 7600
A23: Inventories - Total | B23: 12198 | C23: 11618
A24: Inventories - Raw Materials | B24: 1344 | C24: 993
A25: Inventories - Work in Progress | B25: 7432 | C25: 7840
A26: Inventories - Finished Goods | B26: 3422 | C26: 2785
A27: Other Current Assets - Total | B27: 6986 | C27: 3215
A28: Other Current Assets | B28: 6986 | C28: 3215
A29: Total Current Assets | B29: 47324 | C29: 63688
A30: Non-Current Assets
A31: Investments - Long-Term | B31: 5383 | C31: 8512
A32: Investments - Available for Sale/Held to Maturity - Long-Term | B32: 5383 | C32: 8512
A33: Marketable Securities - Long-Term | B33: 848 | C33: 484
A34: Derivative Financial Instruments - Hedging - Long-Term | B34: 1 | C34: 2
A35: Property, Plant & Equipment - Net - Total | B35: 108376 | C35: 105835
A36: Property, Plant & Equipment - excluding Assets Leased Out - Net - Total | B36: 108376 | C36: 105835
A37: Property, Plant & Equipment - Gross - Total | B37: 210569 | C37: 212299
A38: Property, Plant & Equipment - excluding Assets Leased Out - Gross | B38: 210569 | C38: 212299
A39: Land & Buildings - Gross | B39: 56544 | C39: 65395
A40: Plant, Machinery & Equipment - Gross | B40: 103150 | C40: 111940
A41: Construction in Progress - Gross | B41: 50418 | C41: 34543
A42: Right of Use Tangible Assets - Total - Gross | B42: 457 | C42: 421
... A46: Other Non-Current Assets - Total | B46: 7017 | C46: 6708
A47: Restricted Accounts - Long-Term | C47: 447
A48: Deferred Tax - Asset - Long-Term | B48: 603 | C48: 570
A49: Other Non-Current Assets | B49: 6414 | C49: 5691
A50: Intangible Assets - Total - Net | B50: 28384 | C50: 26684
A51: Goodwill/Cost in Excess of Assets Purchased - Net | B51: 24693 | C51: 23912
A52: Intangible Assets - excluding Goodwill - Net - Total | B52: 3691 | C52: 2772
A53: Computer Software - Intangible Assets - Net | B53: 1617 | C53: 967
A54: Licenses, Franchises, Copyrights, Property Rights, Prototypes, Contract Based, Models & Designs - Net | B54: 1535 | C54: 1577
A55: Intangible Assets - Other - Net | B55: 539 | C55: 228
A56: Total Non-Current Assets | B56: 149161 | C56: 147741
A57: Total Assets
A58: Total Assets | B58: 196485 | C58: 211429
A59: Current Liabilities
A60: Trade Accounts Payable & Accruals - Short-Term | B60: 30000 | C60: 28362
A61: Trade Accounts & Trade Notes Payable - Short-Term | B61: 12556 | C61: 9882
A62: Accrued Expenses - Short-Term | B62: 17444 | C62: 18480
A63: Short-Term Debt & Current Portion of Long-Term Debt | B63: 3836 | C63: 2595
A64: Current Portion of Long-Term Debt including Capitalized Leases | B64: 3836 | C64: 2595
A65: Current Portion of Long-Term Debt excluding Capitalized Leases | B65: 3729 | C65: 2499
A66: Capitalized Leases - Current Portion | B66: 107 | C66: 96
A67: Income Taxes - Payable - Short-Term | B67: 1756 | C67: 604
A68: Operating Lease Liabilities - Current Portion/Short-Term | B68: 181 | C68: 110
A69: Other Current Liabilities - Total | B69: -107 | C69: -96
A70: Other Current Liabilities | B70: -107 | C70: -96
A71: Total Current Liabilities | B71: 35666 | C71: 31575
A72: Non-Current Liabilities
A73: Debt - Long-Term - Total | B73: 46410 | C73: 44123
A74: Long-Term Debt excluding Capitalized Leases | B74: 46282 | C74: 44086
A75: Debt - Non-Convertible - Long-Term | B75: 46282 | C75: 44086
A76: Capitalized Lease Obligations - Long-Term | B76: 128 | C76: 37
A77: Operating Lease Liabilities - Long-Term | B77: 279 | C77: 281
A78: Other Non-Current Liabilities - Total | B78: 9098 | C78: 9090
A79: Other Non-Current Liabilities | B79: 9098 | C79: 9090
A80: Total Non-Current Liabilities | B80: 55787 | C80: 53494
A81: Total Liabilities
A82: Total Liabilities | B82: 91453 | C82: 85069
A83: Shareholders' Equity
A84: Shareholders' Equity - Attributable to Parent Shareholders - Total | B84: 99270 | C84: 114281
A85: Preferred Shareholders Equity | B85: 0 | C85: 0
A86: Preferred Stock - Non-Redeemable | B86: 0 | C86: 0
A87: Preferred Stock - Convertible - Non-Redeemable | B87: 0 | C87: 0
A88: Common Equity Attributable to Parent Shareholders | B88: 99270 | C88: 114281
A89: Common Equity - Contributed | B89: 50949 | C89: 65185
A90: Common Stock - Issued & Paid | B90: 4.33 | C90: 4.99
A91: Common Stock - Additional Paid in Capital including Option Reserve | B91: 50944.67 | C91: 65180.01
A92: Equity - Non-Contributed - Reserves & Retained Earnings | B92: 48321 | C92: 49096
A93: Retained Earnings - Total | B93: 49032 | C93: 48983
A94: Comprehensive Income - Accumulated - Total | B94: -711 | C94: 113
A95: Hedging Reserves | B95: -582 | C95: 161
... A99: Minority Interest - Equity | B99: 5762 | C99: 12079
A100: Total Shareholders' Equity
A101: Total Shareholders' Equity - including Minority Interest & Hybrid Debt | B101: 105032 | C101: 126360
A102: Total Liabilities & Shareholders' Equity
A103: Total Liabilities & Equity | B103: 196485 | C103: 211429
A104: Share/Per Share - Common
A105: Common Shares - Issued - Total | B105: 4330 | C105: 4994
A106: Common Shares - Outstanding - Total | B106: 4330 | C106: 4994
...

Sheet Broadcom
A1: Company Fundamentals - Balance Sheet
A2: Company Name | B2: Broadcom Inc (AVGO.OQ)
A3: Country of Exchange | B3: United States of America
A4: Country of Headquarters | B4: United States of America
A5: TRBC Industry Group | B5: Semiconductors & Semiconductor Equipment
A6: CF Template | B6: IND
A7: Consolidation Basis | B7: Consolidated
A8: Scaling | B8: Millions
A9: Period | B9: Annual
A10: Export Date | B10: 46295.603
A11: Statement Data | B11: 2024 | C11: 2025
A12: Period End Date | B12: 45599 | C12: 45963
A13: Standardized Currency | B13: USD | C13: USD
A14: Balance Sheet - Standardized (Currency: US Dollar)
A15: Field Name | B15: 02-11-2024 | C15: 01-11-2025
A16: Current Assets
A17: Cash & Short-Term Investments | B17: 9348 | C17: 16178
A18: Cash & Cash Equivalents | B18: 9348 | C18: 16178
A19: Loans & Receivables - Net - Short-Term | B19: 6332 | C19: 12150
A20: Trade Accounts & Trade Notes Receivable - Net | B20: 4416 | C20: 7145
A21: Receivables - Other - Total | B21: 1916 | C21: 5005
A22: Inventories - Total | B22: 1760 | C22: 2270
A23: Inventories - Raw Materials | B23: 286 | C23: 308
A24: Inventories - Work in Progress | B24: 970 | C24: 1280
A25: Inventories - Finished Goods | B25: 504 | C25: 682
A26: Prepaid Expenses - Short-Term | B26: 1391 | C26: 518
A27: Other Current Assets - Total | B27: 764 | C27: 457
A28: Other Current Assets | B28: 764 | C28: 457
A29: Total Current Assets | B29: 19595 | C29: 31573
A30: Non-Current Assets
A31: Property, Plant & Equipment - Net - Total | B31: 3846 | C31: 3848
A32: Property, Plant & Equipment - excluding Assets Leased Out - Net - Total | B32: 3846 | C32: 3848
A33: Property, Plant & Equipment - Gross - Total | B33: 8350 | C33: 8744
A34: Property, Plant & Equipment - excluding Assets Leased Out - Gross | B34: 8350 | C34: 8744
A35: Land & Buildings - Gross | B35: 1722 | C35: 1692
A36: Land/Improvements - Gross | B36: 204 | C36: 204
A37: Buildings - Gross | B37: 1518 | C37: 1488
A38: Plant, Machinery & Equipment - Gross | B38: 5246 | C38: 5656
A39: Construction in Progress - Gross | B39: 57 | C39: 78
A40: Right of Use Tangible Assets - Total - Gross | B40: 1325 | C40: 1318
A41: Right of Use Tangible Assets - Operating Lease - Gross | B41: 1325 | C41: 1318
A42: Property, Plant & Equipment - Accumulated Depreciation & Impairment - Total | B42: 4504 | C42: 4896
... A53: Total Non-Current Assets | B53: 146050 | C53: 139519
A54: Total Assets
A55: Total Assets | B55: 165645 | C55: 171092
A56: Current Liabilities
A57: Trade Accounts Payable & Accruals - Short-Term | B57: 3633 | C57: 3689
A58: Trade Accounts & Trade Notes Payable - Short-Term | B58: 1662 | C58: 1560
A59: Accrued Expenses - Short-Term | B59: 1971 | C59: 2129
A60: Short-Term Debt & Current Portion of Long-Term Debt | B60: 1271 | C60: 3152
A61: Current Portion of Long-Term Debt including Capitalized Leases | B61: 1271 | C61: 3152
A62: Current Portion of Long-Term Debt excluding Capitalized Leases | B62: 1245 | C62: 3152
A63: Capitalized Leases - Current Portion | B63: 26 | C63: 0
A64: Income Taxes - Payable - Short-Term | B64: 720 | C64: 921
A65: Operating Lease Liabilities - Current Portion/Short-Term | B65: 207 | C65: 144
A66: Other Current Liabilities - Total | B66: 10866 | C66: 10608
A67: Deferred Income - Short-Term | B67: 9395 | C67: 9469
A68: Other Current Liabilities | B68: 1471 | C68: 1139
A69: Total Current Liabilities | B69: 16697 | C69: 18514
A70: Non-Current Liabilities
A71: Accounts Payable including Accrued Expenses - Long-Term | B71: 3669 | C71: 1628
A72: Accrued Expenses - Long-Term | B72: 3669 | C72: 1628
A73: Debt - Long-Term - Total | B73: 66295 | C73: 61984
A74: Long-Term Debt excluding Capitalized Leases | B74: 66282 | C74: 61984
A75: Debt - Non-Convertible - Long-Term | B75: 66282 | C75: 61984
A76: Capitalized Lease Obligations - Long-Term | B76: 13 | C76: 0
A77: Deferred Tax & Investment Tax Credits - Long-Term | B77: 4703 | C77: 2704
A78: Deferred Tax - Liability - Long-Term | B78: 4703 | C78: 2704
A79: Operating Lease Liabilities - Long-Term | B79: 1143 | C79: 1181
A80: Other Non-Current Liabilities - Total | B80: 5460 | C80: 3789
A81: Deferred Revenue - Long-Term | B81: 5100 | C81: 3547
A82: Other Non-Current Liabilities | B82: 360 | C82: 242
A83: Total Non-Current Liabilities | B83: 81270 | C83: 71286
A84: Total Liabilities
A85: Total Liabilities | B85: 97967 | C85: 89800
A86: Shareholders' Equity
A87: Shareholders' Equity - Attributable to Parent Shareholders - Total | B87: 67678 | C87: 81292
A88: Preferred Shareholders Equity | B88: 0
A89: Preferred Stock - Redeemable - Total | B89: 0
A90: Common Equity Attributable to Parent Shareholders | B90: 67678 | C90: 81292
A91: Common Equity - Contributed | B91: 67471 | C91: 71313
A92: Common Stock - Issued & Paid | B92: 5 | C92: 5
A93: Common Stock - Additional Paid in Capital including Option Reserve | B93: 67466 | C93: 71308
A94: Equity - Non-Contributed - Reserves & Retained Earnings | B94: 207 | C94: 9979
A95: Retained Earnings - Total | B95: 0 | C95: 9761
A96: Comprehensive Income - Accumulated - Total | B96: 207 | C96: 218
A97: Common Equity - Total | B97: 67678 | C97: 81292
A98: Total Shareholders' Equity
A99: Total Shareholders' Equity - including Minority Interest & Hybrid Debt | B99: 67678 | C99: 81292
A100: Total Liabilities & Shareholders' Equity
A101: Total Liabilities & Equity | B101: 165645 | C101: 171092
A102: Share/Per Share - Common
